Workbook

Sheet Base
A2: Producto | B2: Unidad | C2: Masa drenada | D2: Costo bruto | E2: Costo neto | F2: Código
A3: . | B3: . | C3: . | D3: . | E3: 0 | F3: 0
A4: ='Almacén '!B4 -> Producto | B4: ='Almacén '!D5 -> Kg | C4: ='Almacén '!F5 -> 1 | D4: ='Almacén '!G5 -> 24 | E4: ='Almacén '!H5 -> 24 | F4: ='Almacén '!A5 -> ABA-001
A5: ='Almacén '!B5 -> Azucár | B5: ='Almacén '!D6 -> Kg | C5: ='Almacén '!F6 -> 1 | D5: ='Almacén '!G6 -> 30 | E5: ='Almacén '!H6 -> 30 | F5: ='Almacén '!A6 -> ABA-002
A6: ='Almacén '!B7 -> Canela en polvo | B6: ='Almacén '!D7 -> Kg | C6: ='Almacén '!F7 -> 1 | D6: ='Almacén '!G7 -> 50 | E6: ='Almacén '!H7 -> 50 | F6: ='Almacén '!A7 -> ABA-003
A7: ='Almacén '!B8 | B7: ='Almacén '!D8 | C7: ='Almacén '!F8 -> 1 | D7: ='Almacén '!G8 | E7: ='Almacén '!H8 -> 0 | F7: ='Almacén '!A8 -> ABA-004
A8: ='Almacén '!B9 | B8: ='Almacén '!D9 | C8: ='Almacén '!F9 -> 1 | D8: ='Almacén '!G9 | E8: ='Almacén '!H9 -> 0 | F8: ='Almacén '!A9 -> ABA-005
A9: ='Almacén '!B10 | B9: ='Almacén '!D10 | C9: ='Almacén '!F10 -> 1 | D9: ='Almacén '!G10 | E9: ='Almacén '!H10 -> 0 | F9: ='Almacén '!A10 -> ABA-006
A10: ='Almacén '!B11 | B10: ='Almacén '!D11 | C10: ='Almacén '!F11 -> 1 | D10: ='Almacén '!G11 | E10: ='Almacén '!H11 -> 0 | F10: ='Almacén '!A11 -> ABA-007
A11: ='Almacén '!B12 | B11: ='Almacén '!D12 | C11: ='Almacén '!F12 -> 1 | D11: ='Almacén '!G12 | E11: ='Almacén '!H12 -> 0 | F11: ='Almacén '!A12 -> ABA-008
A12: ='Almacén '!B13 | B12: ='Almacén '!D13 | C12: ='Almacén '!F13 -> 1 | D12: ='Almacén '!G13 | E12: ='Almacén '!H13 -> 0 | F12: ='Almacén '!A13 -> ABA-009
A13: ='Almacén '!B14 | B13: ='Almacén '!D14 | C13: ='Almacén '!F14 -> 1 | D13: ='Almacén '!G14 | E13: ='Almacén '!H14 -> 0 | F13: ='Almacén '!A14 -> ABA-010
A14: ='Almacén '!B15 | B14: ='Almacén '!D15 | C14: ='Almacén '!F15 -> 1 | D14: ='Almacén '!G15 | E14: ='Almacén '!H15 -> 0 | F14: ='Almacén '!A15 -> ABA-011
A15: ='Almacén '!B16 | B15: ='Almacén '!D16 | C15: ='Almacén '!F16 -> 1 | D15: ='Almacén '!G16 | E15: ='Almacén '!H16 -> 0 | F15: ='Almacén '!A16 -> ABA-012
A16: ='Almacén '!B17 | B16: ='Almacén '!D17 | C16: ='Almacén '!F17 -> 1 | D16: ='Almacén '!G17 | E16: ='Almacén '!H17 -> 0 | F16: ='Almacén '!A17 -> ABA-013
A17: ='Almacén '!B18 | B17: ='Almacén '!D18 | C17: ='Almacén '!F18 -> 1 | D17: ='Almacén '!G18 | E17: ='Almacén '!H18 -> 0 | F17: ='Almacén '!A18 -> ABA-014
... A103: ='Almacén '!B104 | B103: ='Almacén '!D104 | C103: ='Almacén '!F104 -> 1 | D103: ='Almacén '!G104 | E103: ='Almacén '!H104 -> 0 | F103: ='Almacén '!A104 -> ABA-100
A104: ='Almacén '!B108 | B104: ='Almacén '!D108 | C104: ='Almacén '!G108 -> 1 | D104: ='Almacén '!H108 | E104: ='Almacén '!I108 -> 0 | F104: ='Almacén '!A108 -> FYV-001
A105: ='Almacén '!B109 | B105: ='Almacén '!D109 | C105: ='Almacén '!G109 -> 1 | D105: ='Almacén '!H109 | E105: ='Almacén '!I109 -> 0 | F105: ='Almacén '!A109 -> FYV-002
A106: ='Almacén '!B110 | B106: ='Almacén '!D110 | C106: ='Almacén '!G110 -> 1 | D106: ='Almacén '!H110 | E106: ='Almacén '!I110 -> 0 | F106: ='Almacén '!A110 -> FYV-003
A107: ='Almacén '!B111 | B107: ='Almacén '!D111 | C107: ='Almacén '!G111 -> 1 | D107: ='Almacén '!H111 | E107: ='Almacén '!I111 -> 0 | F107: ='Almacén '!A111 -> FYV-004
A108: ='Almacén '!B112 | B108: ='Almacén '!D112 | C108: ='Almacén '!G112 -> 1 | D108: ='Almacén '!H112 | E108: ='Almacén '!I112 -> 0 | F108: ='Almacén '!A112 -> FYV-005
A109: ='Almacén '!B113 | B109: ='Almacén '!D113 | C109: ='Almacén '!G113 -> 1 | D109: ='Almacén '!H113 | E109: ='Almacén '!I113 -> 0 | F109: ='Almacén '!A113 -> FYV-006
A110: ='Almacén '!B114 | B110: ='Almacén '!D114 | C110: ='Almacén '!G114 -> 1 | D110: ='Almacén '!H114 | E110: ='Almacén '!I114 -> 0 | F110: ='Almacén '!A114 -> FYV-007
A111: ='Almacén '!B115 | B111: ='Almacén '!D115 | C111: ='Almacén '!G115 -> 1 | D111: ='Almacén '!H115 | E111: ='Almacén '!I115 -> 0 | F111: ='Almacén '!A115 -> FYV-008
A112: ='Almacén '!B116 | B112: ='Almacén '!D116 | C112: ='Almacén '!G116 -> 1 | D112: ='Almacén '!H116 | E112: ='Almacén '!I116 -> 0 | F112: ='Almacén '!A116 -> FYV-009
A113: ='Almacén '!B117 | B113: ='Almacén '!D117 | C113: ='Almacén '!G117 -> 1 | D113: ='Almacén '!H117 | E113: ='Almacén '!I117 -> 0 | F113: ='Almacén '!A117 -> FYV-010
A114: ='Almacén '!B118 | B114: ='Almacén '!D118 | C114: ='Almacén '!G118 -> 1 | D114: ='Almacén '!H118 | E114: ='Almacén '!I118 -> 0 | F114: ='Almacén '!A118 -> FYV-011
A115: ='Almacén '!B119 | B115: ='Almacén '!D119 | C115: ='Almacén '!G119 -> 1 | D115: ='Almacén '!H119 | E115: ='Almacén '!I119 -> 0 | F115: ='Almacén '!A119 -> FYV-012
... A203: ='Almacén '!B207 | B203: ='Almacén '!D207 | C203: ='Almacén '!G207 -> 1 | D203: ='Almacén '!H207 | E203: ='Almacén '!I207 -> 0 | F203: ='Almacén '!A207 -> FYV-100
A204: ='Almacén '!B212 | B204: ='Almacén '!D212 | C204: ='Almacén '!G212 -> 1 | D204: ='Almacén '!H212 | E204: ='Almacén '!I212 -> 0 | F204: ='Almacén '!A212 -> RES-001
A205: ='Almacén '!B213 | B205: ='Almacén '!D213 | C205: ='Almacén '!G213 -> 1 | D205: ='Almacén '!H213 | E205: ='Almacén '!I213 -> 0 | F205: ='Almacén '!A213 -> RES-002
A206: ='Almacén '!B214 | B206: ='Almacén '!D214 | C206: ='Almacén '!G214 -> 1 | D206: ='Almacén '!H214 | E206: ='Almacén '!I214 -> 0 | F206: ='Almacén '!A214 -> RES-003
A207: ='Almacén '!B215 | B207: ='Almacén '!D215 | C207: ='Almacén '!G215 -> 1 | D207: ='Almacén '!H215 | E207: ='Almacén '!I215 -> 0 | F207: ='Almacén '!A215 -> RES-004
A208: ='Almacén '!B216 | B208: ='Almacén '!D216 | C208: ='Almacén '!G216 -> 1 | D208: ='Almacén '!H216 | E208: ='Almacén '!I216 -> 0 | F208: ='Almacén '!A216 -> RES-005
A209: ='Almacén '!B217 | B209: ='Almacén '!D217 | C209: ='Almacén '!G217 -> 1 | D209: ='Almacén '!H217 | E209: ='Almacén '!I217 -> 0 | F209: ='Almacén '!A217 -> RES-006
A210: ='Almacén '!B218 | B210: ='Almacén '!D218 | C210: ='Almacén '!G218 -> 1 | D210: ='Almacén '!H218 | E210: ='Almacén '!I218 -> 0 | F210: ='Almacén '!A218 -> RES-007
A211: ='Almacén '!B219 | B211: ='Almacén '!D219 | C211: ='Almacén '!G219 -> 1 | D211: ='Almacén '!H219 | E211: ='Almacén '!I219 -> 0 | F211: ='Almacén '!A219 -> RES-008
A212: ='Almacén '!B220 | B212: ='Almacén '!D220 | C212: ='Almacén '!G220 -> 1 | D212: ='Almacén '!H220 | E212: ='Almacén '!I220 -> 0 | F212: ='Almacén '!A220 -> RES-009
A213: ='Almacén '!B221 | B213: ='Almacén '!D221 | C213: ='Almacén '!G221 -> 1 | D213: ='Almacén '!H221 | E213: ='Almacén '!I221 -> 0 | F213: ='Almacén '!A221 -> RES-010
A214: ='Almacén '!B223 | B214: ='Almacén '!D223 | C214: ='Almacén '!G223 -> 1 | D214: ='Almacén '!H223 | E214: ='Almacén '!I223 -> 0 | F214: ='Almacén '!A223 -> CER-001
A215: ='Almacén '!B224 | B215: ='Almacén '!D224 | C215: ='Almacén '!G224 -> 1 | D215: ='Almacén '!H224 | E215: ='Almacén '!I224 -> 0 | F215: ='Almacén '!A224 -> CER-002
A216: ='Almacén '!B225 | B216: ='Almacén '!D225 | C216: ='Almacén '!G225 -> 1 | D216: ='Almacén '!H225 | E216: ='Almacén '!I225 -> 0 | F216: ='Almacén '!A225 -> CER-003
A217: ='Almacén '!B226 | B217: ='Almacén '!D226 | C217: ='Almacén '!G226 -> 1 | D217: ='Almacén '!H226 | E217: ='Almacén '!I226 -> 0 | F217: ='Almacén '!A226 -> CER-004
A218: ='Almacén '!B227 | B218: ='Almacén '!D227 | C218: ='Almacén '!G227 -> 1 | D218: ='Almacén '!H227 | E218: ='Almacén '!I227 -> 0 | F218: ='Almacén '!A227 -> CER-005
A219: ='Almacén '!B228 | B219: ='Almacén '!D228 | C219: ='Almacén '!G228 -> 1 | D219: ='Almacén '!H228 | E219: ='Almacén '!I228 -> 0 | F219: ='Almacén '!A228 -> CER-006
A220: ='Almacén '!B229 | B220: ='Almacén '!D229 | C220: ='Almacén '!G229 -> 1 | D220: ='Almacén '!H229 | E220: ='Almacén '!I229 -> 0 | F220: ='Almacén '!A229 -> CER-007
A221: ='Almacén '!B230 | B221: ='Almacén '!D230 | C221: ='Almacén '!G230 -> 1 | D221: ='Almacén '!H230 | E221: ='Almacén '!I230 -> 0 | F221: ='Almacén '!A230 -> CER-008
A222: ='Almacén '!B231 | B222: ='Almacén '!D231 | C222: ='Almacén '!G231 -> 1 | D222: ='Almacén '!H231 | E222: ='Almacén '!I231 -> 0 | F222: ='Almacén '!A231 -> CER-009
A223: ='Almacén '!B232 | B223: ='Almacén '!D232 | C223: ='Almacén '!G232 -> 1 | D223: ='Almacén '!H232 | E223: ='Almacén '!I232 -> 0 | F223: ='Almacén '!A232 -> CER-010
A224: ='Almacén '!B234 | B224: ='Almacén '!D234 | C224: ='Almacén '!G234 -> 1 | D224: ='Almacén '!H234 | E224: ='Almacén '!I234 -> 0 | F224: ='Almacén '!A234 -> AVE-001
A225: ='Almacén '!B235 | B225: ='Almacén '!D235 | C225: ='Almacén '!G235 -> 1 | D225: ='Almacén '!H235 | E225: ='Almacén '!I235 -> 0 | F225: ='Almacén '!A235 -> AVE-002
A226: ='Almacén '!B236 | B226: ='Almacén '!D236 | C226: ='Almacén '!G236 -> 1 | D226: ='Almacén '!H236 | E226: ='Almacén '!I236 -> 0 | F226: ='Almacén '!A236 -> AVE-003
A227: ='Almacén '!B237 | B227: ='Almacén '!D237 | C227: ='Almacén '!G237 -> 1 | D227: ='Almacén '!H237 | E227: ='Almacén '!I237 -> 0 | F227: ='Almacén '!A237 -> AVE-004
A228: ='Almacén '!B238 | B228: ='Almacén '!D238 | C228: ='Almacén '!G238 -> 1 | D228: ='Almacén '!H238 | E228: ='Almacén '!I238 -> 0 | F228: ='Almacén '!A238 -> AVE-005
A229: ='Almacén '!B239 | B229: ='Almacén '!D239 | C229: ='Almacén '!G239 -> 1 | D229: ='Almacén '!H239 | E229: ='Almacén '!I239 -> 0 | F229: ='Almacén '!A239 -> AVE-006
A230: ='Almacén '!B240 | B230: ='Almacén '!D240 | C230: ='Almacén '!G240 -> 1 | D230: ='Almacén '!H240 | E230: ='Almacén '!I240 -> 0 | F230: ='Almacén '!A240 -> AVE-007
A231: ='Almacén '!B241 | B231: ='Almacén '!D241 | C231: ='Almacén '!G241 -> 1 | D231: ='Almacén '!H241 | E231: ='Almacén '!I241 -> 0 | F231: ='Almacén '!A241 -> AVE-008
A232: ='Almacén '!B242 | B232: ='Almacén '!D242 | C232: ='Almacén '!G242 -> 1 | D232: ='Almacén '!H242 | E232: ='Almacén '!I242 -> 0 | F232: ='Almacén '!A242 -> AVE-009
A233: ='Almacén '!B243 | B233: ='Almacén '!D243 | C233: ='Almacén '!G243 -> 1 | D233: ='Almacén '!H243 | E233: ='Almacén '!I243 -> 0 | F233: ='Almacén '!A243 -> AVE-010
A234: ='Almacén '!B245 | B234: ='Almacén '!D245 | C234: ='Almacén '!G245 -> 1 | D234: ='Almacén '!H245 | E234: ='Almacén '!I245 -> 0 | F234: ='Almacén '!A245 -> PYM-001
A235: ='Almacén '!B246 | B235: ='Almacén '!D246 | C235: ='Almacén '!G246 -> 1 | D235: ='Almacén '!H246 | E235: ='Almacén '!I246 -> 0 | F235: ='Almacén '!A246 -> PYM-002
A236: ='Almacén '!B247 | B236: ='Almacén '!D247 | C236: ='Almacén '!G247 -> 1 | D236: ='Almacén '!H247 | E236: ='Almacén '!I247 -> 0 | F236: ='Almacén '!A247 -> PYM-003
A237: ='Almacén '!B248 | B237: ='Almacén '!D248 | C237: ='Almacén '!G248 -> 1 | D237: ='Almacén '!H248 | E237: ='Almacén '!I248 -> 0 | F237: ='Almacén '!A248 -> PYM-004
A238: ='Almacén '!B249 | B238: ='Almacén '!D249 | C238: ='Almacén '!G249 -> 1 | D238: ='Almacén '!H249 | E238: ='Almacén '!I249 -> 0 | F238: ='Almacén '!A249 -> PYM-005
A239: ='Almacén '!B250 | B239: ='Almacén '!D250 | C239: ='Almacén '!G250 -> 1 | D239: ='Almacén '!H250 | E239: ='Almacén '!I250 -> 0 | F239: ='Almacén '!A250 -> PYM-006
A240: ='Almacén '!B251 | B240: ='Almacén '!D251 | C240: ='Almacén '!G251 -> 1 | D240: ='Almacén '!H251 | E240: ='Almacén '!I251 -> 0 | F240: ='Almacén '!A251 -> PYM-007
A241: ='Almacén '!B252 | B241: ='Almacén '!D252 | C241: ='Almacén '!G252 -> 1 | D241: ='Almacén '!H252 | E241: ='Almacén '!I252 -> 0 | F241: ='Almacén '!A252 -> PYM-008
A242: ='Almacén '!B253 | B242: ='Almacén '!D253 | C242: ='Almacén '!G253 -> 1 | D242: ='Almacén '!H253 | E242: ='Almacén '!I253 -> 0 | F242: ='Almacén '!A253 -> PYM-009
A243: ='Almacén '!B254 | B243: ='Almacén '!D254 | C243: ='Almacén '!G254 -> 1 | D243: ='Almacén '!H254 | E243: ='Almacén '!I254 -> 0 | F243: ='Almacén '!A254 -> PYM-010
A244: ='Almacén '!B256 | B244: ='Almacén '!D256 | C244: ='Almacén '!G256 -> 1 | D244: ='Almacén '!H256 | E244: ='Almacén '!I256 -> 0 | F244: ='Almacén '!A256 -> ADC-001
A245: ='Almacén '!B257 | B245: ='Almacén '!D257 | C245: ='Almacén '!G257 -> 1 | D245: ='Almacén '!H257 | E245: ='Almacén '!I257 -> 0 | F245: ='Almacén '!A257 -> ADC-002
A246: ='Almacén '!B258 | B246: ='Almacén '!D258 | C246: ='Almacén '!G258 -> 1 | D246: ='Almacén '!H258 | E246: ='Almacén '!I258 -> 0 | F246: ='Almacén '!A258 -> ADC-003
A247: ='Almacén '!B259 | B247: ='Almacén '!D259 | C247: ='Almacén '!G259 -> 1 | D247: ='Almacén '!H259 | E247: ='Almacén '!I259 -> 0 | F247: ='Almacén '!A259 -> ADC-004
A248: ='Almacén '!B260 | B248: ='Almacén '!D260 | C248: ='Almacén '!G260 -> 1 | D248: ='Almacén '!H260 | E248: ='Almacén '!I260 -> 0 | F248: ='Almacén '!A260 -> ADC-005
A249: ='Almacén '!B261 | B249: ='Almacén '!D261 | C249: ='Almacén '!G261 -> 1 | D249: ='Almacén '!H261 | E249: ='Almacén '!I261 -> 0 | F249: ='Almacén '!A261 -> ADC-006
A250: ='Almacén '!B262 | B250: ='Almacén '!D262 | C250: ='Almacén '!G262 -> 1 | D250: ='Almacén '!H262 | E250: ='Almacén '!I262 -> 0 | F250: ='Almacén '!A262 -> ADC-007
A251: ='Almacén '!B263 | B251: ='Almacén '!D263 | C251: ='Almacén '!G263 -> 1 | D251: ='Almacén '!H263 | E251: ='Almacén '!I263 -> 0 | F251: ='Almacén '!A263 -> ADC-008
A252: ='Almacén '!B264 | B252: ='Almacén '!D264 | C252: ='Almacén '!G264 -> 1 | D252: ='Almacén '!H264 | E252: ='Almacén '!I264 -> 0 | F252: ='Almacén '!A264 -> ADC-009
A253: ='Almacén '!B265 | B253: ='Almacén '!D265 | C253: ='Almacén '!G265 -> 1 | D253: ='Almacén '!H265 | E253: ='Almacén '!I265 -> 0 | F253: ='Almacén '!A265 -> ADC-010
A254: ='Almacén '!B267 | B254: ='Almacén '!D267 | C254: ='Almacén '!G267 -> 1 | D254: ='Almacén '!H267 | E254: ='Almacén '!I267 -> 0 | F254: ='Almacén '!A267
A255: ='Almacén '!B268 | B255: ='Almacén '!D268 | C255: ='Almacén '!G268 -> 1 | D255: ='Almacén '!H268 | E255: ='Almacén '!I268 -> 0 | F255: ='Almacén '!A268
A256: ='Almacén '!B269 | B256: ='Almacén '!D269 | C256: ='Almacén '!G269 -> 1 | D256: ='Almacén '!H269 | E256: ='Almacén '!I269 -> 0 | F256: ='Almacén '!A269
A257: ='Almacén '!B270 | B257: ='Almacén '!D270 | C257: ='Almacén '!G270 -> 1 | D257: ='Almacén '!H270 | E257: ='Almacén '!I270 -> 0 | F257: ='Almacén '!A270
A258: ='Almacén '!B271 | B258: ='Almacén '!D271 | C258: ='Almacén '!G271 -> 1 | D258: ='Almacén '!H271 | E258: ='Almacén '!I271 -> 0 | F258: ='Almacén '!A271
A259: ='Almacén '!B272 | B259: ='Almacén '!D272 | C259: ='Almacén '!G272 -> 1 | D259: ='Almacén '!H272 | E259: ='Almacén '!I272 -> 0 | F259: ='Almacén '!A272
A260: ='Almacén '!B273 | B260: ='Almacén '!D273 | C260: ='Almacén '!G273 -> 1 | D260: ='Almacén '!H273 | E260: ='Almacén '!I273 -> 0 | F260: ='Almacén '!A273
A261: ='Almacén '!B274 | B261: ='Almacén '!D274 | C261: ='Almacén '!G274 -> 1 | D261: ='Almacén '!H274 | E261: ='Almacén '!I274 -> 0 | F261: ='Almacén '!A274
A262: ='Almacén '!B275 | B262: ='Almacén '!D275 | C262: ='Almacén '!G275 -> 1 | D262: ='Almacén '!H275 | E262: ='Almacén '!I275 -> 0 | F262: ='Almacén '!A275
A263: ='Almacén '!B276 | B263: ='Almacén '!D276 | C263: ='Almacén '!G276 -> 1 | D263: ='Almacén '!H276 | E263: ='Almacén '!I276 -> 0 | F263: ='Almacén '!A276
A264: ='Almacén '!B278 | B264: ='Almacén '!D278 | C264: ='Almacén '!G278 -> 1 | D264: ='Almacén '!H278 | E264: ='Almacén '!I278 -> 0 | F264: ='Almacén '!A278
A265: ='Almacén '!B279 | B265: ='Almacén '!D279 | C265: ='Almacén '!G279 -> 1 | D265: ='Almacén '!H279 | E265: ='Almacén '!I279 -> 0 | F265: ='Almacén '!A279
A266: ='Almacén '!B280 | B266: ='Almacén '!D280 | C266: ='Almacén '!G280 -> 1 | D266: ='Almacén '!H280 | E266: ='Almacén '!I280 -> 0 | F266: ='Almacén '!A280
A267: ='Almacén '!B281 | B267: ='Almacén '!D281 | C267: ='Almacén '!G281 -> 1 | D267: ='Almacén '!H281 | E267: ='Almacén '!I281 -> 0 | F267: ='Almacén '!A281
A268: ='Almacén '!B282 | B268: ='Almacén '!D282 | C268: ='Almacén '!G282 -> 1 | D268: ='Almacén '!H282 | E268: ='Almacén '!I282 -> 0 | F268: ='Almacén '!A282
A269: ='Almacén '!B283 | B269: ='Almacén '!D283 | C269: ='Almacén '!G283 -> 1 | D269: ='Almacén '!H283 | E269: ='Almacén '!I283 -> 0 | F269: ='Almacén '!A283
A270: ='Almacén '!B284 | B270: ='Almacén '!D284 | C270: ='Almacén '!G284 -> 1 | D270: ='Almacén '!H284 | E270: ='Almacén '!I284 -> 0 | F270: ='Almacén '!A284
A271: ='Almacén '!B285 | B271: ='Almacén '!D285 | C271: ='Almacén '!G285 -> 1 | D271: ='Almacén '!H285 | E271: ='Almacén '!I285 -> 0 | F271: ='Almacén '!A285
A272: ='Almacén '!B286 | B272: ='Almacén '!D286 | C272: ='Almacén '!G286 -> 1 | D272: ='Almacén '!H286 | E272: ='Almacén '!I286 -> 0 | F272: ='Almacén '!A286
A273: ='Almacén '!B287 | B273: ='Almacén '!D287 | C273: ='Almacén '!G287 | D273: ='Almacén '!H287 | E273: ='Almacén '!I287 | F273: ='Almacén '!A287
...

Sheet Almacén 
A1: NOMBRE DEL ESTABLECIMIENTO
I2: Inventario físico | J2: Inventario Teorico | K2: Maximo | L2: Minimo
A3: Almacén de Abarrotes y secos
A4: Código | B4: Producto | C4: Marca o proveedor | D4: Unidad | E4: Presentación de compra | F4: Masa drenada | G4: Costo Bruto | H4: Costo neto
A5: ABA-001 | B5: Azucár | C5: Morena | D5: Kg | E5: 1 | F5: 1 | G5: 24 | H5: =(G5/F5) -> 24 | I5: 50 | J5: 55 | K5: 45 | L5: 10
A6: ABA-002 | B6: Acido Citrico | C6: Citricos | D6: Kg | E6: 1 | F6: 1 | G6: 30 | H6: =(G6/F6) -> 30
A7: ABA-003 | B7: Canela en polvo | C7: Moderna | D7: Kg | E7: 1 | F7: 1 | G7: 50 | H7: =(G7/F7) -> 50
A8: ABA-004 | E8: 1 | F8: 1 | H8: =(G8/F8) -> 0
A9: ABA-005 | E9: 1 | F9: 1 | H9: =(G9/F9) -> 0
A10: ABA-006 | E10: 1 | F10: 1 | H10: =(G10/F10) -> 0
A11: ABA-007 | E11: 1 | F11: 1 | H11: =(G11/F11) -> 0
A12: ABA-008 | E12: 1 | F12: 1 | H12: =(G12/F12) -> 0
A13: ABA-009 | E13: 1 | F13: 1 | H13: =(G13/F13) -> 0
A14: ABA-010 | E14: 1 | F14: 1 | H14: =(G14/F14) -> 0
A15: ABA-011 | E15: 1 | F15: 1 | H15: =(G15/F15) -> 0
A16: ABA-012 | E16: 1 | F16: 1 | H16: =(G16/F16) -> 0
A17: ABA-013 | E17: 1 | F17: 1 | H17: =(G17/F17) -> 0
A18: ABA-014 | E18: 1 | F18: 1 | H18: =(G18/F18) -> 0
A19: ABA-015 | E19: 1 | F19: 1 | H19: =(G19/F19) -> 0
... A104: ABA-100 | E104: 1 | F104: 1 | H104: =(G104/F104) -> 0
A106: Almacén de Frutas y Verduras
A107: Código | B107: Producto | C107: Marca o proveedor | D107: Unidad | E107: % Merma | F107: Utilizable | G107: Peso neto | H107: Costo bruto | I107: Costo neto
A108: FYV-001 | F108: =100-E108 -> 100 | G108: =F108/100 -> 1 | I108: =H108/G108 -> 0
A109: FYV-002 | F109: =100-E109 -> 100 | G109: =F109/100 -> 1 | I109: =H109/G109 -> 0
A110: FYV-003 | F110: =100-E110 -> 100 | G110: =F110/100 -> 1 | I110: =H110/G110 -> 0
A111: FYV-004 | F111: =100-E111 -> 100 | G111: =F111/100 -> 1 | I111: =H111/G111 -> 0
A112: FYV-005 | F112: =100-E112 -> 100 | G112: =F112/100 -> 1 | I112: =H112/G112 -> 0
A113: FYV-006 | F113: =100-E113 -> 100 | G113: =F113/100 -> 1 | I113: =H113/G113 -> 0
A114: FYV-007 | F114: =100-E114 -> 100 | G114: =F114/100 -> 1 | I114: =H114/G114 -> 0
A115: FYV-008 | F115: =100-E115 -> 100 | G115: =F115/100 -> 1 | I115: =H115/G115 -> 0
A116: FYV-009 | F116: =100-E116 -> 100 | G116: =F116/100 -> 1 | I116: =H116/G116 -> 0
A117: FYV-010 | F117: =100-E117 -> 100 | G117: =F117/100 -> 1 | I117: =H117/G117 -> 0
A118: FYV-011 | F118: =100-E118 -> 100 | G118: =F118/100 -> 1 | I118: =H118/G118 -> 0
A119: FYV-012 | F119: =100-E119 -> 100 | G119: =F119/100 -> 1 | I119: =H119/G119 -> 0
... A207: FYV-100 | F207: =100-E207 -> 100 | G207: =F207/100 -> 1 | I207: =H207/G207 -> 0
A209: Almacén de cárnicos (res, cerdo, aves, pescados, mariscos, animales de caza, etc.)
A210: Código | B210: Producto | C210: Marca o proveedor | D210: Unidad | E210: % Merma | F210: Utilizable | G210: Peso neto | H210: Costo bruto | I210: Costo neto
B211: Res
A212: RES-001 | F212: =100-E212 -> 100 | G212: =F212/100 -> 1 | I212: =H212/G212 -> 0
A213: RES-002 | F213: =100-E213 -> 100 | G213: =F213/100 -> 1 | I213: =H213/G213 -> 0
A214: RES-003 | F214: =100-E214 -> 100 | G214: =F214/100 -> 1 | I214: =H214/G214 -> 0
A215: RES-004 | F215: =100-E215 -> 100 | G215: =F215/100 -> 1 | I215: =H215/G215 -> 0
A216: RES-005 | F216: =100-E216 -> 100 | G216: =F216/100 -> 1 | I216: =H216/G216 -> 0
A217: RES-006 | F217: =100-E217 -> 100 | G217: =F217/100 -> 1 | I217: =H217/G217 -> 0
A218: RES-007 | F218: =100-E218 -> 100 | G218: =F218/100 -> 1 | I218: =H218/G218 -> 0
A219: RES-008 | F219: =100-E219 -> 100 | G219: =F219/100 -> 1 | I219: =H219/G219 -> 0
A220: RES-009 | F220: =100-E220 -> 100 | G220: =F220/100 -> 1 | I220: =H220/G220 -> 0
A221: RES-010 | F221: =100-E221 -> 100 | G221: =F221/100 -> 1 | I221: =H221/G221 -> 0
B222: Cerdo
A223: CER-001 | F223: =100-E223 -> 100 | G223: =F223/100 -> 1 | I223: =H223/G223 -> 0
A224: CER-002 | F224: =100-E224 -> 100 | G224: =F224/100 -> 1 | I224: =H224/G224 -> 0
A225: CER-003 | F225: =100-E225 -> 100 | G225: =F225/100 -> 1 | I225: =H225/G225 -> 0
A226: CER-004 | F226: =100-E226 -> 100 | G226: =F226/100 -> 1 | I226: =H226/G226 -> 0
A227: CER-005 | F227: =100-E227 -> 100 | G227: =F227/100 -> 1 | I227: =H227/G227 -> 0
A228: CER-006 | F228: =100-E228 -> 100 | G228: =F228/100 -> 1 | I228: =H228/G228 -> 0
A229: CER-007 | F229: =100-E229 -> 100 | G229: =F229/100 -> 1 | I229: =H229/G229 -> 0
A230: CER-008 | F230: =100-E230 -> 100 | G230: =F230/100 -> 1 | I230: =H230/G230 -> 0
A231: CER-009 | F231: =100-E231 -> 100 | G231: =F231/100 -> 1 | I231: =H231/G231 -> 0
A232: CER-010 | F232: =100-E232 -> 100 | G232: =F232/100 -> 1 | I232: =H232/G232 -> 0
B233: Aves
A234: AVE-001 | F234: =100-E234 -> 100 | G234: =F234/100 -> 1 | I234: =H234/G234 -> 0
A235: AVE-002 | F235: =100-E235 -> 100 | G235: =F235/100 -> 1 | I235: =H235/G235 -> 0
A236: AVE-003 | F236: =100-E236 -> 100 | G236: =F236/100 -> 1 | I236: =H236/G236 -> 0
A237: AVE-004 | F237: =100-E237 -> 100 | G237: =F237/100 -> 1 | I237: =H237/G237 -> 0
A238: AVE-005 | F238: =100-E238 -> 100 | G238: =F238/100 -> 1 | I238: =H238/G238 -> 0
A239: AVE-006 | F239: =100-E239 -> 100 | G239: =F239/100 -> 1 | I239: =H239/G239 -> 0
A240: AVE-007 | F240: =100-E240 -> 100 | G240: =F240/100 -> 1 | I240: =H240/G240 -> 0
A241: AVE-008 | F241: =100-E241 -> 100 | G241: =F241/100 -> 1 | I241: =H241/G241 -> 0
A242: AVE-009 | F242: =100-E242 -> 100 | G242: =F242/100 -> 1 | I242: =H242/G242 -> 0
A243: AVE-010 | F243: =100-E243 -> 100 | G243: =F243/100 -> 1 | I243: =H243/G243 -> 0
B244: Pescados y mariscos
A245: PYM-001 | F245: =100-E245 -> 100 | G245: =F245/100 -> 1 | I245: =H245/G245 -> 0
A246: PYM-002 | F246: =100-E246 -> 100 | G246: =F246/100 -> 1 | I246: =H246/G246 -> 0
A247: PYM-003 | F247: =100-E247 -> 100 | G247: =F247/100 -> 1 | I247: =H247/G247 -> 0
A248: PYM-004 | F248: =100-E248 -> 100 | G248: =F248/100 -> 1 | I248: =H248/G248 -> 0
A249: PYM-005 | F249: =100-E249 -> 100 | G249: =F249/100 -> 1 | I249: =H249/G249 -> 0
A250: PYM-006 | F250: =100-E250 -> 100 | G250: =F250/100 -> 1 | I250: =H250/G250 -> 0
A251: PYM-007 | F251: =100-E251 -> 100 | G251: =F251/100 -> 1 | I251: =H251/G251 -> 0
A252: PYM-008 | F252: =100-E252 -> 100 | G252: =F252/100 -> 1 | I252: =H252/G252 -> 0
A253: PYM-009 | F253: =100-E253 -> 100 | G253: =F253/100 -> 1 | I253: =H253/G253 -> 0
A254: PYM-010 | F254: =100-E254 -> 100 | G254: =F254/100 -> 1 | I254: =H254/G254 -> 0
B255: Animales de caza
A256: ADC-001 | F256: =100-E256 -> 100 | G256: =F256/100 -> 1 | I256: =H256/G256 -> 0
A257: ADC-002 | F257: =100-E257 -> 100 | G257: =F257/100 -> 1 | I257: =H257/G257 -> 0
A258: ADC-003 | F258: =100-E258 -> 100 | G258: =F258/100 -> 1 | I258: =H258/G258 -> 0
A259: ADC-004 | F259: =100-E259 -> 100 | G259: =F259/100 -> 1 | I259: =H259/G259 -> 0
A260: ADC-005 | F260: =100-E260 -> 100 | G260: =F260/100 -> 1 | I260: =H260/G260 -> 0
A261: ADC-006 | F261: =100-E261 -> 100 | G261: =F261/100 -> 1 | I261: =H261/G261 -> 0
A262: ADC-007 | F262: =100-E262 -> 100 | G262: =F262/100 -> 1 | I262: =H262/G262 -> 0
A263: ADC-008 | F263: =100-E263 -> 100 | G263: =F263/100 -> 1 | I263: =H263/G263 -> 0
A264: ADC-009 | F264: =100-E264 -> 100 | G264: =F264/100 -> 1 | I264: =H264/G264 -> 0
A265: ADC-010 | F265: =100-E265 -> 100 | G265: =F265/100 -> 1 | I265: =H265/G265 -> 0
F267: =100-E267 -> 100 | G267: =F267/100 -> 1 | I267: =H267/G267 -> 0
F268: =100-E268 -> 100 | G268: =F268/100 -> 1 | I268: =H268/G268 -> 0
F269: =100-E269 -> 100 | G269: =F269/100 -> 1 | I269: =H269/G269 -> 0
F270: =100-E270 -> 100 | G270: =F270/100 -> 1 | I270: =H270/G270 -> 0
F271: =100-E271 -> 100 | G271: =F271/100 -> 1 | I271: =H271/G271 -> 0
F272: =100-E272 -> 100 | G272: =F272/100 -> 1 | I272: =H272/G272 -> 0
F273: =100-E273 -> 100 | G273: =F273/100 -> 1 | I273: =H273/G273 -> 0
F274: =100-E274 -> 100 | G274: =F274/100 -> 1 | I274: =H274/G274 -> 0
...

Sheet SUBRECETAS Y GUARNICIONES
A1: NOMBRE DEL ESTABLECIMIENTO
A2: SUB-RECETAS | L2: GUARNICIONES
A4: NOMBRE: | F4: FECHA: | L4: NOMBRE: | Q4: FECHA: | R4: =$G$4 | W4: NOMBRE: | AB4: FECHA: | AC4: =$G$4
A5: CÓDIGO DE RECETA: | B5: sub001 | D5: PORCIONES: | E5: 1 | L5: CÓDIGO DE RECETA: | M5: Gua001 | O5: PORCIONES: | W5: CÓDIGO DE RECETA: | Z5: PORCIONES:
A6: CÓDIGO | B6: INGREDIENTES | D6: CANTIDAD | E6: UNIDAD | F6: EQUIPO Y UTENSILIOS | I6: COSTO NETO | J6: IMPORTE | L6: CÓDIGO | M6: INGREDIENTES | O6: CANTIDAD | P6: UNIDAD | Q6: EQUIPO Y UTENSILIOS | T6: COSTO NETO | U6: IMPORTE | W6: CÓDIGO | X6: INGREDIENTES | Z6: CANTIDAD | AA6: UNIDAD | AB6: EQUIPO Y UTENSILIOS | AE6: COSTO NETO | AF6: IMPORTE
A7: =VLOOKUP(B7,Base!$A$3:$F$994, 6, false) -> 0 | B7: . | E7: =VLOOKUP(B7,Base!$A$3:$F$994, 2, false) -> . | I7: =VLOOKUP(B7,Base!$A$3:$F$994, 5, false) -> 0 | J7: =I7*D7 -> 0 | L7: =VLOOKUP(M7,Base!$A$3:$F$994, 6, false) -> 0 | M7: . | P7: =VLOOKUP(M7,Base!$A$3:$F$994, 2, false) -> . | T7: =VLOOKUP(M7,Base!$A$3:$F$994, 5, false) -> 0 | U7: =T7*O7 -> 0 | W7: =VLOOKUP(X7,Base!$A$3:$F$994, 6, false) -> 0 | X7: . | AA7: =VLOOKUP(X7,Base!$A$3:$F$994, 2, false) -> . | AE7: =VLOOKUP(X7,Base!$A$3:$F$994, 5, false) -> 0 | AF7: =AE7*Z7 -> 0
A8: =VLOOKUP(B8,Base!$A$3:$F$994, 6, false) -> 0 | B8: . | E8: =VLOOKUP(B8,Base!$A$3:$F$994, 2, false) -> . | I8: =VLOOKUP(B8,Base!$A$3:$F$994, 5, false) -> 0 | J8: =I8*D8 -> 0 | L8: =VLOOKUP(M8,Base!$A$3:$F$994, 6, false) -> 0 | M8: . | P8: =VLOOKUP(M8,Base!$A$3:$F$994, 2, false) -> . | T8: =VLOOKUP(M8,Base!$A$3:$F$994, 5, false) -> 0 | U8: =T8*O8 -> 0 | W8: =VLOOKUP(X8,Base!$A$3:$F$994, 6, false) -> 0 | X8: . | AA8: =VLOOKUP(X8,Base!$A$3:$F$994, 2, false) -> . | AE8: =VLOOKUP(X8,Base!$A$3:$F$994, 5, false) -> 0 | AF8: =AE8*Z8 -> 0
A9: =VLOOKUP(B9,Base!$A$3:$F$994, 6, false) -> 0 | B9: . | E9: =VLOOKUP(B9,Base!$A$3:$F$994, 2, false) -> . | I9: =VLOOKUP(B9,Base!$A$3:$F$994, 5, false) -> 0 | J9: =I9*D9 -> 0 | L9: =VLOOKUP(M9,Base!$A$3:$F$994, 6, false) -> 0 | M9: . | P9: =VLOOKUP(M9,Base!$A$3:$F$994, 2, false) -> . | T9: =VLOOKUP(M9,Base!$A$3:$F$994, 5, false) -> 0 | U9: =T9*O9 -> 0 | W9: =VLOOKUP(X9,Base!$A$3:$F$994, 6, false) -> 0 | X9: . | AA9: =VLOOKUP(X9,Base!$A$3:$F$994, 2, false) -> . | AE9: =VLOOKUP(X9,Base!$A$3:$F$994, 5, false) -> 0 | AF9: =AE9*Z9 -> 0
A10: =VLOOKUP(B10,Base!$A$3:$F$994, 6, false) -> 0 | B10: . | E10: =VLOOKUP(B10,Base!$A$3:$F$994, 2, false) -> . | I10: =VLOOKUP(B10,Base!$A$3:$F$994, 5, false) -> 0 | J10: =I10*D10 -> 0 | L10: =VLOOKUP(M10,Base!$A$3:$F$994, 6, false) -> 0 | M10: . | P10: =VLOOKUP(M10,Base!$A$3:$F$994, 2, false) -> . | T10: =VLOOKUP(M10,Base!$A$3:$F$994, 5, false) -> 0 | U10: =T10*O10 -> 0 | W10: =VLOOKUP(X10,Base!$A$3:$F$994, 6, false) -> 0 | X10: . | AA10: =VLOOKUP(X10,Base!$A$3:$F$994, 2, false) -> . | AE10: =VLOOKUP(X10,Base!$A$3:$F$994, 5, false) -> 0 | AF10: =AE10*Z10 -> 0
A11: =VLOOKUP(B11,Base!$A$3:$F$994, 6, false) -> 0 | B11: . | E11: =VLOOKUP(B11,Base!$A$3:$F$994, 2, false) -> . | I11: =VLOOKUP(B11,Base!$A$3:$F$994, 5, false) -> 0 | J11: =I11*D11 -> 0 | L11: =VLOOKUP(M11,Base!$A$3:$F$994, 6, false) -> 0 | M11: . | P11: =VLOOKUP(M11,Base!$A$3:$F$994, 2, false) -> . | T11: =VLOOKUP(M11,Base!$A$3:$F$994, 5, false) -> 0 | U11: =T11*O11 -> 0 | W11: =VLOOKUP(X11,Base!$A$3:$F$994, 6, false) -> 0 | X11: . | AA11: =VLOOKUP(X11,Base!$A$3:$F$994, 2, false) -> . | AE11: =VLOOKUP(X11,Base!$A$3:$F$994, 5, false) -> 0 | AF11: =AE11*Z11 -> 0
A12: =VLOOKUP(B12,Base!$A$3:$F$994, 6, false) -> 0 | B12: . | E12: =VLOOKUP(B12,Base!$A$3:$F$994, 2, false) -> . | I12: =VLOOKUP(B12,Base!$A$3:$F$994, 5, false) -> 0 | J12: =I12*D12 -> 0 | L12: =VLOOKUP(M12,Base!$A$3:$F$994, 6, false) -> 0 | M12: . | P12: =VLOOKUP(M12,Base!$A$3:$F$994, 2, false) -> . | T12: =VLOOKUP(M12,Base!$A$3:$F$994, 5, false) -> 0 | U12: =T12*O12 -> 0 | W12: =VLOOKUP(X12,Base!$A$3:$F$994, 6, false) -> 0 | X12: . | AA12: =VLOOKUP(X12,Base!$A$3:$F$994, 2, false) -> . | AE12: =VLOOKUP(X12,Base!$A$3:$F$994, 5, false) -> 0 | AF12: =AE12*Z12 -> 0
A13: =VLOOKUP(B13,Base!$A$3:$F$994, 6, false) -> 0 | B13: . | E13: =VLOOKUP(B13,Base!$A$3:$F$994, 2, false) -> . | I13: =VLOOKUP(B13,Base!$A$3:$F$994, 5, false) -> 0 | J13: =I13*D13 -> 0 | L13: =VLOOKUP(M13,Base!$A$3:$F$994, 6, false) -> 0 | M13: . | P13: =VLOOKUP(M13,Base!$A$3:$F$994, 2, false) -> . | T13: =VLOOKUP(M13,Base!$A$3:$F$994, 5, false) -> 0 | U13: =T13*O13 -> 0 | W13: =VLOOKUP(X13,Base!$A$3:$F$994, 6, false) -> 0 | X13: . | AA13: =VLOOKUP(X13,Base!$A$3:$F$994, 2, false) -> . | AE13: =VLOOKUP(X13,Base!$A$3:$F$994, 5, false) -> 0 | AF13: =AE13*Z13 -> 0
A14: =VLOOKUP(B14,Base!$A$3:$F$994, 6, false) -> 0 | B14: . | E14: =VLOOKUP(B14,Base!$A$3:$F$994, 2, false) -> . | I14: =VLOOKUP(B14,Base!$A$3:$F$994, 5, false) -> 0 | J14: =I14*D14 -> 0 | L14: =VLOOKUP(M14,Base!$A$3:$F$994, 6, false) -> 0 | M14: . | P14: =VLOOKUP(M14,Base!$A$3:$F$994, 2, false) -> . | T14: =VLOOKUP(M14,Base!$A$3:$F$994, 5, false) -> 0 | U14: =T14*O14 -> 0 | W14: =VLOOKUP(X14,Base!$A$3:$F$994, 6, false) -> 0 | X14: . | AA14: =VLOOKUP(X14,Base!$A$3:$F$994, 2, false) -> . | AE14: =VLOOKUP(X14,Base!$A$3:$F$994, 5, false) -> 0 | AF14: =AE14*Z14 -> 0
A15: =VLOOKUP(B15,Base!$A$3:$F$994, 6, false) -> 0 | B15: . | E15: =VLOOKUP(B15,Base!$A$3:$F$994, 2, false) -> . | I15: =VLOOKUP(B15,Base!$A$3:$F$994, 5, false) -> 0 | J15: =I15*D15 -> 0 | L15: =VLOOKUP(M15,Base!$A$3:$F$994, 6, false) -> 0 | M15: . | P15: =VLOOKUP(M15,Base!$A$3:$F$994, 2, false) -> . | T15: =VLOOKUP(M15,Base!$A$3:$F$994, 5, false) -> 0 | U15: =T15*O15 -> 0 | W15: =VLOOKUP(X15,Base!$A$3:$F$994, 6, false) -> 0 | X15: . | AA15: =VLOOKUP(X15,Base!$A$3:$F$994, 2, false) -> . | AE15: =VLOOKUP(X15,Base!$A$3:$F$994, 5, false) -> 0 | AF15: =AE15*Z15 -> 0
A16: =VLOOKUP(B16,Base!$A$3:$F$994, 6, false) -> 0 | B16: . | E16: =VLOOKUP(B16,Base!$A$3:$F$994, 2, false) -> . | I16: =VLOOKUP(B16,Base!$A$3:$F$994, 5, false) -> 0 | J16: =I16*D16 -> 0 | L16: =VLOOKUP(M16,Base!$A$3:$F$994, 6, false) -> 0 | M16: . | P16: =VLOOKUP(M16,Base!$A$3:$F$994, 2, false) -> . | T16: =VLOOKUP(M16,Base!$A$3:$F$994, 5, false) -> 0 | U16: =T16*O16 -> 0 | W16: =VLOOKUP(X16,Base!$A$3:$F$994, 6, false) -> 0 | X16: . | AA16: =VLOOKUP(X16,Base!$A$3:$F$994, 2, false) -> . | AE16: =VLOOKUP(X16,Base!$A$3:$F$994, 5, false) -> 0 | AF16: =AE16*Z16 -> 0
A17: =VLOOKUP(B17,Base!$A$3:$F$994, 6, false) -> 0 | B17: . | E17: =VLOOKUP(B17,Base!$A$3:$F$994, 2, false) -> . | F17: PREPARACIÒN | I17: =VLOOKUP(B17,Base!$A$3:$F$994, 5, false) -> 0 | J17: =I17*D17 -> 0 | L17: =VLOOKUP(M17,Base!$A$3:$F$994, 6, false) -> 0 | M17: . | P17: =VLOOKUP(M17,Base!$A$3:$F$994, 2, false) -> . | Q17: PREPARACIÒN | T17: =VLOOKUP(M17,Base!$A$3:$F$994, 5, false) -> 0 | U17: =T17*O17 -> 0 | W17: =VLOOKUP(X17,Base!$A$3:$F$994, 6, false) -> 0 | X17: . | AA17: =VLOOKUP(X17,Base!$A$3:$F$994, 2, false) -> . | AB17: PREPARACIÒN | AE17: =VLOOKUP(X17,Base!$A$3:$F$994, 5, false) -> 0 | AF17: =AE17*Z17 -> 0
A18: =VLOOKUP(B18,Base!$A$3:$F$994, 6, false) -> 0 | B18: . | E18: =VLOOKUP(B18,Base!$A$3:$F$994, 2, false) -> . | I18: =VLOOKUP(B18,Base!$A$3:$F$994, 5, false) -> 0 | J18: =I18*D18 -> 0 | L18: =VLOOKUP(M18,Base!$A$3:$F$994, 6, false) -> 0 | M18: . | P18: =VLOOKUP(M18,Base!$A$3:$F$994, 2, false) -> . | T18: =VLOOKUP(M18,Base!$A$3:$F$994, 5, false) -> 0 | U18: =T18*O18 -> 0 | W18: =VLOOKUP(X18,Base!$A$3:$F$994, 6, false) -> 0 | X18: . | AA18: =VLOOKUP(X18,Base!$A$3:$F$994, 2, false) -> . | AE18: =VLOOKUP(X18,Base!$A$3:$F$994, 5, false) -> 0 | AF18: =AE18*Z18 -> 0
A19: =VLOOKUP(B19,Base!$A$3:$F$994, 6, false) -> 0 | B19: . | E19: =VLOOKUP(B19,Base!$A$3:$F$994, 2, false) -> . | I19: =VLOOKUP(B19,Base!$A$3:$F$994, 5, false) -> 0 | J19: =I19*D19 -> 0 | L19: =VLOOKUP(M19,Base!$A$3:$F$994, 6, false) -> 0 | M19: . | P19: =VLOOKUP(M19,Base!$A$3:$F$994, 2, false) -> . | T19: =VLOOKUP(M19,Base!$A$3:$F$994, 5, false) -> 0 | U19: =T19*O19 -> 0 | W19: =VLOOKUP(X19,Base!$A$3:$F$994, 6, false) -> 0 | X19: . | AA19: =VLOOKUP(X19,Base!$A$3:$F$994, 2, false) -> . | AE19: =VLOOKUP(X19,Base!$A$3:$F$994, 5, false) -> 0 | AF19: =AE19*Z19 -> 0
A20: =VLOOKUP(B20,Base!$A$3:$F$994, 6, false) -> 0 | B20: . | E20: =VLOOKUP(B20,Base!$A$3:$F$994, 2, false) -> . | I20: =VLOOKUP(B20,Base!$A$3:$F$994, 5, false) -> 0 | J20: =I20*D20 -> 0 | L20: =VLOOKUP(M20,Base!$A$3:$F$994, 6, false) -> 0 | M20: . | P20: =VLOOKUP(M20,Base!$A$3:$F$994, 2, false) -> . | T20: =VLOOKUP(M20,Base!$A$3:$F$994, 5, false) -> 0 | U20: =T20*O20 -> 0 | W20: =VLOOKUP(X20,Base!$A$3:$F$994, 6, false) -> 0 | X20: . | AA20: =VLOOKUP(X20,Base!$A$3:$F$994, 2, false) -> . | AE20: =VLOOKUP(X20,Base!$A$3:$F$994, 5, false) -> 0 | AF20: =AE20*Z20 -> 0
A21: =VLOOKUP(B21,Base!$A$3:$F$994, 6, false) -> 0 | B21: . | E21: =VLOOKUP(B21,Base!$A$3:$F$994, 2, false) -> . | I21: =VLOOKUP(B21,Base!$A$3:$F$994, 5, false) -> 0 | J21: =I21*D21 -> 0 | L21: =VLOOKUP(M21,Base!$A$3:$F$994, 6, false) -> 0 | M21: . | P21: =VLOOKUP(M21,Base!$A$3:$F$994, 2, false) -> . | T21: =VLOOKUP(M21,Base!$A$3:$F$994, 5, false) -> 0 | U21: =T21*O21 -> 0 | W21: =VLOOKUP(X21,Base!$A$3:$F$994, 6, false) -> 0 | X21: . | AA21: =VLOOKUP(X21,Base!$A$3:$F$994, 2, false) -> . | AE21: =VLOOKUP(X21,Base!$A$3:$F$994, 5, false) -> 0 | AF21: =AE21*Z21 -> 0
A22: =VLOOKUP(B22,Base!$A$3:$F$994, 6, false) -> 0 | B22: . | E22: =VLOOKUP(B22,Base!$A$3:$F$994, 2, false) -> . | I22: =VLOOKUP(B22,Base!$A$3:$F$994, 5, false) -> 0 | J22: =I22*D22 -> 0 | L22: =VLOOKUP(M22,Base!$A$3:$F$994, 6, false) -> 0 | M22: . | P22: =VLOOKUP(M22,Base!$A$3:$F$994, 2, false) -> . | T22: =VLOOKUP(M22,Base!$A$3:$F$994, 5, false) -> 0 | U22: =T22*O22 -> 0 | W22: =VLOOKUP(X22,Base!$A$3:$F$994, 6, false) -> 0 | X22: . | AA22: =VLOOKUP(X22,Base!$A$3:$F$994, 2, false) -> . | AE22: =VLOOKUP(X22,Base!$A$3:$F$994, 5, false) -> 0 | AF22: =AE22*Z22 -> 0
A23: =VLOOKUP(B23,Base!$A$3:$F$994, 6, false) -> 0 | B23: . | E23: =VLOOKUP(B23,Base!$A$3:$F$994, 2, false) -> . | I23: =VLOOKUP(B23,Base!$A$3:$F$994, 5, false) -> 0 | J23: =I23*D23 -> 0 | L23: =VLOOKUP(M23,Base!$A$3:$F$994, 6, false) -> 0 | M23: . | P23: =VLOOKUP(M23,Base!$A$3:$F$994, 2, false) -> . | T23: =VLOOKUP(M23,Base!$A$3:$F$994, 5, false) -> 0 | U23: =T23*O23 -> 0 | W23: =VLOOKUP(X23,Base!$A$3:$F$994, 6, false) -> 0 | X23: . | AA23: =VLOOKUP(X23,Base!$A$3:$F$994, 2, false) -> . | AE23: =VLOOKUP(X23,Base!$A$3:$F$994, 5, false) -> 0 | AF23: =AE23*Z23 -> 0
A24: =VLOOKUP(B24,Base!$A$3:$F$994, 6, false) -> 0 | B24: . | E24: =VLOOKUP(B24,Base!$A$3:$F$994, 2, false) -> . | I24: =VLOOKUP(B24,Base!$A$3:$F$994, 5, false) -> 0 | J24: =I24*D24 -> 0 | L24: =VLOOKUP(M24,Base!$A$3:$F$994, 6, false) -> 0 | M24: . | P24: =VLOOKUP(M24,Base!$A$3:$F$994, 2, false) -> . | T24: =VLOOKUP(M24,Base!$A$3:$F$994, 5, false) -> 0 | U24: =T24*O24 -> 0 | W24: =VLOOKUP(X24,Base!$A$3:$F$994, 6, false) -> 0 | X24: . | AA24: =VLOOKUP(X24,Base!$A$3:$F$994, 2, false) -> . | AE24: =VLOOKUP(X24,Base!$A$3:$F$994, 5, false) -> 0 | AF24: =AE24*Z24 -> 0
A25: ELABORACION | I25: TOTAL DE MP: | J25: =SUM(J7:J24) -> 0 | L25: ELABORACIÒN | T25: TOTAL DE MP: | U25: =SUM(U7:U24) -> 0 | W25: ELABORACIÒN | AE25: TOTAL DE MP: | AF25: =SUM(AF7:AF24) -> 0
I26: TOTAL P/P: | J26: =J25/E5 -> 0 | T26: TOTAL P/P: | U26: =U25/P5 -> #DIV/0! | AE26: TOTAL P/P: | AF26: =AF25/AA5 -> #DIV/0!
I27: IMPREVISTO: | J27: 0.05 | T27: IMPREVISTO: | U27: 0.05 | AE27: IMPREVISTO: | AF27: 0.05
I28: TOTAL DE COSTO: | J28: =J26+(J26*J27) -> 0 | T28: TOTAL DE COSTO: | U28: =U26+(U26*U27) -> #DIV/0! | AE28: TOTAL DE COSTO: | AF28: =AF26+(AF26*AF27) -> #DIV/0!
A34: MONTAJE | L34: MONTAJE | W34: MONTAJE
A38: OBSERVACIONES | L38: OBSERVACIONES | W38: OBSERVACIONES
A47: NOMBRE: | F47: FECHA: | G47: =$G$4 | L47: NOMBRE: | Q47: FECHA: | R47: =$G$4 | W47: NOMBRE: | AB47: FECHA: | AC47: =$G$4
A48: CÓDIGO DE RECETA: | D48: PORCIONES: | L48: CÓDIGO DE RECETA: | O48: PORCIONES: | W48: CÓDIGO DE RECETA: | Z48: PORCIONES:
A49: CÓDIGO | B49: INGREDIENTES | D49: CANTIDAD | E49: UNIDAD | F49: EQUIPO Y UTENSILIOS | I49: COSTO NETO | J49: IMPORTE | L49: CÓDIGO | M49: INGREDIENTES | O49: CANTIDAD | P49: UNIDAD | Q49: EQUIPO Y UTENSILIOS | T49: COSTO NETO | U49: IMPORTE | W49: CÓDIGO | X49: INGREDIENTES | Z49: CANTIDAD | AA49: UNIDAD | AB49: EQUIPO Y UTENSILIOS | AE49: COSTO NETO | AF49: IMPORTE
A50: =VLOOKUP(B50,Base!$A$3:$F$994, 6, false) -> 0 | B50: . | E50: =VLOOKUP(B50,Base!$A$3:$F$994, 2, false) -> . | I50: =VLOOKUP(B50,Base!$A$3:$F$994, 5, false) -> 0 | J50: =I50*D50 -> 0 | L50: =VLOOKUP(M50,Base!$A$3:$F$994, 6, false) -> 0 | M50: . | P50: =VLOOKUP(M50,Base!$A$3:$F$994, 2, false) -> . | T50: =VLOOKUP(M50,Base!$A$3:$F$994, 5, false) -> 0 | U50: =T50*O50 -> 0 | W50: =VLOOKUP(X50,Base!$A$3:$F$994, 6, false) -> 0 | X50: . | AA50: =VLOOKUP(X50,Base!$A$3:$F$994, 2, false) -> . | AE50: =VLOOKUP(X50,Base!$A$3:$F$994, 5, false) -> 0 | AF50: =AE50*Z50 -> 0
A51: =VLOOKUP(B51,Base!$A$3:$F$994, 6, false) -> 0 | B51: . | E51: =VLOOKUP(B51,Base!$A$3:$F$994, 2, false) -> . | I51: =VLOOKUP(B51,Base!$A$3:$F$994, 5, false) -> 0 | J51: =I51*D51 -> 0 | L51: =VLOOKUP(M51,Base!$A$3:$F$994, 6, false) -> 0 | M51: . | P51: =VLOOKUP(M51,Base!$A$3:$F$994, 2, false) -> . | T51: =VLOOKUP(M51,Base!$A$3:$F$994, 5, false) -> 0 | U51: =T51*O51 -> 0 | W51: =VLOOKUP(X51,Base!$A$3:$F$994, 6, false) -> 0 | X51: . | AA51: =VLOOKUP(X51,Base!$A$3:$F$994, 2, false) -> . | AE51: =VLOOKUP(X51,Base!$A$3:$F$994, 5, false) -> 0 | AF51: =AE51*Z51 -> 0
A52: =VLOOKUP(B52,Base!$A$3:$F$994, 6, false) -> 0 | B52: . | E52: =VLOOKUP(B52,Base!$A$3:$F$994, 2, false) -> . | I52: =VLOOKUP(B52,Base!$A$3:$F$994, 5, false) -> 0 | J52: =I52*D52 -> 0 | L52: =VLOOKUP(M52,Base!$A$3:$F$994, 6, false) -> 0 | M52: . | P52: =VLOOKUP(M52,Base!$A$3:$F$994, 2, false) -> . | T52: =VLOOKUP(M52,Base!$A$3:$F$994, 5, false) -> 0 | U52: =T52*O52 -> 0 | W52: =VLOOKUP(X52,Base!$A$3:$F$994, 6, false) -> 0 | X52: . | AA52: =VLOOKUP(X52,Base!$A$3:$F$994, 2, false) -> . | AE52: =VLOOKUP(X52,Base!$A$3:$F$994, 5, false) -> 0 | AF52: =AE52*Z52 -> 0
A53: =VLOOKUP(B53,Base!$A$3:$F$994, 6, false) -> 0 | B53: . | E53: =VLOOKUP(B53,Base!$A$3:$F$994, 2, false) -> . | I53: =VLOOKUP(B53,Base!$A$3:$F$994, 5, false) -> 0 | J53: =I53*D53 -> 0 | L53: =VLOOKUP(M53,Base!$A$3:$F$994, 6, false) -> 0 | M53: . | P53: =VLOOKUP(M53,Base!$A$3:$F$994, 2, false) -> . | T53: =VLOOKUP(M53,Base!$A$3:$F$994, 5, false) -> 0 | U53: =T53*O53 -> 0 | W53: =VLOOKUP(X53,Base!$A$3:$F$994, 6, false) -> 0 | X53: . | AA53: =VLOOKUP(X53,Base!$A$3:$F$994, 2, false) -> . | AE53: =VLOOKUP(X53,Base!$A$3:$F$994, 5, false) -> 0 | AF53: =AE53*Z53 -> 0
A54: =VLOOKUP(B54,Base!$A$3:$F$994, 6, false) -> 0 | B54: . | E54: =VLOOKUP(B54,Base!$A$3:$F$994, 2, false) -> . | I54: =VLOOKUP(B54,Base!$A$3:$F$994, 5, false) -> 0 | J54: =I54*D54 -> 0 | L54: =VLOOKUP(M54,Base!$A$3:$F$994, 6, false) -> 0 | M54: . | P54: =VLOOKUP(M54,Base!$A$3:$F$994, 2, false) -> . | T54: =VLOOKUP(M54,Base!$A$3:$F$994, 5, false) -> 0 | U54: =T54*O54 -> 0 | W54: =VLOOKUP(X54,Base!$A$3:$F$994, 6, false) -> 0 | X54: . | AA54: =VLOOKUP(X54,Base!$A$3:$F$994, 2, false) -> . | AE54: =VLOOKUP(X54,Base!$A$3:$F$994, 5, false) -> 0 | AF54: =AE54*Z54 -> 0
A55: =VLOOKUP(B55,Base!$A$3:$F$994, 6, false) -> 0 | B55: . | E55: =VLOOKUP(B55,Base!$A$3:$F$994, 2, false) -> . | I55: =VLOOKUP(B55,Base!$A$3:$F$994, 5, false) -> 0 | J55: =I55*D55 -> 0 | L55: =VLOOKUP(M55,Base!$A$3:$F$994, 6, false) -> 0 | M55: . | P55: =VLOOKUP(M55,Base!$A$3:$F$994, 2, false) -> . | T55: =VLOOKUP(M55,Base!$A$3:$F$994, 5, false) -> 0 | U55: =T55*O55 -> 0 | W55: =VLOOKUP(X55,Base!$A$3:$F$994, 6, false) -> 0 | X55: . | AA55: =VLOOKUP(X55,Base!$A$3:$F$994, 2, false) -> . | AE55: =VLOOKUP(X55,Base!$A$3:$F$994, 5, false) -> 0 | AF55: =AE55*Z55 -> 0
A56: =VLOOKUP(B56,Base!$A$3:$F$994, 6, false) -> 0 | B56: . | E56: =VLOOKUP(B56,Base!$A$3:$F$994, 2, false) -> . | I56: =VLOOKUP(B56,Base!$A$3:$F$994, 5, false) -> 0 | J56: =I56*D56 -> 0 | L56: =VLOOKUP(M56,Base!$A$3:$F$994, 6, false) -> 0 | M56: . | P56: =VLOOKUP(M56,Base!$A$3:$F$994, 2, false) -> . | T56: =VLOOKUP(M56,Base!$A$3:$F$994, 5, false) -> 0 | U56: =T56*O56 -> 0 | W56: =VLOOKUP(X56,Base!$A$3:$F$994, 6, false) -> 0 | X56: . | AA56: =VLOOKUP(X56,Base!$A$3:$F$994, 2, false) -> . | AE56: =VLOOKUP(X56,Base!$A$3:$F$994, 5, false) -> 0 | AF56: =AE56*Z56 -> 0
A57: =VLOOKUP(B57,Base!$A$3:$F$994, 6, false) -> 0 | B57: . | E57: =VLOOKUP(B57,Base!$A$3:$F$994, 2, false) -> . | I57: =VLOOKUP(B57,Base!$A$3:$F$994, 5, false) -> 0 | J57: =I57*D57 -> 0 | L57: =VLOOKUP(M57,Base!$A$3:$F$994, 6, false) -> 0 | M57: . | P57: =VLOOKUP(M57,Base!$A$3:$F$994, 2, false) -> . | T57: =VLOOKUP(M57,Base!$A$3:$F$994, 5, false) -> 0 | U57: =T57*O57 -> 0 | W57: =VLOOKUP(X57,Base!$A$3:$F$994, 6, false) -> 0 | X57: . | AA57: =VLOOKUP(X57,Base!$A$3:$F$994, 2, false) -> . | AE57: =VLOOKUP(X57,Base!$A$3:$F$994, 5, false) -> 0 | AF57: =AE57*Z57 -> 0
A58: =VLOOKUP(B58,Base!$A$3:$F$994, 6, false) -> 0 | B58: . | E58: =VLOOKUP(B58,Base!$A$3:$F$994, 2, false) -> . | I58: =VLOOKUP(B58,Base!$A$3:$F$994, 5, false) -> 0 | J58: =I58*D58 -> 0 | L58: =VLOOKUP(M58,Base!$A$3:$F$994, 6, false) -> 0 | M58: . | P58: =VLOOKUP(M58,Base!$A$3:$F$994, 2, false) -> . | T58: =VLOOKUP(M58,Base!$A$3:$F$994, 5, false) -> 0 | U58: =T58*O58 -> 0 | W58: =VLOOKUP(X58,Base!$A$3:$F$994, 6, false) -> 0 | X58: . | AA58: =VLOOKUP(X58,Base!$A$3:$F$994, 2, false) -> . | AE58: =VLOOKUP(X58,Base!$A$3:$F$994, 5, false) -> 0 | AF58: =AE58*Z58 -> 0
A59: =VLOOKUP(B59,Base!$A$3:$F$994, 6, false) -> 0 | B59: . | E59: =VLOOKUP(B59,Base!$A$3:$F$994, 2, false) -> . | I59: =VLOOKUP(B59,Base!$A$3:$F$994, 5, false) -> 0 | J59: =I59*D59 -> 0 | L59: =VLOOKUP(M59,Base!$A$3:$F$994, 6, false) -> 0 | M59: . | P59: =VLOOKUP(M59,Base!$A$3:$F$994, 2, false) -> . | T59: =VLOOKUP(M59,Base!$A$3:$F$994, 5, false) -> 0 | U59: =T59*O59 -> 0 | W59: =VLOOKUP(X59,Base!$A$3:$F$994, 6, false) -> 0 | X59: . | AA59: =VLOOKUP(X59,Base!$A$3:$F$994, 2, false) -> . | AE59: =VLOOKUP(X59,Base!$A$3:$F$994, 5, false) -> 0 | AF59: =AE59*Z59 -> 0
A60: =VLOOKUP(B60,Base!$A$3:$F$994, 6, false) -> 0 | B60: . | E60: =VLOOKUP(B60,Base!$A$3:$F$994, 2, false) -> . | F60: PREPARACIÒN | I60: =VLOOKUP(B60,Base!$A$3:$F$994, 5, false) -> 0 | J60: =I60*D60 -> 0 | L60: =VLOOKUP(M60,Base!$A$3:$F$994, 6, false) -> 0 | M60: . | P60: =VLOOKUP(M60,Base!$A$3:$F$994, 2, false) -> . | Q60: PREPARACIÒN | T60: =VLOOKUP(M60,Base!$A$3:$F$994, 5, false) -> 0 | U60: =T60*O60 -> 0 | W60: =VLOOKUP(X60,Base!$A$3:$F$994, 6, false) -> 0 | X60: . | AA60: =VLOOKUP(X60,Base!$A$3:$F$994, 2, false) -> . | AB60: PREPARACIÒN | AE60: =VLOOKUP(X60,Base!$A$3:$F$994, 5, false) -> 0 | AF60: =AE60*Z60 -> 0
A61: =VLOOKUP(B61,Base!$A$3:$F$994, 6, false) -> 0 | B61: . | E61: =VLOOKUP(B61,Base!$A$3:$F$994, 2, false) -> . | I61: =VLOOKUP(B61,Base!$A$3:$F$994, 5, false) -> 0 | J61: =I61*D61 -> 0 | L61: =VLOOKUP(M61,Base!$A$3:$F$994, 6, false) -> 0 | M61: . | P61: =VLOOKUP(M61,Base!$A$3:$F$994, 2, false) -> . | T61: =VLOOKUP(M61,Base!$A$3:$F$994, 5, false) -> 0 | U61: =T61*O61 -> 0 | W61: =VLOOKUP(X61,Base!$A$3:$F$994, 6, false) -> 0 | X61: . | AA61: =VLOOKUP(X61,Base!$A$3:$F$994, 2, false) -> . | AE61: =VLOOKUP(X61,Base!$A$3:$F$994, 5, false) -> 0 | AF61: =AE61*Z61 -> 0
A62: =VLOOKUP(B62,Base!$A$3:$F$994, 6, false) -> 0 | B62: . | E62: =VLOOKUP(B62,Base!$A$3:$F$994, 2, false) -> . | I62: =VLOOKUP(B62,Base!$A$3:$F$994, 5, false) -> 0 | J62: =I62*D62 -> 0 | L62: =VLOOKUP(M62,Base!$A$3:$F$994, 6, false) -> 0 | M62: . | P62: =VLOOKUP(M62,Base!$A$3:$F$994, 2, false) -> . | T62: =VLOOKUP(M62,Base!$A$3:$F$994, 5, false) -> 0 | U62: =T62*O62 -> 0 | W62: =VLOOKUP(X62,Base!$A$3:$F$994, 6, false) -> 0 | X62: . | AA62: =VLOOKUP(X62,Base!$A$3:$F$994, 2, false) -> . | AE62: =VLOOKUP(X62,Base!$A$3:$F$994, 5, false) -> 0 | AF62: =AE62*Z62 -> 0
A63: =VLOOKUP(B63,Base!$A$3:$F$994, 6, false) -> 0 | B63: . | E63: =VLOOKUP(B63,Base!$A$3:$F$994, 2, false) -> . | I63: =VLOOKUP(B63,Base!$A$3:$F$994, 5, false) -> 0 | J63: =I63*D63 -> 0 | L63: =VLOOKUP(M63,Base!$A$3:$F$994, 6, false) -> 0 | M63: . | P63: =VLOOKUP(M63,Base!$A$3:$F$994, 2, false) -> . | T63: =VLOOKUP(M63,Base!$A$3:$F$994, 5, false) -> 0 | U63: =T63*O63 -> 0 | W63: =VLOOKUP(X63,Base!$A$3:$F$994, 6, false) -> 0 | X63: . | AA63: =VLOOKUP(X63,Base!$A$3:$F$994, 2, false) -> . | AE63: =VLOOKUP(X63,Base!$A$3:$F$994, 5, false) -> 0 | AF63: =AE63*Z63 -> 0
A64: =VLOOKUP(B64,Base!$A$3:$F$994, 6, false) -> 0 | B64: . | E64: =VLOOKUP(B64,Base!$A$3:$F$994, 2, false) -> . | I64: =VLOOKUP(B64,Base!$A$3:$F$994, 5, false) -> 0 | J64: =I64*D64 -> 0 | L64: =VLOOKUP(M64,Base!$A$3:$F$994, 6, false) -> 0 | M64: . | P64: =VLOOKUP(M64,Base!$A$3:$F$994, 2, false) -> . | T64: =VLOOKUP(M64,Base!$A$3:$F$994, 5, false) -> 0 | U64: =T64*O64 -> 0 | W64: =VLOOKUP(X64,Base!$A$3:$F$994, 6, false) -> 0 | X64: . | AA64: =VLOOKUP(X64,Base!$A$3:$F$994, 2, false) -> . | AE64: =VLOOKUP(X64,Base!$A$3:$F$994, 5, false) -> 0 | AF64: =AE64*Z64 -> 0
A65: =VLOOKUP(B65,Base!$A$3:$F$994, 6, false) -> 0 | B65: . | E65: =VLOOKUP(B65,Base!$A$3:$F$994, 2, false) -> . | I65: =VLOOKUP(B65,Base!$A$3:$F$994, 5, false) -> 0 | J65: =I65*D65 -> 0 | L65: =VLOOKUP(M65,Base!$A$3:$F$994, 6, false) -> 0 | M65: . | P65: =VLOOKUP(M65,Base!$A$3:$F$994, 2, false) -> . | T65: =VLOOKUP(M65,Base!$A$3:$F$994, 5, false) -> 0 | U65: =T65*O65 -> 0 | W65: =VLOOKUP(X65,Base!$A$3:$F$994, 6, false) -> 0 | X65: . | AA65: =VLOOKUP(X65,Base!$A$3:$F$994, 2, false) -> . | AE65: =VLOOKUP(X65,Base!$A$3:$F$994, 5, false) -> 0 | AF65: =AE65*Z65 -> 0
A66: =VLOOKUP(B66,Base!$A$3:$F$994, 6, false) -> 0 | B66: . | E66: =VLOOKUP(B66,Base!$A$3:$F$994, 2, false) -> . | I66: =VLOOKUP(B66,Base!$A$3:$F$994, 5, false) -> 0 | J66: =I66*D66 -> 0 | L66: =VLOOKUP(M66,Base!$A$3:$F$994, 6, false) -> 0 | M66: . | P66: =VLOOKUP(M66,Base!$A$3:$F$994, 2, false) -> . | T66: =VLOOKUP(M66,Base!$A$3:$F$994, 5, false) -> 0 | U66: =T66*O66 -> 0 | W66: =VLOOKUP(X66,Base!$A$3:$F$994, 6, false) -> 0 | X66: . | AA66: =VLOOKUP(X66,Base!$A$3:$F$994, 2, false) -> . | AE66: =VLOOKUP(X66,Base!$A$3:$F$994, 5, false) -> 0 | AF66: =AE66*Z66 -> 0
A67: =VLOOKUP(B67,Base!$A$3:$F$994, 6, false) -> 0 | B67: . | E67: =VLOOKUP(B67,Base!$A$3:$F$994, 2, false) -> . | I67: =VLOOKUP(B67,Base!$A$3:$F$994, 5, false) -> 0 | J67: =I67*D67 -> 0 | L67: =VLOOKUP(M67,Base!$A$3:$F$994, 6, false) -> 0 | M67: . | P67: =VLOOKUP(M67,Base!$A$3:$F$994, 2, false) -> . | T67: =VLOOKUP(M67,Base!$A$3:$F$994, 5, false) -> 0 | U67: =T67*O67 -> 0 | W67: =VLOOKUP(X67,Base!$A$3:$F$994, 6, false) -> 0 | X67: . | AA67: =VLOOKUP(X67,Base!$A$3:$F$994, 2, false) -> . | AE67: =VLOOKUP(X67,Base!$A$3:$F$994, 5, false) -> 0 | AF67: =AE67*Z67 -> 0
A68: ELABORACIÒN | I68: TOTAL DE MP: | J68: =SUM(J50:J67) -> 0 | L68: ELABORACIÒN | T68: TOTAL DE MP: | U68: =SUM(U50:U67) -> 0 | W68: ELABORACIÒN | AE68: TOTAL DE MP: | AF68: =SUM(AF50:AF67) -> 0
I69: TOTAL P/P: | J69: =J68/E48 -> #DIV/0! | T69: TOTAL P/P: | U69: =U68/P48 -> #DIV/0! | AE69: TOTAL P/P: | AF69: =AF68/AA48 -> #DIV/0!
I70: IMPREVISTO: | J70: 0.05 | T70: IMPREVISTO: | U70: 0.05 | AE70: IMPREVISTO: | AF70: 0.05
I71: TOTAL DE COSTO: | J71: =J69+(J69*J70) -> #DIV/0! | T71: TOTAL DE COSTO: | U71: =U69+(U69*U70) -> #DIV/0! | AE71: TOTAL DE COSTO: | AF71: =AF69+(AF69*AF70) -> #DIV/0!
A77: MONTAJE | L77: MONTAJE | W77: MONTAJE
A81: OBSERVACIONES | L81: OBSERVACIONES | W81: OBSERVACIONES
A90: NOMBRE: | F90: FECHA: | G90: =$G$4 | L90: NOMBRE: | Q90: FECHA: | R90: =$G$4 | W90: NOMBRE: | AB90: FECHA: | AC90: =$G$4
A91: CÓDIGO DE RECETA: | B91: 3 | D91: PORCIONES: | L91: CÓDIGO DE RECETA: | O91: PORCIONES: | W91: CÓDIGO DE RECETA: | Z91: PORCIONES:
A92: CÓDIGO | B92: INGREDIENTES | D92: CANTIDAD | E92: UNIDAD | F92: EQUIPO Y UTENSILIOS | I92: COSTO NETO | J92: IMPORTE | L92: CÓDIGO | M92: INGREDIENTES | O92: CANTIDAD | P92: UNIDAD | Q92: EQUIPO Y UTENSILIOS | T92: COSTO NETO | U92: IMPORTE | W92: CÓDIGO | X92: INGREDIENTES | Z92: CANTIDAD | AA92: UNIDAD | AB92: EQUIPO Y UTENSILIOS | AE92: COSTO NETO | AF92: IMPORTE
A93: =VLOOKUP(B93,Base!$A$3:$F$994, 6, false) -> 0 | B93: . | E93: =VLOOKUP(B93,Base!$A$3:$F$994, 2, false) -> . | I93: =VLOOKUP(B93,Base!$A$3:$F$994, 5, false) -> 0 | J93: =I93*D93 -> 0 | L93: =VLOOKUP(M93,Base!$A$3:$F$994, 6, false) -> 0 | M93: . | P93: =VLOOKUP(M93,Base!$A$3:$F$994, 2, false) -> . | T93: =VLOOKUP(M93,Base!$A$3:$F$994, 5, false) -> 0 | U93: =T93*O93 -> 0 | W93: =VLOOKUP(X93,Base!$A$3:$F$994, 6, false) -> 0 | X93: . | AA93: =VLOOKUP(X93,Base!$A$3:$F$994, 2, false) -> . | AE93: =VLOOKUP(X93,Base!$A$3:$F$994, 5, false) -> 0 | AF93: =AE93*Z93 -> 0
A94: =VLOOKUP(B94,Base!$A$3:$F$994, 6, false) -> 0 | B94: . | E94: =VLOOKUP(B94,Base!$A$3:$F$994, 2, false) -> . | I94: =VLOOKUP(B94,Base!$A$3:$F$994, 5, false) -> 0 | J94: =I94*D94 -> 0 | L94: =VLOOKUP(M94,Base!$A$3:$F$994, 6, false) -> 0 | M94: . | P94: =VLOOKUP(M94,Base!$A$3:$F$994, 2, false) -> . | T94: =VLOOKUP(M94,Base!$A$3:$F$994, 5, false) -> 0 | U94: =T94*O94 -> 0 | W94: =VLOOKUP(X94,Base!$A$3:$F$994, 6, false) -> 0 | X94: . | AA94: =VLOOKUP(X94,Base!$A$3:$F$994, 2, false) -> . | AE94: =VLOOKUP(X94,Base!$A$3:$F$994, 5, false) -> 0 | AF94: =AE94*Z94 -> 0
A95: =VLOOKUP(B95,Base!$A$3:$F$994, 6, false) -> 0 | B95: . | E95: =VLOOKUP(B95,Base!$A$3:$F$994, 2, false) -> . | I95: =VLOOKUP(B95,Base!$A$3:$F$994, 5, false) -> 0 | J95: =I95*D95 -> 0 | L95: =VLOOKUP(M95,Base!$A$3:$F$994, 6, false) -> 0 | M95: . | P95: =VLOOKUP(M95,Base!$A$3:$F$994, 2, false) -> . | T95: =VLOOKUP(M95,Base!$A$3:$F$994, 5, false) -> 0 | U95: =T95*O95 -> 0 | W95: =VLOOKUP(X95,Base!$A$3:$F$994, 6, false) -> 0 | X95: . | AA95: =VLOOKUP(X95,Base!$A$3:$F$994, 2, false) -> . | AE95: =VLOOKUP(X95,Base!$A$3:$F$994, 5, false) -> 0 | AF95: =AE95*Z95 -> 0
A96: =VLOOKUP(B96,Base!$A$3:$F$994, 6, false) -> 0 | B96: . | E96: =VLOOKUP(B96,Base!$A$3:$F$994, 2, false) -> . | I96: =VLOOKUP(B96,Base!$A$3:$F$994, 5, false) -> 0 | J96: =I96*D96 -> 0 | L96: =VLOOKUP(M96,Base!$A$3:$F$994, 6, false) -> 0 | M96: . | P96: =VLOOKUP(M96,Base!$A$3:$F$994, 2, false) -> . | T96: =VLOOKUP(M96,Base!$A$3:$F$994, 5, false) -> 0 | U96: =T96*O96 -> 0 | W96: =VLOOKUP(X96,Base!$A$3:$F$994, 6, false) -> 0 | X96: . | AA96: =VLOOKUP(X96,Base!$A$3:$F$994, 2, false) -> . | AE96: =VLOOKUP(X96,Base!$A$3:$F$994, 5, false) -> 0 | AF96: =AE96*Z96 -> 0
A97: =VLOOKUP(B97,Base!$A$3:$F$994, 6, false) -> 0 | B97: . | E97: =VLOOKUP(B97,Base!$A$3:$F$994, 2, false) -> . | I97: =VLOOKUP(B97,Base!$A$3:$F$994, 5, false) -> 0 | J97: =I97*D97 -> 0 | L97: =VLOOKUP(M97,Base!$A$3:$F$994, 6, false) -> 0 | M97: . | P97: =VLOOKUP(M97,Base!$A$3:$F$994, 2, false) -> . | T97: =VLOOKUP(M97,Base!$A$3:$F$994, 5, false) -> 0 | U97: =T97*O97 -> 0 | W97: =VLOOKUP(X97,Base!$A$3:$F$994, 6, false) -> 0 | X97: . | AA97: =VLOOKUP(X97,Base!$A$3:$F$994, 2, false) -> . | AE97: =VLOOKUP(X97,Base!$A$3:$F$994, 5, false) -> 0 | AF97: =AE97*Z97 -> 0
A98: =VLOOKUP(B98,Base!$A$3:$F$994, 6, false) -> 0 | B98: . | E98: =VLOOKUP(B98,Base!$A$3:$F$994, 2, false) -> . | I98: =VLOOKUP(B98,Base!$A$3:$F$994, 5, false) -> 0 | J98: =I98*D98 -> 0 | L98: =VLOOKUP(M98,Base!$A$3:$F$994, 6, false) -> 0 | M98: . | P98: =VLOOKUP(M98,Base!$A$3:$F$994, 2, false) -> . | T98: =VLOOKUP(M98,Base!$A$3:$F$994, 5, false) -> 0 | U98: =T98*O98 -> 0 | W98: =VLOOKUP(X98,Base!$A$3:$F$994, 6, false) -> 0 | X98: . | AA98: =VLOOKUP(X98,Base!$A$3:$F$994, 2, false) -> . | AE98: =VLOOKUP(X98,Base!$A$3:$F$994, 5, false) -> 0 | AF98: =AE98*Z98 -> 0
A99: =VLOOKUP(B99,Base!$A$3:$F$994, 6, false) -> 0 | B99: . | E99: =VLOOKUP(B99,Base!$A$3:$F$994, 2, false) -> . | I99: =VLOOKUP(B99,Base!$A$3:$F$994, 5, false) -> 0 | J99: =I99*D99 -> 0 | L99: =VLOOKUP(M99,Base!$A$3:$F$994, 6, false) -> 0 | M99: . | P99: =VLOOKUP(M99,Base!$A$3:$F$994, 2, false) -> . | T99: =VLOOKUP(M99,Base!$A$3:$F$994, 5, false) -> 0 | U99: =T99*O99 -> 0 | W99: =VLOOKUP(X99,Base!$A$3:$F$994, 6, false) -> 0 | X99: . | AA99: =VLOOKUP(X99,Base!$A$3:$F$994, 2, false) -> . | AE99: =VLOOKUP(X99,Base!$A$3:$F$994, 5, false) -> 0 | AF99: =AE99*Z99 -> 0
A100: =VLOOKUP(B100,Base!$A$3:$F$994, 6, false) -> 0 | B100: . | E100: =VLOOKUP(B100,Base!$A$3:$F$994, 2, false) -> . | I100: =VLOOKUP(B100,Base!$A$3:$F$994, 5, false) -> 0 | J100: =I100*D100 -> 0 | L100: =VLOOKUP(M100,Base!$A$3:$F$994, 6, false) -> 0 | M100: . | P100: =VLOOKUP(M100,Base!$A$3:$F$994, 2, false) -> . | T100: =VLOOKUP(M100,Base!$A$3:$F$994, 5, false) -> 0 | U100: =T100*O100 -> 0 | W100: =VLOOKUP(X100,Base!$A$3:$F$994, 6, false) -> 0 | X100: . | AA100: =VLOOKUP(X100,Base!$A$3:$F$994, 2, false) -> . | AE100: =VLOOKUP(X100,Base!$A$3:$F$994, 5, false) -> 0 | AF100: =AE100*Z100 -> 0
A101: =VLOOKUP(B101,Base!$A$3:$F$994, 6, false) -> 0 | B101: . | E101: =VLOOKUP(B101,Base!$A$3:$F$994, 2, false) -> . | I101: =VLOOKUP(B101,Base!$A$3:$F$994, 5, false) -> 0 | J101: =I101*D101 -> 0 | L101: =VLOOKUP(M101,Base!$A$3:$F$994, 6, false) -> 0 | M101: . | P101: =VLOOKUP(M101,Base!$A$3:$F$994, 2, false) -> . | T101: =VLOOKUP(M101,Base!$A$3:$F$994, 5, false) -> 0 | U101: =T101*O101 -> 0 | W101: =VLOOKUP(X101,Base!$A$3:$F$994, 6, false) -> 0 | X101: . | AA101: =VLOOKUP(X101,Base!$A$3:$F$994, 2, false) -> . | AE101: =VLOOKUP(X101,Base!$A$3:$F$994, 5, false) -> 0 | AF101: =AE101*Z101 -> 0
A102: =VLOOKUP(B102,Base!$A$3:$F$994, 6, false) -> 0 | B102: . | E102: =VLOOKUP(B102,Base!$A$3:$F$994, 2, false) -> . | I102: =VLOOKUP(B102,Base!$A$3:$F$994, 5, false) -> 0 | J102: =I102*D102 -> 0 | L102: =VLOOKUP(M102,Base!$A$3:$F$994, 6, false) -> 0 | M102: . | P102: =VLOOKUP(M102,Base!$A$3:$F$994, 2, false) -> . | T102: =VLOOKUP(M102,Base!$A$3:$F$994, 5, false) -> 0 | U102: =T102*O102 -> 0 | W102: =VLOOKUP(X102,Base!$A$3:$F$994, 6, false) -> 0 | X102: . | AA102: =VLOOKUP(X102,Base!$A$3:$F$994, 2, false) -> . | AE102: =VLOOKUP(X102,Base!$A$3:$F$994, 5, false) -> 0 | AF102: =AE102*Z102 -> 0
A103: =VLOOKUP(B103,Base!$A$3:$F$994, 6, false) -> 0 | B103: . | E103: =VLOOKUP(B103,Base!$A$3:$F$994, 2, false) -> . | F103: PREPARACIÒN | I103: =VLOOKUP(B103,Base!$A$3:$F$994, 5, false) -> 0 | J103: =I103*D103 -> 0 | L103: =VLOOKUP(M103,Base!$A$3:$F$994, 6, false) -> 0 | M103: . | P103: =VLOOKUP(M103,Base!$A$3:$F$994, 2, false) -> . | Q103: PREPARACIÒN | T103: =VLOOKUP(M103,Base!$A$3:$F$994, 5, false) -> 0 | U103: =T103*O103 -> 0 | W103: =VLOOKUP(X103,Base!$A$3:$F$994, 6, false) -> 0 | X103: . | AA103: =VLOOKUP(X103,Base!$A$3:$F$994, 2, false) -> . | AB103: PREPARACIÒN | AE103: =VLOOKUP(X103,Base!$A$3:$F$994, 5, false) -> 0 | AF103: =AE103*Z103 -> 0
A104: =VLOOKUP(B104,Base!$A$3:$F$994, 6, false) -> 0 | B104: . | E104: =VLOOKUP(B104,Base!$A$3:$F$994, 2, false) -> . | I104: =VLOOKUP(B104,Base!$A$3:$F$994, 5, false) -> 0 | J104: =I104*D104 -> 0 | L104: =VLOOKUP(M104,Base!$A$3:$F$994, 6, false) -> 0 | M104: . | P104: =VLOOKUP(M104,Base!$A$3:$F$994, 2, false) -> . | T104: =VLOOKUP(M104,Base!$A$3:$F$994, 5, false) -> 0 | U104: =T104*O104 -> 0 | W104: =VLOOKUP(X104,Base!$A$3:$F$994, 6, false) -> 0 | X104: . | AA104: =VLOOKUP(X104,Base!$A$3:$F$994, 2, false) -> . | AE104: =VLOOKUP(X104,Base!$A$3:$F$994, 5, false) -> 0 | AF104: =AE104*Z104 -> 0
A105: =VLOOKUP(B105,Base!$A$3:$F$994, 6, false) -> 0 | B105: . | E105: =VLOOKUP(B105,Base!$A$3:$F$994, 2, false) -> . | I105: =VLOOKUP(B105,Base!$A$3:$F$994, 5, false) -> 0 | J105: =I105*D105 -> 0 | L105: =VLOOKUP(M105,Base!$A$3:$F$994, 6, false) -> 0 | M105: . | P105: =VLOOKUP(M105,Base!$A$3:$F$994, 2, false) -> . | T105: =VLOOKUP(M105,Base!$A$3:$F$994, 5, false) -> 0 | U105: =T105*O105 -> 0 | W105: =VLOOKUP(X105,Base!$A$3:$F$994, 6, false) -> 0 | X105: . | AA105: =VLOOKUP(X105,Base!$A$3:$F$994, 2, false) -> . | AE105: =VLOOKUP(X105,Base!$A$3:$F$994, 5, false) -> 0 | AF105: =AE105*Z105 -> 0
A106: =VLOOKUP(B106,Base!$A$3:$F$994, 6, false) -> 0 | B106: . | E106: =VLOOKUP(B106,Base!$A$3:$F$994, 2, false) -> . | I106: =VLOOKUP(B106,Base!$A$3:$F$994, 5, false) -> 0 | J106: =I106*D106 -> 0 | L106: =VLOOKUP(M106,Base!$A$3:$F$994, 6, false) -> 0 | M106: . | P106: =VLOOKUP(M106,Base!$A$3:$F$994, 2, false) -> . | T106: =VLOOKUP(M106,Base!$A$3:$F$994, 5, false) -> 0 | U106: =T106*O106 -> 0 | W106: =VLOOKUP(X106,Base!$A$3:$F$994, 6, false) -> 0 | X106: . | AA106: =VLOOKUP(X106,Base!$A$3:$F$994, 2, false) -> . | AE106: =VLOOKUP(X106,Base!$A$3:$F$994, 5, false) -> 0 | AF106: =AE106*Z106 -> 0
A107: =VLOOKUP(B107,Base!$A$3:$F$994, 6, false) -> 0 | B107: . | E107: =VLOOKUP(B107,Base!$A$3:$F$994, 2, false) -> . | I107: =VLOOKUP(B107,Base!$A$3:$F$994, 5, false) -> 0 | J107: =I107*D107 -> 0 | L107: =VLOOKUP(M107,Base!$A$3:$F$994, 6, false) -> 0 | M107: . | P107: =VLOOKUP(M107,Base!$A$3:$F$994, 2, false) -> . | T107: =VLOOKUP(M107,Base!$A$3:$F$994, 5, false) -> 0 | U107: =T107*O107 -> 0 | W107: =VLOOKUP(X107,Base!$A$3:$F$994, 6, false) -> 0 | X107: . | AA107: =VLOOKUP(X107,Base!$A$3:$F$994, 2, false) -> . | AE107: =VLOOKUP(X107,Base!$A$3:$F$994, 5, false) -> 0 | AF107: =AE107*Z107 -> 0
A108: =VLOOKUP(B108,Base!$A$3:$F$994, 6, false) -> 0 | B108: . | E108: =VLOOKUP(B108,Base!$A$3:$F$994, 2, false) -> . | I108: =VLOOKUP(B108,Base!$A$3:$F$994, 5, false) -> 0 | J108: =I108*D108 -> 0 | L108: =VLOOKUP(M108,Base!$A$3:$F$994, 6, false) -> 0 | M108: . | P108: =VLOOKUP(M108,Base!$A$3:$F$994, 2, false) -> . | T108: =VLOOKUP(M108,Base!$A$3:$F$994, 5, false) -> 0 | U108: =T108*O108 -> 0 | W108: =VLOOKUP(X108,Base!$A$3:$F$994, 6, false) -> 0 | X108: . | AA108: =VLOOKUP(X108,Base!$A$3:$F$994, 2, false) -> . | AE108: =VLOOKUP(X108,Base!$A$3:$F$994, 5, false) -> 0 | AF108: =AE108*Z108 -> 0
A109: =VLOOKUP(B109,Base!$A$3:$F$994, 6, false) -> 0 | B109: . | E109: =VLOOKUP(B109,Base!$A$3:$F$994, 2, false) -> . | I109: =VLOOKUP(B109,Base!$A$3:$F$994, 5, false) -> 0 | J109: =I109*D109 -> 0 | L109: =VLOOKUP(M109,Base!$A$3:$F$994, 6, false) -> 0 | M109: . | P109: =VLOOKUP(M109,Base!$A$3:$F$994, 2, false) -> . | T109: =VLOOKUP(M109,Base!$A$3:$F$994, 5, false) -> 0 | U109: =T109*O109 -> 0 | W109: =VLOOKUP(X109,Base!$A$3:$F$994, 6, false) -> 0 | X109: . | AA109: =VLOOKUP(X109,Base!$A$3:$F$994, 2, false) -> . | AE109: =VLOOKUP(X109,Base!$A$3:$F$994, 5, false) -> 0 | AF109: =AE109*Z109 -> 0
A110: =VLOOKUP(B110,Base!$A$3:$F$994, 6, false) -> 0 | B110: . | E110: =VLOOKUP(B110,Base!$A$3:$F$994, 2, false) -> . | I110: =VLOOKUP(B110,Base!$A$3:$F$994, 5, false) -> 0 | J110: =I110*D110 -> 0 | L110: =VLOOKUP(M110,Base!$A$3:$F$994, 6, false) -> 0 | M110: . | P110: =VLOOKUP(M110,Base!$A$3:$F$994, 2, false) -> . | T110: =VLOOKUP(M110,Base!$A$3:$F$994, 5, false) -> 0 | U110: =T110*O110 -> 0 | W110: =VLOOKUP(X110,Base!$A$3:$F$994, 6, false) -> 0 | X110: . | AA110: =VLOOKUP(X110,Base!$A$3:$F$994, 2, false) -> . | AE110: =VLOOKUP(X110,Base!$A$3:$F$994, 5, false) -> 0 | AF110: =AE110*Z110 -> 0
A111: ELABORACIÒN | I111: TOTAL DE MP: | J111: =SUM(J93:J110) -> 0 | L111: ELABORACIÒN | T111: TOTAL DE MP: | U111: =SUM(U93:U110) -> 0 | W111: ELABORACIÒN | AE111: TOTAL DE MP: | AF111: =SUM(AF93:AF110) -> 0
I112: TOTAL P/P: | J112: =J111/E91 -> #DIV/0! | T112: TOTAL P/P: | U112: =U111/P91 -> #DIV/0! | AE112: TOTAL P/P: | AF112: =AF111/AA91 -> #DIV/0!
I113: IMPREVISTO: | J113: 0.05 | T113: IMPREVISTO: | U113: 0.05 | AE113: IMPREVISTO: | AF113: 0.05
I114: TOTAL DE COSTO: | J114: =J112+(J112*J113) -> #DIV/0! | T114: TOTAL DE COSTO: | U114: =U112+(U112*U113) -> #DIV/0! | AE114: TOTAL DE COSTO: | AF114: =AF112+(AF112*AF113) -> #DIV/0!
A120: MONTAJE | L120: MONTAJE | W120: MONTAJE
A124: OBSERVACIONES | L124: OBSERVACIONES | W124: OBSERVACIONES
A133: NOMBRE: | F133: FECHA: | G133: =$G$4 | L133: NOMBRE: | Q133: FECHA: | R133: =$G$4 | W133: NOMBRE: | AB133: FECHA: | AC133: =$G$4
A134: CÓDIGO DE RECETA: | B134: 4 | D134: PORCIONES: | L134: CÓDIGO DE RECETA: | O134: PORCIONES: | W134: CÓDIGO DE RECETA: | Z134: PORCIONES:
A135: CÓDIGO | B135: INGREDIENTES | D135: CANTIDAD | E135: UNIDAD | F135: EQUIPO Y UTENSILIOS | I135: COSTO NETO | J135: IMPORTE | L135: CÓDIGO | M135: INGREDIENTES | O135: CANTIDAD | P135: UNIDAD | Q135: EQUIPO Y UTENSILIOS | T135: COSTO NETO | U135: IMPORTE | W135: CÓDIGO | X135: INGREDIENTES | Z135: CANTIDAD | AA135: UNIDAD | AB135: EQUIPO Y UTENSILIOS | AE135: COSTO NETO | AF135: IMPORTE
A136: =VLOOKUP(B136,Base!$A$3:$F$994, 6, false) -> 0 | B136: . | E136: =VLOOKUP(B136,Base!$A$3:$F$994, 2, false) -> . | I136: =VLOOKUP(B136,Base!$A$3:$F$994, 5, false) -> 0 | J136: =I136*D136 -> 0 | L136: =VLOOKUP(M136,Base!$A$3:$F$994, 6, false) -> 0 | M136: . | P136: =VLOOKUP(M136,Base!$A$3:$F$994, 2, false) -> . | T136: =VLOOKUP(M136,Base!$A$3:$F$994, 5, false) -> 0 | U136: =T136*O136 -> 0 | W136: =VLOOKUP(X136,Base!$A$3:$F$994, 6, false) -> 0 | X136: . | AA136: =VLOOKUP(X136,Base!$A$3:$F$994, 2, false) -> . | AE136: =VLOOKUP(X136,Base!$A$3:$F$994, 5, false) -> 0 | AF136: =AE136*Z136 -> 0
A137: =VLOOKUP(B137,Base!$A$3:$F$994, 6, false) -> 0 | B137: . | E137: =VLOOKUP(B137,Base!$A$3:$F$994, 2, false) -> . | I137: =VLOOKUP(B137,Base!$A$3:$F$994, 5, false) -> 0 | J137: =I137*D137 -> 0 | L137: =VLOOKUP(M137,Base!$A$3:$F$994, 6, false) -> 0 | M137: . | P137: =VLOOKUP(M137,Base!$A$3:$F$994, 2, false) -> . | T137: =VLOOKUP(M137,Base!$A$3:$F$994, 5, false) -> 0 | U137: =T137*O137 -> 0 | W137: =VLOOKUP(X137,Base!$A$3:$F$994, 6, false) -> 0 | X137: . | AA137: =VLOOKUP(X137,Base!$A$3:$F$994, 2, false) -> . | AE137: =VLOOKUP(X137,Base!$A$3:$F$994, 5, false) -> 0 | AF137: =AE137*Z137 -> 0
A138: =VLOOKUP(B138,Base!$A$3:$F$994, 6, false) -> 0 | B138: . | E138: =VLOOKUP(B138,Base!$A$3:$F$994, 2, false) -> . | I138: =VLOOKUP(B138,Base!$A$3:$F$994, 5, false) -> 0 | J138: =I138*D138 -> 0 | L138: =VLOOKUP(M138,Base!$A$3:$F$994, 6, false) -> 0 | M138: . | P138: =VLOOKUP(M138,Base!$A$3:$F$994, 2, false) -> . | T138: =VLOOKUP(M138,Base!$A$3:$F$994, 5, false) -> 0 | U138: =T138*O138 -> 0 | W138: =VLOOKUP(X138,Base!$A$3:$F$994, 6, false) -> 0 | X138: . | AA138: =VLOOKUP(X138,Base!$A$3:$F$994, 2, false) -> . | AE138: =VLOOKUP(X138,Base!$A$3:$F$994, 5, false) -> 0 | AF138: =AE138*Z138 -> 0
A139: =VLOOKUP(B139,Base!$A$3:$F$994, 6, false) -> 0 | B139: . | E139: =VLOOKUP(B139,Base!$A$3:$F$994, 2, false) -> . | I139: =VLOOKUP(B139,Base!$A$3:$F$994, 5, false) -> 0 | J139: =I139*D139 -> 0 | L139: =VLOOKUP(M139,Base!$A$3:$F$994, 6, false) -> 0 | M139: . | P139: =VLOOKUP(M139,Base!$A$3:$F$994, 2, false) -> . | T139: =VLOOKUP(M139,Base!$A$3:$F$994, 5, false) -> 0 | U139: =T139*O139 -> 0 | W139: =VLOOKUP(X139,Base!$A$3:$F$994, 6, false) -> 0 | X139: . | AA139: =VLOOKUP(X139,Base!$A$3:$F$994, 2, false) -> . | AE139: =VLOOKUP(X139,Base!$A$3:$F$994, 5, false) -> 0 | AF139: =AE139*Z139 -> 0
A140: =VLOOKUP(B140,Base!$A$3:$F$994, 6, false) -> 0 | B140: . | E140: =VLOOKUP(B140,Base!$A$3:$F$994, 2, false) -> . | I140: =VLOOKUP(B140,Base!$A$3:$F$994, 5, false) -> 0 | J140: =I140*D140 -> 0 | L140: =VLOOKUP(M140,Base!$A$3:$F$994, 6, false) -> 0 | M140: . | P140: =VLOOKUP(M140,Base!$A$3:$F$994, 2, false) -> . | T140: =VLOOKUP(M140,Base!$A$3:$F$994, 5, false) -> 0 | U140: =T140*O140 -> 0 | W140: =VLOOKUP(X140,Base!$A$3:$F$994, 6, false) -> 0 | X140: . | AA140: =VLOOKUP(X140,Base!$A$3:$F$994, 2, false) -> . | AE140: =VLOOKUP(X140,Base!$A$3:$F$994, 5, false) -> 0 | AF140: =AE140*Z140 -> 0
A141: =VLOOKUP(B141,Base!$A$3:$F$994, 6, false) -> 0 | B141: . | E141: =VLOOKUP(B141,Base!$A$3:$F$994, 2, false) -> . | I141: =VLOOKUP(B141,Base!$A$3:$F$994, 5, false) -> 0 | J141: =I141*D141 -> 0 | L141: =VLOOKUP(M141,Base!$A$3:$F$994, 6, false) -> 0 | M141: . | P141: =VLOOKUP(M141,Base!$A$3:$F$994, 2, false) -> . | T141: =VLOOKUP(M141,Base!$A$3:$F$994, 5, false) -> 0 | U141: =T141*O141 -> 0 | W141: =VLOOKUP(X141,Base!$A$3:$F$994, 6, false) -> 0 | X141: . | AA141: =VLOOKUP(X141,Base!$A$3:$F$994, 2, false) -> . | AE141: =VLOOKUP(X141,Base!$A$3:$F$994, 5, false) -> 0 | AF141: =AE141*Z141 -> 0
A142: =VLOOKUP(B142,Base!$A$3:$F$994, 6, false) -> 0 | B142: . | E142: =VLOOKUP(B142,Base!$A$3:$F$994, 2, false) -> . | I142: =VLOOKUP(B142,Base!$A$3:$F$994, 5, false) -> 0 | J142: =I142*D142 -> 0 | L142: =VLOOKUP(M142,Base!$A$3:$F$994, 6, false) -> 0 | M142: . | P142: =VLOOKUP(M142,Base!$A$3:$F$994, 2, false) -> . | T142: =VLOOKUP(M142,Base!$A$3:$F$994, 5, false) -> 0 | U142: =T142*O142 -> 0 | W142: =VLOOKUP(X142,Base!$A$3:$F$994, 6, false) -> 0 | X142: . | AA142: =VLOOKUP(X142,Base!$A$3:$F$994, 2, false) -> . | AE142: =VLOOKUP(X142,Base!$A$3:$F$994, 5, false) -> 0 | AF142: =AE142*Z142 -> 0
A143: =VLOOKUP(B143,Base!$A$3:$F$994, 6, false) -> 0 | B143: . | E143: =VLOOKUP(B143,Base!$A$3:$F$994, 2, false) -> . | I143: =VLOOKUP(B143,Base!$A$3:$F$994, 5, false) -> 0 | J143: =I143*D143 -> 0 | L143: =VLOOKUP(M143,Base!$A$3:$F$994, 6, false) -> 0 | M143: . | P143: =VLOOKUP(M143,Base!$A$3:$F$994, 2, false) -> . | T143: =VLOOKUP(M143,Base!$A$3:$F$994, 5, false) -> 0 | U143: =T143*O143 -> 0 | W143: =VLOOKUP(X143,Base!$A$3:$F$994, 6, false) -> 0 | X143: . | AA143: =VLOOKUP(X143,Base!$A$3:$F$994, 2, false) -> . | AE143: =VLOOKUP(X143,Base!$A$3:$F$994, 5, false) -> 0 | AF143: =AE143*Z143 -> 0
A144: =VLOOKUP(B144,Base!$A$3:$F$994, 6, false) -> 0 | B144: . | E144: =VLOOKUP(B144,Base!$A$3:$F$994, 2, false) -> . | I144: =VLOOKUP(B144,Base!$A$3:$F$994, 5, false) -> 0 | J144: =I144*D144 -> 0 | L144: =VLOOKUP(M144,Base!$A$3:$F$994, 6, false) -> 0 | M144: . | P144: =VLOOKUP(M144,Base!$A$3:$F$994, 2, false) -> . | T144: =VLOOKUP(M144,Base!$A$3:$F$994, 5, false) -> 0 | U144: =T144*O144 -> 0 | W144: =VLOOKUP(X144,Base!$A$3:$F$994, 6, false) -> 0 | X144: . | AA144: =VLOOKUP(X144,Base!$A$3:$F$994, 2, false) -> . | AE144: =VLOOKUP(X144,Base!$A$3:$F$994, 5, false) -> 0 | AF144: =AE144*Z144 -> 0
A145: =VLOOKUP(B145,Base!$A$3:$F$994, 6, false) -> 0 | B145: . | E145: =VLOOKUP(B145,Base!$A$3:$F$994, 2, false) -> . | I145: =VLOOKUP(B145,Base!$A$3:$F$994, 5, false) -> 0 | J145: =I145*D145 -> 0 | L145: =VLOOKUP(M145,Base!$A$3:$F$994, 6, false) -> 0 | M145: . | P145: =VLOOKUP(M145,Base!$A$3:$F$994, 2, false) -> . | T145: =VLOOKUP(M145,Base!$A$3:$F$994, 5, false) -> 0 | U145: =T145*O145 -> 0 | W145: =VLOOKUP(X145,Base!$A$3:$F$994, 6, false) -> 0 | X145: . | AA145: =VLOOKUP(X145,Base!$A$3:$F$994, 2, false) -> . | AE145: =VLOOKUP(X145,Base!$A$3:$F$994, 5, false) -> 0 | AF145: =AE145*Z145 -> 0
A146: =VLOOKUP(B146,Base!$A$3:$F$994, 6, false) -> 0 | B146: . | E146: =VLOOKUP(B146,Base!$A$3:$F$994, 2, false) -> . | F146: PREPARACIÒN | I146: =VLOOKUP(B146,Base!$A$3:$F$994, 5, false) -> 0 | J146: =I146*D146 -> 0 | L146: =VLOOKUP(M146,Base!$A$3:$F$994, 6, false) -> 0 | M146: . | P146: =VLOOKUP(M146,Base!$A$3:$F$994, 2, false) -> . | Q146: PREPARACIÒN | T146: =VLOOKUP(M146,Base!$A$3:$F$994, 5, false) -> 0 | U146: =T146*O146 -> 0 | W146: =VLOOKUP(X146,Base!$A$3:$F$994, 6, false) -> 0 | X146: . | AA146: =VLOOKUP(X146,Base!$A$3:$F$994, 2, false) -> . | AB146: PREPARACIÒN | AE146: =VLOOKUP(X146,Base!$A$3:$F$994, 5, false) -> 0 | AF146: =AE146*Z146 -> 0
A147: =VLOOKUP(B147,Base!$A$3:$F$994, 6, false) -> 0 | B147: . | E147: =VLOOKUP(B147,Base!$A$3:$F$994, 2, false) -> . | I147: =VLOOKUP(B147,Base!$A$3:$F$994, 5, false) -> 0 | J147: =I147*D147 -> 0 | L147: =VLOOKUP(M147,Base!$A$3:$F$994, 6, false) -> 0 | M147: . | P147: =VLOOKUP(M147,Base!$A$3:$F$994, 2, false) -> . | T147: =VLOOKUP(M147,Base!$A$3:$F$994, 5, false) -> 0 | U147: =T147*O147 -> 0 | W147: =VLOOKUP(X147,Base!$A$3:$F$994, 6, false) -> 0 | X147: . | AA147: =VLOOKUP(X147,Base!$A$3:$F$994, 2, false) -> . | AE147: =VLOOKUP(X147,Base!$A$3:$F$994, 5, false) -> 0 | AF147: =AE147*Z147 -> 0
A148: =VLOOKUP(B148,Base!$A$3:$F$994, 6, false) -> 0 | B148: . | E148: =VLOOKUP(B148,Base!$A$3:$F$994, 2, false) -> . | I148: =VLOOKUP(B148,Base!$A$3:$F$994, 5, false) -> 0 | J148: =I148*D148 -> 0 | L148: =VLOOKUP(M148,Base!$A$3:$F$994, 6, false) -> 0 | M148: . | P148: =VLOOKUP(M148,Base!$A$3:$F$994, 2, false) -> . | T148: =VLOOKUP(M148,Base!$A$3:$F$994, 5, false) -> 0 | U148: =T148*O148 -> 0 | W148: =VLOOKUP(X148,Base!$A$3:$F$994, 6, false) -> 0 | X148: . | AA148: =VLOOKUP(X148,Base!$A$3:$F$994, 2, false) -> . | AE148: =VLOOKUP(X148,Base!$A$3:$F$994, 5, false) -> 0 | AF148: =AE148*Z148 -> 0
A149: =VLOOKUP(B149,Base!$A$3:$F$994, 6, false) -> 0 | B149: . | E149: =VLOOKUP(B149,Base!$A$3:$F$994, 2, false) -> . | I149: =VLOOKUP(B149,Base!$A$3:$F$994, 5, false) -> 0 | J149: =I149*D149 -> 0 | L149: =VLOOKUP(M149,Base!$A$3:$F$994, 6, false) -> 0 | M149: . | P149: =VLOOKUP(M149,Base!$A$3:$F$994, 2, false) -> . | T149: =VLOOKUP(M149,Base!$A$3:$F$994, 5, false) -> 0 | U149: =T149*O149 -> 0 | W149: =VLOOKUP(X149,Base!$A$3:$F$994, 6, false) -> 0 | X149: . | AA149: =VLOOKUP(X149,Base!$A$3:$F$994, 2, false) -> . | AE149: =VLOOKUP(X149,Base!$A$3:$F$994, 5, false) -> 0 | AF149: =AE149*Z149 -> 0
...

Sheet CONCENTRADO DE SUB Y GUA
A1: NOMBRE DEL ESTABLECIMIENTO
B3: SUB-RECETAS | G3: GUARNICIONES
B4: Código | C4: Nombre/Producto | D4: Unidad | E4: Total de costo | G4: Código | H4: Nombre/Producto | I4: Unidad | J4: Total de costo
B5: 1 | G5: 1
B6: 2 | G6: 2
B7: 3 | G7: 3
B8: 4 | G8: 4
B9: 5 | G9: 5
B10: 6 | G10: 6
B11: 7 | G11: 7
B12: 8 | G12: 8
B13: 9 | G13: 9
B14: 10 | G14: 10
B15: 11 | G15: 11
B16: 12 | G16: 12
... B34: 30 | G34: 30

Sheet REC ALIMENTOS
A1: NOMBRE DEL ESTABLECIMIENTO
A2: PRIMER TIEMPO | L2: SEGUNDO TIEMPO | W2: TERCER TIEMPO | AH2: CUARTO TIEMPO | AS2: QUINTO TIEMPO | BD2: SEXTO TIEMPO
I3: IMPUESTO | J3: 0.16 | T3: IMPUESTO: | U3: =$J$3 -> 0.16 | AE3: IMPUESTO: | AF3: =$J$3 -> 0.16 | AP3: IMPUESTO: | AQ3: =$J$3 -> 0.16 | BA3: IMPUESTO: | BB3: =$J$3 -> 0.16 | BL3: IMPUESTO: | BM3: =$J$3 -> 0.16
A4: NOMBRE: | F4: FECHA: | G4: 42399 | I4: FACTOR DE VENTA | J4: % DE COSTO | L4: NOMBRE: | Q4: FECHA: | R4: =$G$4 -> 42399 | T4: FACTOR DE VENTA | U4: % DE COSTO | W4: NOMBRE: | AB4: FECHA: | AC4: =$G$4 -> 42399 | AE4: FACTOR DE VENTA | AF4: % DE COSTO | AH4: NOMBRE: | AM4: FECHA: | AN4: =$G$4 -> 42399 | AP4: FACTOR DE VENTA | AQ4: % DE COSTO | AS4: NOMBRE: | AX4: FECHA: | AY4: =$G$4 -> 42399 | BA4: FACTOR DE VENTA | BB4: % DE COSTO | BD4: NOMBRE: | BI4: FECHA: | BJ4: =$G$4 -> 42399 | BL4: FACTOR DE VENTA | BM4: % DE COSTO
A5: CÓDIGO DE RECETA: | D5: PORCIONES: | I5: =1/J5 -> 3.3333333 | J5: 0.3 | L5: CÓDIGO DE RECETA: | O5: PORCIONES: | P5: 10 | T5: =1/U5 -> 3.3333333 | U5: =$J$5 -> 0.3 | W5: CÓDIGO DE RECETA: | Z5: PORCIONES: | AA5: 10 | AE5: =1/AF5 -> 3.3333333 | AF5: =$J$5 -> 0.3 | AH5: CÓDIGO DE RECETA: | AK5: PORCIONES: | AL5: 10 | AP5: =1/AQ5 -> 3.3333333 | AQ5: =$J$5 -> 0.3 | AS5: CÓDIGO DE RECETA: | AV5: PORCIONES: | AW5: 10 | BA5: =1/BB5 -> 3.3333333 | BB5: =$J$5 -> 0.3 | BD5: CÓDIGO DE RECETA: | BG5: PORCIONES: | BH5: 10 | BL5: =1/BM5 -> 3.3333333 | BM5: =$J$5 -> 0.3
A6: CÓDIGO | B6: INGREDIENTES | D6: CANTIDAD | E6: UNIDAD | F6: EQUIPO Y UTENSILIOS | I6: COSTO NETO | J6: IMPORTE | L6: CÓDIGO | M6: INGREDIENTES | O6: CANTIDAD | P6: UNIDAD | Q6: EQUIPO Y UTENSILIOS | T6: COSTO NETO | U6: IMPORTE | W6: CÓDIGO | X6: INGREDIENTES | Z6: CANTIDAD | AA6: UNIDAD | AB6: EQUIPO Y UTENSILIOS | AE6: COSTO NETO | AF6: IMPORTE | AH6: CÓDIGO | AI6: INGREDIENTES | AK6: CANTIDAD | AL6: UNIDAD | AM6: EQUIPO Y UTENSILIOS | AP6: COSTO NETO | AQ6: IMPORTE | AS6: CÓDIGO | AT6: INGREDIENTES | AV6: CANTIDAD | AW6: UNIDAD | AX6: EQUIPO Y UTENSILIOS | BA6: COSTO NETO | BB6: IMPORTE | BD6: CÓDIGO | BE6: INGREDIENTES | BG6: CANTIDAD | BH6: UNIDAD | BI6: EQUIPO Y UTENSILIOS | BL6: COSTO NETO | BM6: IMPORTE
A7: =VLOOKUP(B7,Base!$A$3:$F$994, 6, false) -> #N/A | B7: Azucar | D7: 0.200 | E7: =VLOOKUP(B7,Base!$A$3:$F$994, 2, false) -> #N/A | F7: Cuchara | I7: =VLOOKUP(B7,Base!$A$3:$F$994, 5, false) -> #N/A | J7: =I7*D7 -> #N/A | L7: =VLOOKUP(M7,Base!$A$3:$F$994, 6, false) -> 0 | M7: . | P7: =VLOOKUP(M7,Base!$A$3:$F$994, 2, false) -> . | T7: =VLOOKUP(M7,Base!$A$3:$F$994, 5, false) -> 0 | U7: =T7*O7 -> 0 | W7: =VLOOKUP(X7,Base!$A$3:$F$994, 6, false) -> 0 | X7: . | AA7: =VLOOKUP(X7,Base!$A$3:$F$994, 2, false) -> . | AE7: =VLOOKUP(X7,Base!$A$3:$F$994, 5, false) -> 0 | AF7: =AE7*Z7 -> 0 | AH7: =VLOOKUP(AI7,Base!$A$3:$F$994, 6, false) -> 0 | AI7: . | AL7: =VLOOKUP(AI7,Base!$A$3:$F$994, 2, false) -> . | AP7: =VLOOKUP(AI7,Base!$A$3:$F$994, 5, false) -> 0 | AQ7: =AP7*AK7 -> 0 | AS7: =VLOOKUP(AT7,Base!$A$3:$F$994, 6, false) -> 0 | AT7: . | AW7: =VLOOKUP(AT7,Base!$A$3:$F$994, 2, false) -> . | BA7: =VLOOKUP(AT7,Base!$A$3:$F$994, 5, false) -> 0 | BB7: =BA7*AV7 -> 0 | BD7: =VLOOKUP(BE7,Base!$A$3:$F$994, 6, false) -> 0 | BE7: . | BH7: =VLOOKUP(BE7,Base!$A$3:$F$994, 2, false) -> . | BL7: =VLOOKUP(BE7,Base!$A$3:$F$994, 5, false) -> 0 | BM7: =BL7*BG7 -> 0
A8: =VLOOKUP(B8,Base!$A$3:$F$994, 6, false) -> 0 | B8: . | E8: =VLOOKUP(B8,Base!$A$3:$F$994, 2, false) -> . | F8: Cuchillo de chef | I8: =VLOOKUP(B8,Base!$A$3:$F$994, 5, false) -> 0 | J8: =I8*D8 -> 0 | L8: =VLOOKUP(M8,Base!$A$3:$F$994, 6, false) -> 0 | M8: . | P8: =VLOOKUP(M8,Base!$A$3:$F$994, 2, false) -> . | T8: =VLOOKUP(M8,Base!$A$3:$F$994, 5, false) -> 0 | U8: =T8*O8 -> 0 | W8: =VLOOKUP(X8,Base!$A$3:$F$994, 6, false) -> 0 | X8: . | AA8: =VLOOKUP(X8,Base!$A$3:$F$994, 2, false) -> . | AE8: =VLOOKUP(X8,Base!$A$3:$F$994, 5, false) -> 0 | AF8: =AE8*Z8 -> 0 | AH8: =VLOOKUP(AI8,Base!$A$3:$F$994, 6, false) -> 0 | AI8: . | AL8: =VLOOKUP(AI8,Base!$A$3:$F$994, 2, false) -> . | AP8: =VLOOKUP(AI8,Base!$A$3:$F$994, 5, false) -> 0 | AQ8: =AP8*AK8 -> 0 | AS8: =VLOOKUP(AT8,Base!$A$3:$F$994, 6, false) -> 0 | AT8: . | AW8: =VLOOKUP(AT8,Base!$A$3:$F$994, 2, false) -> . | BA8: =VLOOKUP(AT8,Base!$A$3:$F$994, 5, false) -> 0 | BB8: =BA8*AV8 -> 0 | BD8: =VLOOKUP(BE8,Base!$A$3:$F$994, 6, false) -> 0 | BE8: . | BH8: =VLOOKUP(BE8,Base!$A$3:$F$994, 2, false) -> . | BL8: =VLOOKUP(BE8,Base!$A$3:$F$994, 5, false) -> 0 | BM8: =BL8*BG8 -> 0
A9: =VLOOKUP(B9,Base!$A$3:$F$994, 6, false) -> 0 | B9: . | E9: =VLOOKUP(B9,Base!$A$3:$F$994, 2, false) -> . | F9: Olla | I9: =VLOOKUP(B9,Base!$A$3:$F$994, 5, false) -> 0 | J9: =I9*D9 -> 0 | L9: =VLOOKUP(M9,Base!$A$3:$F$994, 6, false) -> 0 | M9: . | O9: 0 | P9: =VLOOKUP(M9,Base!$A$3:$F$994, 2, false) -> . | T9: =VLOOKUP(M9,Base!$A$3:$F$994, 5, false) -> 0 | U9: =T9*O9 -> 0 | W9: =VLOOKUP(X9,Base!$A$3:$F$994, 6, false) -> 0 | X9: . | AA9: =VLOOKUP(X9,Base!$A$3:$F$994, 2, false) -> . | AE9: =VLOOKUP(X9,Base!$A$3:$F$994, 5, false) -> 0 | AF9: =AE9*Z9 -> 0 | AH9: =VLOOKUP(AI9,Base!$A$3:$F$994, 6, false) -> 0 | AI9: . | AL9: =VLOOKUP(AI9,Base!$A$3:$F$994, 2, false) -> . | AP9: =VLOOKUP(AI9,Base!$A$3:$F$994, 5, false) -> 0 | AQ9: =AP9*AK9 -> 0 | AS9: =VLOOKUP(AT9,Base!$A$3:$F$994, 6, false) -> 0 | AT9: . | AW9: =VLOOKUP(AT9,Base!$A$3:$F$994, 2, false) -> . | BA9: =VLOOKUP(AT9,Base!$A$3:$F$994, 5, false) -> 0 | BB9: =BA9*AV9 -> 0 | BD9: =VLOOKUP(BE9,Base!$A$3:$F$994, 6, false) -> 0 | BE9: . | BH9: =VLOOKUP(BE9,Base!$A$3:$F$994, 2, false) -> . | BL9: =VLOOKUP(BE9,Base!$A$3:$F$994, 5, false) -> 0 | BM9: =BL9*BG9 -> 0
A10: =VLOOKUP(B10,Base!$A$3:$F$994, 6, false) -> 0 | B10: . | E10: =VLOOKUP(B10,Base!$A$3:$F$994, 2, false) -> . | F10: Tabla para cortar verdura | I10: =VLOOKUP(B10,Base!$A$3:$F$994, 5, false) -> 0 | J10: =I10*D10 -> 0 | L10: =VLOOKUP(M10,Base!$A$3:$F$994, 6, false) -> 0 | M10: . | P10: =VLOOKUP(M10,Base!$A$3:$F$994, 2, false) -> . | T10: =VLOOKUP(M10,Base!$A$3:$F$994, 5, false) -> 0 | U10: =T10*O10 -> 0 | W10: =VLOOKUP(X10,Base!$A$3:$F$994, 6, false) -> 0 | X10: . | AA10: =VLOOKUP(X10,Base!$A$3:$F$994, 2, false) -> . | AE10: =VLOOKUP(X10,Base!$A$3:$F$994, 5, false) -> 0 | AF10: =AE10*Z10 -> 0 | AH10: =VLOOKUP(AI10,Base!$A$3:$F$994, 6, false) -> 0 | AI10: . | AL10: =VLOOKUP(AI10,Base!$A$3:$F$994, 2, false) -> . | AP10: =VLOOKUP(AI10,Base!$A$3:$F$994, 5, false) -> 0 | AQ10: =AP10*AK10 -> 0 | AS10: =VLOOKUP(AT10,Base!$A$3:$F$994, 6, false) -> 0 | AT10: . | AW10: =VLOOKUP(AT10,Base!$A$3:$F$994, 2, false) -> . | BA10: =VLOOKUP(AT10,Base!$A$3:$F$994, 5, false) -> 0 | BB10: =BA10*AV10 -> 0 | BD10: =VLOOKUP(BE10,Base!$A$3:$F$994, 6, false) -> 0 | BE10: . | BH10: =VLOOKUP(BE10,Base!$A$3:$F$994, 2, false) -> . | BL10: =VLOOKUP(BE10,Base!$A$3:$F$994, 5, false) -> 0 | BM10: =BL10*BG10 -> 0
A11: =VLOOKUP(B11,Base!$A$3:$F$994, 6, false) -> 0 | B11: . | E11: =VLOOKUP(B11,Base!$A$3:$F$994, 2, false) -> . | F11: Parrilla | I11: =VLOOKUP(B11,Base!$A$3:$F$994, 5, false) -> 0 | J11: =I11*D11 -> 0 | L11: =VLOOKUP(M11,Base!$A$3:$F$994, 6, false) -> 0 | M11: . | P11: =VLOOKUP(M11,Base!$A$3:$F$994, 2, false) -> . | T11: =VLOOKUP(M11,Base!$A$3:$F$994, 5, false) -> 0 | U11: =T11*O11 -> 0 | W11: =VLOOKUP(X11,Base!$A$3:$F$994, 6, false) -> 0 | X11: . | AA11: =VLOOKUP(X11,Base!$A$3:$F$994, 2, false) -> . | AE11: =VLOOKUP(X11,Base!$A$3:$F$994, 5, false) -> 0 | AF11: =AE11*Z11 -> 0 | AH11: =VLOOKUP(AI11,Base!$A$3:$F$994, 6, false) -> 0 | AI11: . | AL11: =VLOOKUP(AI11,Base!$A$3:$F$994, 2, false) -> . | AP11: =VLOOKUP(AI11,Base!$A$3:$F$994, 5, false) -> 0 | AQ11: =AP11*AK11 -> 0 | AS11: =VLOOKUP(AT11,Base!$A$3:$F$994, 6, false) -> 0 | AT11: . | AW11: =VLOOKUP(AT11,Base!$A$3:$F$994, 2, false) -> . | BA11: =VLOOKUP(AT11,Base!$A$3:$F$994, 5, false) -> 0 | BB11: =BA11*AV11 -> 0 | BD11: =VLOOKUP(BE11,Base!$A$3:$F$994, 6, false) -> 0 | BE11: . | BH11: =VLOOKUP(BE11,Base!$A$3:$F$994, 2, false) -> . | BL11: =VLOOKUP(BE11,Base!$A$3:$F$994, 5, false) -> 0 | BM11: =BL11*BG11 -> 0
A12: =VLOOKUP(B12,Base!$A$3:$F$994, 6, false) -> 0 | B12: . | E12: =VLOOKUP(B12,Base!$A$3:$F$994, 2, false) -> . | I12: =VLOOKUP(B12,Base!$A$3:$F$994, 5, false) -> 0 | J12: =I12*D12 -> 0 | L12: =VLOOKUP(M12,Base!$A$3:$F$994, 6, false) -> 0 | M12: . | P12: =VLOOKUP(M12,Base!$A$3:$F$994, 2, false) -> . | T12: =VLOOKUP(M12,Base!$A$3:$F$994, 5, false) -> 0 | U12: =T12*O12 -> 0 | W12: =VLOOKUP(X12,Base!$A$3:$F$994, 6, false) -> 0 | X12: . | AA12: =VLOOKUP(X12,Base!$A$3:$F$994, 2, false) -> . | AE12: =VLOOKUP(X12,Base!$A$3:$F$994, 5, false) -> 0 | AF12: =AE12*Z12 -> 0 | AH12: =VLOOKUP(AI12,Base!$A$3:$F$994, 6, false) -> 0 | AI12: . | AL12: =VLOOKUP(AI12,Base!$A$3:$F$994, 2, false) -> . | AP12: =VLOOKUP(AI12,Base!$A$3:$F$994, 5, false) -> 0 | AQ12: =AP12*AK12 -> 0 | AS12: =VLOOKUP(AT12,Base!$A$3:$F$994, 6, false) -> 0 | AT12: . | AW12: =VLOOKUP(AT12,Base!$A$3:$F$994, 2, false) -> . | BA12: =VLOOKUP(AT12,Base!$A$3:$F$994, 5, false) -> 0 | BB12: =BA12*AV12 -> 0 | BD12: =VLOOKUP(BE12,Base!$A$3:$F$994, 6, false) -> 0 | BE12: . | BH12: =VLOOKUP(BE12,Base!$A$3:$F$994, 2, false) -> . | BL12: =VLOOKUP(BE12,Base!$A$3:$F$994, 5, false) -> 0 | BM12: =BL12*BG12 -> 0
A13: =VLOOKUP(B13,Base!$A$3:$F$994, 6, false) -> 0 | B13: . | E13: =VLOOKUP(B13,Base!$A$3:$F$994, 2, false) -> . | I13: =VLOOKUP(B13,Base!$A$3:$F$994, 5, false) -> 0 | J13: =I13*D13 -> 0 | L13: =VLOOKUP(M13,Base!$A$3:$F$994, 6, false) -> 0 | M13: . | P13: =VLOOKUP(M13,Base!$A$3:$F$994, 2, false) -> . | T13: =VLOOKUP(M13,Base!$A$3:$F$994, 5, false) -> 0 | U13: =T13*O13 -> 0 | W13: =VLOOKUP(X13,Base!$A$3:$F$994, 6, false) -> 0 | X13: . | AA13: =VLOOKUP(X13,Base!$A$3:$F$994, 2, false) -> . | AE13: =VLOOKUP(X13,Base!$A$3:$F$994, 5, false) -> 0 | AF13: =AE13*Z13 -> 0 | AH13: =VLOOKUP(AI13,Base!$A$3:$F$994, 6, false) -> 0 | AI13: . | AL13: =VLOOKUP(AI13,Base!$A$3:$F$994, 2, false) -> . | AP13: =VLOOKUP(AI13,Base!$A$3:$F$994, 5, false) -> 0 | AQ13: =AP13*AK13 -> 0 | AS13: =VLOOKUP(AT13,Base!$A$3:$F$994, 6, false) -> 0 | AT13: . | AW13: =VLOOKUP(AT13,Base!$A$3:$F$994, 2, false) -> . | BA13: =VLOOKUP(AT13,Base!$A$3:$F$994, 5, false) -> 0 | BB13: =BA13*AV13 -> 0 | BD13: =VLOOKUP(BE13,Base!$A$3:$F$994, 6, false) -> 0 | BE13: . | BH13: =VLOOKUP(BE13,Base!$A$3:$F$994, 2, false) -> . | BL13: =VLOOKUP(BE13,Base!$A$3:$F$994, 5, false) -> 0 | BM13: =BL13*BG13 -> 0
A14: =VLOOKUP(B14,Base!$A$3:$F$994, 6, false) -> 0 | B14: . | E14: =VLOOKUP(B14,Base!$A$3:$F$994, 2, false) -> . | I14: =VLOOKUP(B14,Base!$A$3:$F$994, 5, false) -> 0 | J14: =I14*D14 -> 0 | L14: =VLOOKUP(M14,Base!$A$3:$F$994, 6, false) -> 0 | M14: . | P14: =VLOOKUP(M14,Base!$A$3:$F$994, 2, false) -> . | T14: =VLOOKUP(M14,Base!$A$3:$F$994, 5, false) -> 0 | U14: =T14*O14 -> 0 | W14: =VLOOKUP(X14,Base!$A$3:$F$994, 6, false) -> 0 | X14: . | AA14: =VLOOKUP(X14,Base!$A$3:$F$994, 2, false) -> . | AE14: =VLOOKUP(X14,Base!$A$3:$F$994, 5, false) -> 0 | AF14: =AE14*Z14 -> 0 | AH14: =VLOOKUP(AI14,Base!$A$3:$F$994, 6, false) -> 0 | AI14: . | AL14: =VLOOKUP(AI14,Base!$A$3:$F$994, 2, false) -> . | AP14: =VLOOKUP(AI14,Base!$A$3:$F$994, 5, false) -> 0 | AQ14: =AP14*AK14 -> 0 | AS14: =VLOOKUP(AT14,Base!$A$3:$F$994, 6, false) -> 0 | AT14: . | AW14: =VLOOKUP(AT14,Base!$A$3:$F$994, 2, false) -> . | BA14: =VLOOKUP(AT14,Base!$A$3:$F$994, 5, false) -> 0 | BB14: =BA14*AV14 -> 0 | BD14: =VLOOKUP(BE14,Base!$A$3:$F$994, 6, false) -> 0 | BE14: . | BH14: =VLOOKUP(BE14,Base!$A$3:$F$994, 2, false) -> . | BL14: =VLOOKUP(BE14,Base!$A$3:$F$994, 5, false) -> 0 | BM14: =BL14*BG14 -> 0
A15: =VLOOKUP(B15,Base!$A$3:$F$994, 6, false) -> 0 | B15: . | E15: =VLOOKUP(B15,Base!$A$3:$F$994, 2, false) -> . | I15: =VLOOKUP(B15,Base!$A$3:$F$994, 5, false) -> 0 | J15: =I15*D15 -> 0 | L15: =VLOOKUP(M15,Base!$A$3:$F$994, 6, false) -> 0 | M15: . | P15: =VLOOKUP(M15,Base!$A$3:$F$994, 2, false) -> . | T15: =VLOOKUP(M15,Base!$A$3:$F$994, 5, false) -> 0 | U15: =T15*O15 -> 0 | W15: =VLOOKUP(X15,Base!$A$3:$F$994, 6, false) -> 0 | X15: . | AA15: =VLOOKUP(X15,Base!$A$3:$F$994, 2, false) -> . | AE15: =VLOOKUP(X15,Base!$A$3:$F$994, 5, false) -> 0 | AF15: =AE15*Z15 -> 0 | AH15: =VLOOKUP(AI15,Base!$A$3:$F$994, 6, false) -> 0 | AI15: . | AL15: =VLOOKUP(AI15,Base!$A$3:$F$994, 2, false) -> . | AP15: =VLOOKUP(AI15,Base!$A$3:$F$994, 5, false) -> 0 | AQ15: =AP15*AK15 -> 0 | AS15: =VLOOKUP(AT15,Base!$A$3:$F$994, 6, false) -> 0 | AT15: . | AW15: =VLOOKUP(AT15,Base!$A$3:$F$994, 2, false) -> . | BA15: =VLOOKUP(AT15,Base!$A$3:$F$994, 5, false) -> 0 | BB15: =BA15*AV15 -> 0 | BD15: =VLOOKUP(BE15,Base!$A$3:$F$994, 6, false) -> 0 | BE15: . | BH15: =VLOOKUP(BE15,Base!$A$3:$F$994, 2, false) -> . | BL15: =VLOOKUP(BE15,Base!$A$3:$F$994, 5, false) -> 0 | BM15: =BL15*BG15 -> 0
A16: =VLOOKUP(B16,Base!$A$3:$F$994, 6, false) -> 0 | B16: . | E16: =VLOOKUP(B16,Base!$A$3:$F$994, 2, false) -> . | I16: =VLOOKUP(B16,Base!$A$3:$F$994, 5, false) -> 0 | J16: =I16*D16 -> 0 | L16: =VLOOKUP(M16,Base!$A$3:$F$994, 6, false) -> 0 | M16: . | P16: =VLOOKUP(M16,Base!$A$3:$F$994, 2, false) -> . | T16: =VLOOKUP(M16,Base!$A$3:$F$994, 5, false) -> 0 | U16: =T16*O16 -> 0 | W16: =VLOOKUP(X16,Base!$A$3:$F$994, 6, false) -> 0 | X16: . | AA16: =VLOOKUP(X16,Base!$A$3:$F$994, 2, false) -> . | AE16: =VLOOKUP(X16,Base!$A$3:$F$994, 5, false) -> 0 | AF16: =AE16*Z16 -> 0 | AH16: =VLOOKUP(AI16,Base!$A$3:$F$994, 6, false) -> 0 | AI16: . | AL16: =VLOOKUP(AI16,Base!$A$3:$F$994, 2, false) -> . | AP16: =VLOOKUP(AI16,Base!$A$3:$F$994, 5, false) -> 0 | AQ16: =AP16*AK17 -> 0 | AS16: =VLOOKUP(AT16,Base!$A$3:$F$994, 6, false) -> 0 | AT16: . | AW16: =VLOOKUP(AT16,Base!$A$3:$F$994, 2, false) -> . | BA16: =VLOOKUP(AT16,Base!$A$3:$F$994, 5, false) -> 0 | BB16: =BA16*AV16 -> 0 | BD16: =VLOOKUP(BE16,Base!$A$3:$F$994, 6, false) -> 0 | BE16: . | BH16: =VLOOKUP(BE16,Base!$A$3:$F$994, 2, false) -> . | BL16: =VLOOKUP(BE16,Base!$A$3:$F$994, 5, false) -> 0 | BM16: =BL16*BG16 -> 0
A17: =VLOOKUP(B17,Base!$A$3:$F$994, 6, false) -> 0 | B17: . | E17: =VLOOKUP(B17,Base!$A$3:$F$994, 2, false) -> . | F17: PREPARACIÒN | I17: =VLOOKUP(B17,Base!$A$3:$F$994, 5, false) -> 0 | J17: =I17*D17 -> 0 | L17: =VLOOKUP(M17,Base!$A$3:$F$994, 6, false) -> 0 | M17: . | P17: =VLOOKUP(M17,Base!$A$3:$F$994, 2, false) -> . | Q17: PREPARACIÒN | T17: =VLOOKUP(M17,Base!$A$3:$F$994, 5, false) -> 0 | U17: =T17*O17 -> 0 | W17: =VLOOKUP(X17,Base!$A$3:$F$994, 6, false) -> 0 | X17: . | AA17: =VLOOKUP(X17,Base!$A$3:$F$994, 2, false) -> . | AB17: PREPARACIÒN | AE17: =VLOOKUP(X17,Base!$A$3:$F$994, 5, false) -> 0 | AF17: =AE17*Z17 -> 0 | AH17: =VLOOKUP(AI17,Base!$A$3:$F$994, 6, false) -> 0 | AI17: . | AL17: =VLOOKUP(AI17,Base!$A$3:$F$994, 2, false) -> . | AM17: PREPARACIÒN | AP17: =VLOOKUP(AI17,Base!$A$3:$F$994, 5, false) -> 0 | AQ17: =AP17*AK17 -> 0 | AS17: =VLOOKUP(AT17,Base!$A$3:$F$994, 6, false) -> 0 | AT17: . | AW17: =VLOOKUP(AT17,Base!$A$3:$F$994, 2, false) -> . | AX17: PREPARACIÒN | BA17: =VLOOKUP(AT17,Base!$A$3:$F$994, 5, false) -> 0 | BB17: =BA17*AV17 -> 0 | BD17: =VLOOKUP(BE17,Base!$A$3:$F$994, 6, false) -> 0 | BE17: . | BH17: =VLOOKUP(BE17,Base!$A$3:$F$994, 2, false) -> . | BI17: PREPARACIÒN | BL17: =VLOOKUP(BE17,Base!$A$3:$F$994, 5, false) -> 0 | BM17: =BL17*BG17 -> 0
A18: =VLOOKUP(B18,Base!$A$3:$F$994, 6, false) -> 0 | B18: . | E18: =VLOOKUP(B18,Base!$A$3:$F$994, 2, false) -> . | F18: Cortar zanahoria en juliana | I18: =VLOOKUP(B18,Base!$A$3:$F$994, 5, false) -> 0 | J18: =I18*D18 -> 0 | L18: =VLOOKUP(M18,Base!$A$3:$F$994, 6, false) -> 0 | M18: . | P18: =VLOOKUP(M18,Base!$A$3:$F$994, 2, false) -> . | T18: =VLOOKUP(M18,Base!$A$3:$F$994, 5, false) -> 0 | U18: =T18*O18 -> 0 | W18: =VLOOKUP(X18,Base!$A$3:$F$994, 6, false) -> 0 | X18: . | AA18: =VLOOKUP(X18,Base!$A$3:$F$994, 2, false) -> . | AE18: =VLOOKUP(X18,Base!$A$3:$F$994, 5, false) -> 0 | AF18: =AE18*Z18 -> 0 | AH18: =VLOOKUP(AI18,Base!$A$3:$F$994, 6, false) -> 0 | AI18: . | AL18: =VLOOKUP(AI18,Base!$A$3:$F$994, 2, false) -> . | AP18: =VLOOKUP(AI18,Base!$A$3:$F$994, 5, false) -> 0 | AQ18: =AP18*AK18 -> 0 | AS18: =VLOOKUP(AT18,Base!$A$3:$F$994, 6, false) -> 0 | AT18: . | AW18: =VLOOKUP(AT18,Base!$A$3:$F$994, 2, false) -> . | BA18: =VLOOKUP(AT18,Base!$A$3:$F$994, 5, false) -> 0 | BB18: =BA18*AV18 -> 0 | BD18: =VLOOKUP(BE18,Base!$A$3:$F$994, 6, false) -> 0 | BE18: . | BH18: =VLOOKUP(BE18,Base!$A$3:$F$994, 2, false) -> . | BL18: =VLOOKUP(BE18,Base!$A$3:$F$994, 5, false) -> 0 | BM18: =BL18*BG18 -> 0
A19: =VLOOKUP(B19,Base!$A$3:$F$994, 6, false) -> 0 | B19: . | E19: =VLOOKUP(B19,Base!$A$3:$F$994, 2, false) -> . | F19: Cortar chayote en brunoise | I19: =VLOOKUP(B19,Base!$A$3:$F$994, 5, false) -> 0 | J19: =I19*D19 -> 0 | L19: =VLOOKUP(M19,Base!$A$3:$F$994, 6, false) -> 0 | M19: . | P19: =VLOOKUP(M19,Base!$A$3:$F$994, 2, false) -> . | T19: =VLOOKUP(M19,Base!$A$3:$F$994, 5, false) -> 0 | U19: =T19*O19 -> 0 | W19: =VLOOKUP(X19,Base!$A$3:$F$994, 6, false) -> 0 | X19: . | AA19: =VLOOKUP(X19,Base!$A$3:$F$994, 2, false) -> . | AE19: =VLOOKUP(X19,Base!$A$3:$F$994, 5, false) -> 0 | AF19: =AE19*Z19 -> 0 | AH19: =VLOOKUP(AI19,Base!$A$3:$F$994, 6, false) -> 0 | AI19: . | AL19: =VLOOKUP(AI19,Base!$A$3:$F$994, 2, false) -> . | AP19: =VLOOKUP(AI19,Base!$A$3:$F$994, 5, false) -> 0 | AQ19: =AP19*AK19 -> 0 | AS19: =VLOOKUP(AT19,Base!$A$3:$F$994, 6, false) -> 0 | AT19: . | AW19: =VLOOKUP(AT19,Base!$A$3:$F$994, 2, false) -> . | BA19: =VLOOKUP(AT19,Base!$A$3:$F$994, 5, false) -> 0 | BB19: =BA19*AV19 -> 0 | BD19: =VLOOKUP(BE19,Base!$A$3:$F$994, 6, false) -> 0 | BE19: . | BH19: =VLOOKUP(BE19,Base!$A$3:$F$994, 2, false) -> . | BL19: =VLOOKUP(BE19,Base!$A$3:$F$994, 5, false) -> 0 | BM19: =BL19*BG19 -> 0
A20: =VLOOKUP(B20,Base!$A$3:$F$994, 6, false) -> 0 | B20: . | E20: =VLOOKUP(B20,Base!$A$3:$F$994, 2, false) -> . | I20: =VLOOKUP(B20,Base!$A$3:$F$994, 5, false) -> 0 | J20: =I20*D20 -> 0 | L20: =VLOOKUP(M20,Base!$A$3:$F$994, 6, false) -> 0 | M20: . | P20: =VLOOKUP(M20,Base!$A$3:$F$994, 2, false) -> . | T20: =VLOOKUP(M20,Base!$A$3:$F$994, 5, false) -> 0 | U20: =T20*O20 -> 0 | W20: =VLOOKUP(X20,Base!$A$3:$F$994, 6, false) -> 0 | X20: . | AA20: =VLOOKUP(X20,Base!$A$3:$F$994, 2, false) -> . | AE20: =VLOOKUP(X20,Base!$A$3:$F$994, 5, false) -> 0 | AF20: =AE20*Z20 -> 0 | AH20: =VLOOKUP(AI20,Base!$A$3:$F$994, 6, false) -> 0 | AI20: . | AL20: =VLOOKUP(AI20,Base!$A$3:$F$994, 2, false) -> . | AP20: =VLOOKUP(AI20,Base!$A$3:$F$994, 5, false) -> 0 | AQ20: =AP20*AK20 -> 0 | AS20: =VLOOKUP(AT20,Base!$A$3:$F$994, 6, false) -> 0 | AT20: . | AW20: =VLOOKUP(AT20,Base!$A$3:$F$994, 2, false) -> . | BA20: =VLOOKUP(AT20,Base!$A$3:$F$994, 5, false) -> 0 | BB20: =BA20*AV20 -> 0 | BD20: =VLOOKUP(BE20,Base!$A$3:$F$994, 6, false) -> 0 | BE20: . | BH20: =VLOOKUP(BE20,Base!$A$3:$F$994, 2, false) -> . | BL20: =VLOOKUP(BE20,Base!$A$3:$F$994, 5, false) -> 0 | BM20: =BL20*BG20 -> 0
A21: =VLOOKUP(B21,Base!$A$3:$F$994, 6, false) -> 0 | B21: . | E21: =VLOOKUP(B21,Base!$A$3:$F$994, 2, false) -> . | I21: =VLOOKUP(B21,Base!$A$3:$F$994, 5, false) -> 0 | J21: =I21*D21 -> 0 | L21: =VLOOKUP(M21,Base!$A$3:$F$994, 6, false) -> 0 | M21: . | P21: =VLOOKUP(M21,Base!$A$3:$F$994, 2, false) -> . | T21: =VLOOKUP(M21,Base!$A$3:$F$994, 5, false) -> 0 | U21: =T21*O21 -> 0 | W21: =VLOOKUP(X21,Base!$A$3:$F$994, 6, false) -> 0 | X21: . | AA21: =VLOOKUP(X21,Base!$A$3:$F$994, 2, false) -> . | AE21: =VLOOKUP(X21,Base!$A$3:$F$994, 5, false) -> 0 | AF21: =AE21*Z21 -> 0 | AH21: =VLOOKUP(AI21,Base!$A$3:$F$994, 6, false) -> 0 | AI21: . | AL21: =VLOOKUP(AI21,Base!$A$3:$F$994, 2, false) -> . | AP21: =VLOOKUP(AI21,Base!$A$3:$F$994, 5, false) -> 0 | AQ21: =AP21*AK21 -> 0 | AS21: =VLOOKUP(AT21,Base!$A$3:$F$994, 6, false) -> 0 | AT21: . | AW21: =VLOOKUP(AT21,Base!$A$3:$F$994, 2, false) -> . | BA21: =VLOOKUP(AT21,Base!$A$3:$F$994, 5, false) -> 0 | BB21: =BA21*AV21 -> 0 | BD21: =VLOOKUP(BE21,Base!$A$3:$F$994, 6, false) -> 0 | BE21: . | BH21: =VLOOKUP(BE21,Base!$A$3:$F$994, 2, false) -> . | BL21: =VLOOKUP(BE21,Base!$A$3:$F$994, 5, false) -> 0 | BM21: =BL21*BG21 -> 0
A22: =VLOOKUP(B22,Base!$A$3:$F$994, 6, false) -> 0 | B22: . | E22: =VLOOKUP(B22,Base!$A$3:$F$994, 2, false) -> . | I22: =VLOOKUP(B22,Base!$A$3:$F$994, 5, false) -> 0 | J22: =I22*D22 -> 0 | L22: =VLOOKUP(M22,Base!$A$3:$F$994, 6, false) -> 0 | M22: . | P22: =VLOOKUP(M22,Base!$A$3:$F$994, 2, false) -> . | T22: =VLOOKUP(M22,Base!$A$3:$F$994, 5, false) -> 0 | U22: =T22*O22 -> 0 | W22: =VLOOKUP(X22,Base!$A$3:$F$994, 6, false) -> 0 | X22: . | AA22: =VLOOKUP(X22,Base!$A$3:$F$994, 2, false) -> . | AE22: =VLOOKUP(X22,Base!$A$3:$F$994, 5, false) -> 0 | AF22: =AE22*Z22 -> 0 | AH22: =VLOOKUP(AI22,Base!$A$3:$F$994, 6, false) -> 0 | AI22: . | AL22: =VLOOKUP(AI22,Base!$A$3:$F$994, 2, false) -> . | AP22: =VLOOKUP(AI22,Base!$A$3:$F$994, 5, false) -> 0 | AQ22: =AP22*AK22 -> 0 | AS22: =VLOOKUP(AT22,Base!$A$3:$F$994, 6, false) -> 0 | AT22: . | AW22: =VLOOKUP(AT22,Base!$A$3:$F$994, 2, false) -> . | BA22: =VLOOKUP(AT22,Base!$A$3:$F$994, 5, false) -> 0 | BB22: =BA22*AV22 -> 0 | BD22: =VLOOKUP(BE22,Base!$A$3:$F$994, 6, false) -> 0 | BE22: . | BH22: =VLOOKUP(BE22,Base!$A$3:$F$994, 2, false) -> . | BL22: =VLOOKUP(BE22,Base!$A$3:$F$994, 5, false) -> 0 | BM22: =BL22*BG22 -> 0
A23: =VLOOKUP(B23,Base!$A$3:$F$994, 6, false) -> 0 | B23: . | E23: =VLOOKUP(B23,Base!$A$3:$F$994, 2, false) -> . | I23: =VLOOKUP(B23,Base!$A$3:$F$994, 5, false) -> 0 | J23: =I23*D23 -> 0 | L23: =VLOOKUP(M23,Base!$A$3:$F$994, 6, false) -> 0 | M23: . | P23: =VLOOKUP(M23,Base!$A$3:$F$994, 2, false) -> . | T23: =VLOOKUP(M23,Base!$A$3:$F$994, 5, false) -> 0 | U23: =T23*O23 -> 0 | W23: =VLOOKUP(X23,Base!$A$3:$F$994, 6, false) -> 0 | X23: . | AA23: =VLOOKUP(X23,Base!$A$3:$F$994, 2, false) -> . | AE23: =VLOOKUP(X23,Base!$A$3:$F$994, 5, false) -> 0 | AF23: =AE23*Z23 -> 0 | AH23: =VLOOKUP(AI23,Base!$A$3:$F$994, 6, false) -> 0 | AI23: . | AL23: =VLOOKUP(AI23,Base!$A$3:$F$994, 2, false) -> . | AP23: =VLOOKUP(AI23,Base!$A$3:$F$994, 5, false) -> 0 | AQ23: =AP23*AK23 -> 0 | AS23: =VLOOKUP(AT23,Base!$A$3:$F$994, 6, false) -> 0 | AT23: . | AW23: =VLOOKUP(AT23,Base!$A$3:$F$994, 2, false) -> . | BA23: =VLOOKUP(AT23,Base!$A$3:$F$994, 5, false) -> 0 | BB23: =BA23*AV23 -> 0 | BD23: =VLOOKUP(BE23,Base!$A$3:$F$994, 6, false) -> 0 | BE23: . | BH23: =VLOOKUP(BE23,Base!$A$3:$F$994, 2, false) -> . | BL23: =VLOOKUP(BE23,Base!$A$3:$F$994, 5, false) -> 0 | BM23: =BL23*BG23 -> 0
A24: =VLOOKUP(B24,Base!$A$3:$F$994, 6, false) -> 0 | B24: . | E24: =VLOOKUP(B24,Base!$A$3:$F$994, 2, false) -> . | I24: =VLOOKUP(B24,Base!$A$3:$F$994, 5, false) -> 0 | J24: =I24*D24 -> 0 | L24: =VLOOKUP(M24,Base!$A$3:$F$994, 6, false) -> 0 | M24: . | P24: =VLOOKUP(M24,Base!$A$3:$F$994, 2, false) -> . | T24: =VLOOKUP(M24,Base!$A$3:$F$994, 5, false) -> 0 | U24: =T24*O24 -> 0 | W24: =VLOOKUP(X24,Base!$A$3:$F$994, 6, false) -> 0 | X24: . | AA24: =VLOOKUP(X24,Base!$A$3:$F$994, 2, false) -> . | AE24: =VLOOKUP(X24,Base!$A$3:$F$994, 5, false) -> 0 | AF24: =AE24*Z24 -> 0 | AH24: =VLOOKUP(AI24,Base!$A$3:$F$994, 6, false) -> 0 | AI24: . | AL24: =VLOOKUP(AI24,Base!$A$3:$F$994, 2, false) -> . | AP24: =VLOOKUP(AI24,Base!$A$3:$F$994, 5, false) -> 0 | AQ24: =AP24*AK24 -> 0 | AS24: =VLOOKUP(AT24,Base!$A$3:$F$994, 6, false) -> 0 | AT24: . | AW24: =VLOOKUP(AT24,Base!$A$3:$F$994, 2, false) -> . | BA24: =VLOOKUP(AT24,Base!$A$3:$F$994, 5, false) -> 0 | BB24: =BA24*AV24 -> 0 | BD24: =VLOOKUP(BE24,Base!$A$3:$F$994, 6, false) -> 0 | BE24: . | BH24: =VLOOKUP(BE24,Base!$A$3:$F$994, 2, false) -> . | BL24: =VLOOKUP(BE24,Base!$A$3:$F$994, 5, false) -> 0 | BM24: =BL24*BG24 -> 0
A25: ELABORACIÒN | I25: TOTAL DE MP: | J25: =SUM(J7:J24) -> #N/A | L25: ELABORACIÒN | T25: TOTAL DE MP: | U25: =SUM(U7:U24) -> 0 | W25: ELABORACIÒN | AE25: TOTAL DE MP: | AF25: =SUM(AF7:AF24) -> 0 | AH25: ELABORACIÒN | AP25: TOTAL DE MP: | AQ25: =SUM(AQ7:AQ24) -> 0 | AS25: ELABORACIÒN | BA25: TOTAL DE MP: | BB25: =SUM(BB7:BB24) -> 0 | BD25: ELABORACIÒN | BL25: TOTAL DE MP: | BM25: =SUM(BM7:BM24) -> 0
A26: Cocinar la juliana de zanahoria en agua hirbo | I26: TOTAL P/P: | J26: =J25/E5 -> #N/A | T26: TOTAL P/P: | U26: =U25/P5 -> 0 | AE26: TOTAL P/P: | AF26: =AF25/AA5 -> 0 | AP26: TOTAL P/P: | AQ26: =AQ25/AL5 -> 0 | BA26: TOTAL P/P: | BB26: =BB25/AW5 -> 0 | BL26: TOTAL P/P: | BM26: =BM25/BH5 -> 0
I27: IMPREVISTO: | J27: 0.05 | T27: IMPREVISTO: | U27: 0.05 | AE27: IMPREVISTO: | AF27: 0.05 | AP27: IMPREVISTO: | AQ27: 0.05 | BA27: IMPREVISTO: | BB27: 0.05 | BL27: IMPREVISTO: | BM27: 0.05
I28: TOTAL DE COSTO: | J28: =J26+(J26*J27) -> #N/A | T28: TOTAL DE COSTO: | U28: =U26+(U26*U27) -> 0 | AE28: TOTAL DE COSTO: | AF28: =AF26+(AF26*AF27) -> 0 | AP28: TOTAL DE COSTO: | AQ28: =AQ26+(AQ26*AQ27) -> 0 | BA28: TOTAL DE COSTO: | BB28: =BB26+(BB26*BB27) -> 0 | BL28: TOTAL DE COSTO: | BM28: =BM26+(BM26*BM27) -> 0
I29: PRECIO SUGERIDO: | J29: =J28*I5 -> #N/A | T29: PRECIO SUGERIDO: | U29: =U28*T5 -> 0 | AE29: PRECIO SUGERIDO: | AF29: =AF28*AE5 -> 0 | AP29: PRECIO SUGERIDO: | AQ29: =AQ28*AP5 -> 0 | BA29: PRECIO SUGERIDO: | BB29: =BB28*BA5 -> 0 | BL29: PRECIO SUGERIDO: | BM29: =BM28*BL5 -> 0
I30: IVA: | J30: =J31-J29 -> #N/A | T30: IVA: | U30: =U31-U29 -> 0 | AE30: IVA: | AF30: =AF31-AF29 -> 0 | AP30: IVA: | AQ30: =AQ31-AQ29 -> 0 | BA30: IVA: | BB30: =BB31-BB29 -> 0 | BL30: IVA: | BM30: =BM31-BM29 -> 0
I31: PRECIO SUGERIDO CON IVA: | J31: =J29*(J3*1+1) -> #N/A | T31: PRECIO SUGERIDO CON IVA: | U31: =U29*(U3*1+1) -> 0 | AE31: PRECIO SUGERIDO CON IVA: | AF31: =AF29*(AF3*1+1) -> 0 | AP31: PRECIO SUGERIDO CON IVA: | AQ31: =AQ29*(AQ3*1+1) -> 0 | BA31: PRECIO SUGERIDO CON IVA: | BB31: =BB29*(BB3*1+1) -> 0 | BL31: PRECIO SUGERIDO CON IVA: | BM31: =BM29*(BM3*1+1) -> 0
I32: AJUSTE A LA CARTA | T32: AJUSTE A LA CARTA | AE32: AJUSTE A LA CARTA | AP32: AJUSTE A LA CARTA | BA32: AJUSTE A LA CARTA | BL32: AJUSTE A LA CARTA
I33: PRECIO AJUSTADO: | J33: 50 | T33: PRECIO AJUSTADO: | AE33: PRECIO AJUSTADO: | AP33: PRECIO AJUSTADO: | BA33: PRECIO AJUSTADO: | BL33: PRECIO AJUSTADO:
A34: MONTAJE | I34: IVA: | J34: =J33-J35 -> 6.8965517 | L34: MONTAJE | T34: IVA: | U34: =U33-U35 -> 0 | W34: MONTAJE | AE34: IVA: | AF34: =AF33-AF35 -> 0 | AH34: MONTAJE | AP34: IVA: | AQ34: =AQ33-AQ35 -> 0 | AS34: MONTAJE | BA34: IVA: | BB34: =BB33-BB35 -> 0 | BD34: MONTAJE | BL34: IVA: | BM34: =BM33-BM35 -> 0
A35: Pineri | I35: PRECIO AJUSTADO SIN IVA: | J35: =J33/(J3*1+1) -> 43.103448 | T35: PRECIO AJUSTADO SIN IVA: | U35: =U33/(U3*1+1) -> 0 | AE35: PRECIO AJUSTADO SIN IVA: | AF35: =AF33/(AF3*1+1) -> 0 | AP35: PRECIO AJUSTADO SIN IVA: | AQ35: =AQ33/(AQ3*1+1) -> 0 | BA35: PRECIO AJUSTADO SIN IVA: | BB35: =BB33/(BB3*1+1) -> 0 | BL35: PRECIO AJUSTADO SIN IVA: | BM35: =BM33/(BM3*1+1) -> 0
I36: NUEVO % DE COSTO: | J36: =J28/J35 -> #N/A | T36: NUEVO % DE COSTO: | U36: =U28/U35 -> #DIV/0! | AE36: NUEVO % DE COSTO: | AF36: =AF28/AF35 -> #DIV/0! | AP36: NUEVO % DE COSTO: | AQ36: =AQ28/AQ35 -> #DIV/0! | BA36: NUEVO % DE COSTO: | BB36: =BB28/BB35 -> #DIV/0! | BL36: NUEVO % DE COSTO: | BM36: =BM28/BM35 -> #DIV/0!
I37: NUEVO FACTOR DE VENTA: | J37: =J35/J28 -> #N/A | T37: NUEVO FACTOR DE VENTA: | U37: =U35/U28 -> #DIV/0! | AE37: NUEVO FACTOR DE VENTA: | AF37: =AF35/AF28 -> #DIV/0! | AP37: NUEVO FACTOR DE VENTA: | AQ37: =AQ35/AQ28 -> #DIV/0! | BA37: NUEVO FACTOR DE VENTA: | BB37: =BB35/BB28 -> #DIV/0! | BL37: NUEVO FACTOR DE VENTA: | BM37: =BM35/BM28 -> #DIV/0!
A38: OBSERVACIONES | L38: OBSERVACIONES | W38: OBSERVACIONES | AH38: OBSERVACIONES | AS38: OBSERVACIONES | BD38: OBSERVACIONES
I46: IMPUESTO | J46: =$J$3 -> 0.16 | T46: IMPUESTO: | U46: =$J$3 -> 0.16 | AE46: IMPUESTO: | AF46: =$J$3 -> 0.16 | AP46: IMPUESTO: | AQ46: =$J$3 -> 0.16 | BA46: IMPUESTO: | BB46: =$J$3 -> 0.16 | BL46: IMPUESTO: | BM46: =$J$3 -> 0.16
A47: NOMBRE: | F47: FECHA: | G47: =$G$4 -> 42399 | I47: FACTOR DE VENTA | J47: % DE COSTO | L47: NOMBRE: | Q47: FECHA: | R47: =$G$4 -> 42399 | T47: FACTOR DE VENTA | U47: % DE COSTO | W47: NOMBRE: | AB47: FECHA: | AC47: =$G$4 -> 42399 | AE47: FACTOR DE VENTA | AF47: % DE COSTO | AH47: NOMBRE: | AM47: FECHA: | AN47: =$G$4 -> 42399 | AP47: FACTOR DE VENTA | AQ47: % DE COSTO | AS47: NOMBRE: | AX47: FECHA: | AY47: =$G$4 -> 42399 | BA47: FACTOR DE VENTA | BB47: % DE COSTO | BD47: NOMBRE: | BI47: FECHA: | BJ47: =$G$4 -> 42399 | BL47: FACTOR DE VENTA | BM47: % DE COSTO
A48: CÓDIGO DE RECETA: | B48: 2 | D48: PORCIONES: | E48: 10 | I48: =1/J48 -> 3.3333333 | J48: =$J$5 -> 0.3 | L48: CÓDIGO DE RECETA: | O48: PORCIONES: | P48: 10 | T48: =1/U48 -> 3.3333333 | U48: =$J$5 -> 0.3 | W48: CÓDIGO DE RECETA: | Z48: PORCIONES: | AA48: 10 | AE48: =1/AF48 -> 3.3333333 | AF48: =$J$5 -> 0.3 | AH48: CÓDIGO DE RECETA: | AK48: PORCIONES: | AL48: 10 | AP48: =1/AQ48 -> 3.3333333 | AQ48: =$J$5 -> 0.3 | AS48: CÓDIGO DE RECETA: | AV48: PORCIONES: | AW48: 10 | BA48: =1/BB48 -> 3.3333333 | BB48: =$J$5 -> 0.3 | BD48: CÓDIGO DE RECETA: | BG48: PORCIONES: | BH48: 10 | BL48: =1/BM48 -> 3.3333333 | BM48: =$J$5 -> 0.3
A49: CÓDIGO | B49: INGREDIENTES | D49: CANTIDAD | E49: UNIDAD | F49: EQUIPO Y UTENSILIOS | I49: COSTO NETO | J49: IMPORTE | L49: CÓDIGO | M49: INGREDIENTES | O49: CANTIDAD | P49: UNIDAD | Q49: EQUIPO Y UTENSILIOS | T49: COSTO NETO | U49: IMPORTE | W49: CÓDIGO | X49: INGREDIENTES | Z49: CANTIDAD | AA49: UNIDAD | AB49: EQUIPO Y UTENSILIOS | AE49: COSTO NETO | AF49: IMPORTE | AH49: CÓDIGO | AI49: INGREDIENTES | AK49: CANTIDAD | AL49: UNIDAD | AM49: EQUIPO Y UTENSILIOS | AP49: COSTO NETO | AQ49: IMPORTE | AS49: CÓDIGO | AT49: INGREDIENTES | AV49: CANTIDAD | AW49: UNIDAD | AX49: EQUIPO Y UTENSILIOS | BA49: COSTO NETO | BB49: IMPORTE | BD49: CÓDIGO | BE49: INGREDIENTES | BG49: CANTIDAD | BH49: UNIDAD | BI49: EQUIPO Y UTENSILIOS | BL49: COSTO NETO | BM49: IMPORTE
A50: =VLOOKUP(B50,Base!$A$3:$F$994, 6, false) -> 0 | B50: . | E50: =VLOOKUP(B50,Base!$A$3:$F$994, 2, false) -> . | I50: =VLOOKUP(B50,Base!$A$3:$F$994, 5, false) -> 0 | J50: =I50*D50 -> 0 | L50: =VLOOKUP(M50,Base!$A$3:$F$994, 6, false) -> 0 | M50: . | P50: =VLOOKUP(M50,Base!$A$3:$F$994, 2, false) -> . | T50: =VLOOKUP(M50,Base!$A$3:$F$994, 5, false) -> 0 | U50: =T50*O50 -> 0 | W50: =VLOOKUP(X50,Base!$A$3:$F$994, 6, false) -> 0 | X50: . | AA50: =VLOOKUP(X50,Base!$A$3:$F$994, 2, false) -> . | AE50: =VLOOKUP(X50,Base!$A$3:$F$994, 5, false) -> 0 | AF50: =AE50*Z50 -> 0 | AH50: =VLOOKUP(AI50,Base!$A$3:$F$994, 6, false) -> 0 | AI50: . | AL50: =VLOOKUP(AI50,Base!$A$3:$F$994, 2, false) -> . | AP50: =VLOOKUP(AI50,Base!$A$3:$F$994, 5, false) -> 0 | AQ50: =AP50*AK50 -> 0 | AS50: =VLOOKUP(AT50,Base!$A$3:$F$994, 6, false) -> 0 | AT50: . | AW50: =VLOOKUP(AT50,Base!$A$3:$F$994, 2, false) -> . | BA50: =VLOOKUP(AT50,Base!$A$3:$F$994, 5, false) -> 0 | BB50: =BA50*AV50 -> 0 | BD50: =VLOOKUP(BE50,Base!$A$3:$F$994, 6, false) -> 0 | BE50: . | BH50: =VLOOKUP(BE50,Base!$A$3:$F$994, 2, false) -> . | BL50: =VLOOKUP(BE50,Base!$A$3:$F$994, 5, false) -> 0 | BM50: =BL50*BG50 -> 0
A51: =VLOOKUP(B51,Base!$A$3:$F$994, 6, false) -> 0 | B51: . | E51: =VLOOKUP(B51,Base!$A$3:$F$994, 2, false) -> . | I51: =VLOOKUP(B51,Base!$A$3:$F$994, 5, false) -> 0 | J51: =I51*D51 -> 0 | L51: =VLOOKUP(M51,Base!$A$3:$F$994, 6, false) -> 0 | M51: . | P51: =VLOOKUP(M51,Base!$A$3:$F$994, 2, false) -> . | T51: =VLOOKUP(M51,Base!$A$3:$F$994, 5, false) -> 0 | U51: =T51*O51 -> 0 | W51: =VLOOKUP(X51,Base!$A$3:$F$994, 6, false) -> 0 | X51: . | AA51: =VLOOKUP(X51,Base!$A$3:$F$994, 2, false) -> . | AE51: =VLOOKUP(X51,Base!$A$3:$F$994, 5, false) -> 0 | AF51: =AE51*Z51 -> 0 | AH51: =VLOOKUP(AI51,Base!$A$3:$F$994, 6, false) -> 0 | AI51: . | AL51: =VLOOKUP(AI51,Base!$A$3:$F$994, 2, false) -> . | AP51: =VLOOKUP(AI51,Base!$A$3:$F$994, 5, false) -> 0 | AQ51: =AP51*AK51 -> 0 | AS51: =VLOOKUP(AT51,Base!$A$3:$F$994, 6, false) -> 0 | AT51: . | AW51: =VLOOKUP(AT51,Base!$A$3:$F$994, 2, false) -> . | BA51: =VLOOKUP(AT51,Base!$A$3:$F$994, 5, false) -> 0 | BB51: =BA51*AV51 -> 0 | BD51: =VLOOKUP(BE51,Base!$A$3:$F$994, 6, false) -> 0 | BE51: . | BH51: =VLOOKUP(BE51,Base!$A$3:$F$994, 2, false) -> . | BL51: =VLOOKUP(BE51,Base!$A$3:$F$994, 5, false) -> 0 | BM51: =BL51*BG51 -> 0
A52: =VLOOKUP(B52,Base!$A$3:$F$994, 6, false) -> 0 | B52: . | E52: =VLOOKUP(B52,Base!$A$3:$F$994, 2, false) -> . | I52: =VLOOKUP(B52,Base!$A$3:$F$994, 5, false) -> 0 | J52: =I52*D52 -> 0 | L52: =VLOOKUP(M52,Base!$A$3:$F$994, 6, false) -> 0 | M52: . | P52: =VLOOKUP(M52,Base!$A$3:$F$994, 2, false) -> . | T52: =VLOOKUP(M52,Base!$A$3:$F$994, 5, false) -> 0 | U52: =T52*O52 -> 0 | W52: =VLOOKUP(X52,Base!$A$3:$F$994, 6, false) -> 0 | X52: . | AA52: =VLOOKUP(X52,Base!$A$3:$F$994, 2, false) -> . | AE52: =VLOOKUP(X52,Base!$A$3:$F$994, 5, false) -> 0 | AF52: =AE52*Z52 -> 0 | AH52: =VLOOKUP(AI52,Base!$A$3:$F$994, 6, false) -> 0 | AI52: . | AL52: =VLOOKUP(AI52,Base!$A$3:$F$994, 2, false) -> . | AP52: =VLOOKUP(AI52,Base!$A$3:$F$994, 5, false) -> 0 | AQ52: =AP52*AK52 -> 0 | AS52: =VLOOKUP(AT52,Base!$A$3:$F$994, 6, false) -> 0 | AT52: . | AW52: =VLOOKUP(AT52,Base!$A$3:$F$994, 2, false) -> . | BA52: =VLOOKUP(AT52,Base!$A$3:$F$994, 5, false) -> 0 | BB52: =BA52*AV52 -> 0 | BD52: =VLOOKUP(BE52,Base!$A$3:$F$994, 6, false) -> 0 | BE52: . | BH52: =VLOOKUP(BE52,Base!$A$3:$F$994, 2, false) -> . | BL52: =VLOOKUP(BE52,Base!$A$3:$F$994, 5, false) -> 0 | BM52: =BL52*BG52 -> 0
A53: =VLOOKUP(B53,Base!$A$3:$F$994, 6, false) -> 0 | B53: . | E53: =VLOOKUP(B53,Base!$A$3:$F$994, 2, false) -> . | I53: =VLOOKUP(B53,Base!$A$3:$F$994, 5, false) -> 0 | J53: =I53*D53 -> 0 | L53: =VLOOKUP(M53,Base!$A$3:$F$994, 6, false) -> 0 | M53: . | P53: =VLOOKUP(M53,Base!$A$3:$F$994, 2, false) -> . | T53: =VLOOKUP(M53,Base!$A$3:$F$994, 5, false) -> 0 | U53: =T53*O53 -> 0 | W53: =VLOOKUP(X53,Base!$A$3:$F$994, 6, false) -> 0 | X53: . | AA53: =VLOOKUP(X53,Base!$A$3:$F$994, 2, false) -> . | AE53: =VLOOKUP(X53,Base!$A$3:$F$994, 5, false) -> 0 | AF53: =AE53*Z53 -> 0 | AH53: =VLOOKUP(AI53,Base!$A$3:$F$994, 6, false) -> 0 | AI53: . | AL53: =VLOOKUP(AI53,Base!$A$3:$F$994, 2, false) -> . | AP53: =VLOOKUP(AI53,Base!$A$3:$F$994, 5, false) -> 0 | AQ53: =AP53*AK53 -> 0 | AS53: =VLOOKUP(AT53,Base!$A$3:$F$994, 6, false) -> 0 | AT53: . | AW53: =VLOOKUP(AT53,Base!$A$3:$F$994, 2, false) -> . | BA53: =VLOOKUP(AT53,Base!$A$3:$F$994, 5, false) -> 0 | BB53: =BA53*AV53 -> 0 | BD53: =VLOOKUP(BE53,Base!$A$3:$F$994, 6, false) -> 0 | BE53: . | BH53: =VLOOKUP(BE53,Base!$A$3:$F$994, 2, false) -> . | BL53: =VLOOKUP(BE53,Base!$A$3:$F$994, 5, false) -> 0 | BM53: =BL53*BG53 -> 0
A54: =VLOOKUP(B54,Base!$A$3:$F$994, 6, false) -> 0 | B54: . | E54: =VLOOKUP(B54,Base!$A$3:$F$994, 2, false) -> . | I54: =VLOOKUP(B54,Base!$A$3:$F$994, 5, false) -> 0 | J54: =I54*D54 -> 0 | L54: =VLOOKUP(M54,Base!$A$3:$F$994, 6, false) -> 0 | M54: . | P54: =VLOOKUP(M54,Base!$A$3:$F$994, 2, false) -> . | T54: =VLOOKUP(M54,Base!$A$3:$F$994, 5, false) -> 0 | U54: =T54*O54 -> 0 | W54: =VLOOKUP(X54,Base!$A$3:$F$994, 6, false) -> 0 | X54: . | AA54: =VLOOKUP(X54,Base!$A$3:$F$994, 2, false) -> . | AE54: =VLOOKUP(X54,Base!$A$3:$F$994, 5, false) -> 0 | AF54: =AE54*Z54 -> 0 | AH54: =VLOOKUP(AI54,Base!$A$3:$F$994, 6, false) -> 0 | AI54: . | AL54: =VLOOKUP(AI54,Base!$A$3:$F$994, 2, false) -> . | AP54: =VLOOKUP(AI54,Base!$A$3:$F$994, 5, false) -> 0 | AQ54: =AP54*AK54 -> 0 | AS54: =VLOOKUP(AT54,Base!$A$3:$F$994, 6, false) -> 0 | AT54: . | AW54: =VLOOKUP(AT54,Base!$A$3:$F$994, 2, false) -> . | BA54: =VLOOKUP(AT54,Base!$A$3:$F$994, 5, false) -> 0 | BB54: =BA54*AV54 -> 0 | BD54: =VLOOKUP(BE54,Base!$A$3:$F$994, 6, false) -> 0 | BE54: . | BH54: =VLOOKUP(BE54,Base!$A$3:$F$994, 2, false) -> . | BL54: =VLOOKUP(BE54,Base!$A$3:$F$994, 5, false) -> 0 | BM54: =BL54*BG54 -> 0
A55: =VLOOKUP(B55,Base!$A$3:$F$994, 6, false) -> 0 | B55: . | E55: =VLOOKUP(B55,Base!$A$3:$F$994, 2, false) -> . | I55: =VLOOKUP(B55,Base!$A$3:$F$994, 5, false) -> 0 | J55: =I55*D55 -> 0 | L55: =VLOOKUP(M55,Base!$A$3:$F$994, 6, false) -> 0 | M55: . | P55: =VLOOKUP(M55,Base!$A$3:$F$994, 2, false) -> . | T55: =VLOOKUP(M55,Base!$A$3:$F$994, 5, false) -> 0 | U55: =T55*O55 -> 0 | W55: =VLOOKUP(X55,Base!$A$3:$F$994, 6, false) -> 0 | X55: . | AA55: =VLOOKUP(X55,Base!$A$3:$F$994, 2, false) -> . | AE55: =VLOOKUP(X55,Base!$A$3:$F$994, 5, false) -> 0 | AF55: =AE55*Z55 -> 0 | AH55: =VLOOKUP(AI55,Base!$A$3:$F$994, 6, false) -> 0 | AI55: . | AL55: =VLOOKUP(AI55,Base!$A$3:$F$994, 2, false) -> . | AP55: =VLOOKUP(AI55,Base!$A$3:$F$994, 5, false) -> 0 | AQ55: =AP55*AK55 -> 0 | AS55: =VLOOKUP(AT55,Base!$A$3:$F$994, 6, false) -> 0 | AT55: . | AW55: =VLOOKUP(AT55,Base!$A$3:$F$994, 2, false) -> . | BA55: =VLOOKUP(AT55,Base!$A$3:$F$994, 5, false) -> 0 | BB55: =BA55*AV55 -> 0 | BD55: =VLOOKUP(BE55,Base!$A$3:$F$994, 6, false) -> 0 | BE55: . | BH55: =VLOOKUP(BE55,Base!$A$3:$F$994, 2, false) -> . | BL55: =VLOOKUP(BE55,Base!$A$3:$F$994, 5, false) -> 0 | BM55: =BL55*BG55 -> 0
A56: =VLOOKUP(B56,Base!$A$3:$F$994, 6, false) -> 0 | B56: . | E56: =VLOOKUP(B56,Base!$A$3:$F$994, 2, false) -> . | I56: =VLOOKUP(B56,Base!$A$3:$F$994, 5, false) -> 0 | J56: =I56*D56 -> 0 | L56: =VLOOKUP(M56,Base!$A$3:$F$994, 6, false) -> 0 | M56: . | P56: =VLOOKUP(M56,Base!$A$3:$F$994, 2, false) -> . | T56: =VLOOKUP(M56,Base!$A$3:$F$994, 5, false) -> 0 | U56: =T56*O56 -> 0 | W56: =VLOOKUP(X56,Base!$A$3:$F$994, 6, false) -> 0 | X56: . | AA56: =VLOOKUP(X56,Base!$A$3:$F$994, 2, false) -> . | AE56: =VLOOKUP(X56,Base!$A$3:$F$994, 5, false) -> 0 | AF56: =AE56*Z56 -> 0 | AH56: =VLOOKUP(AI56,Base!$A$3:$F$994, 6, false) -> 0 | AI56: . | AL56: =VLOOKUP(AI56,Base!$A$3:$F$994, 2, false) -> . | AP56: =VLOOKUP(AI56,Base!$A$3:$F$994, 5, false) -> 0 | AQ56: =AP56*AK56 -> 0 | AS56: =VLOOKUP(AT56,Base!$A$3:$F$994, 6, false) -> 0 | AT56: . | AW56: =VLOOKUP(AT56,Base!$A$3:$F$994, 2, false) -> . | BA56: =VLOOKUP(AT56,Base!$A$3:$F$994, 5, false) -> 0 | BB56: =BA56*AV56 -> 0 | BD56: =VLOOKUP(BE56,Base!$A$3:$F$994, 6, false) -> 0 | BE56: . | BH56: =VLOOKUP(BE56,Base!$A$3:$F$994, 2, false) -> . | BL56: =VLOOKUP(BE56,Base!$A$3:$F$994, 5, false) -> 0 | BM56: =BL56*BG56 -> 0
A57: =VLOOKUP(B57,Base!$A$3:$F$994, 6, false) -> 0 | B57: . | E57: =VLOOKUP(B57,Base!$A$3:$F$994, 2, false) -> . | I57: =VLOOKUP(B57,Base!$A$3:$F$994, 5, false) -> 0 | J57: =I57*D57 -> 0 | L57: =VLOOKUP(M57,Base!$A$3:$F$994, 6, false) -> 0 | M57: . | P57: =VLOOKUP(M57,Base!$A$3:$F$994, 2, false) -> . | T57: =VLOOKUP(M57,Base!$A$3:$F$994, 5, false) -> 0 | U57: =T57*O57 -> 0 | W57: =VLOOKUP(X57,Base!$A$3:$F$994, 6, false) -> 0 | X57: . | AA57: =VLOOKUP(X57,Base!$A$3:$F$994, 2, false) -> . | AE57: =VLOOKUP(X57,Base!$A$3:$F$994, 5, false) -> 0 | AF57: =AE57*Z57 -> 0 | AH57: =VLOOKUP(AI57,Base!$A$3:$F$994, 6, false) -> 0 | AI57: . | AL57: =VLOOKUP(AI57,Base!$A$3:$F$994, 2, false) -> . | AP57: =VLOOKUP(AI57,Base!$A$3:$F$994, 5, false) -> 0 | AQ57: =AP57*AK57 -> 0 | AS57: =VLOOKUP(AT57,Base!$A$3:$F$994, 6, false) -> 0 | AT57: . | AW57: =VLOOKUP(AT57,Base!$A$3:$F$994, 2, false) -> . | BA57: =VLOOKUP(AT57,Base!$A$3:$F$994, 5, false) -> 0 | BB57: =BA57*AV57 -> 0 | BD57: =VLOOKUP(BE57,Base!$A$3:$F$994, 6, false) -> 0 | BE57: . | BH57: =VLOOKUP(BE57,Base!$A$3:$F$994, 2, false) -> . | BL57: =VLOOKUP(BE57,Base!$A$3:$F$994, 5, false) -> 0 | BM57: =BL57*BG57 -> 0
A58: =VLOOKUP(B58,Base!$A$3:$F$994, 6, false) -> 0 | B58: . | E58: =VLOOKUP(B58,Base!$A$3:$F$994, 2, false) -> . | I58: =VLOOKUP(B58,Base!$A$3:$F$994, 5, false) -> 0 | J58: =I58*D58 -> 0 | L58: =VLOOKUP(M58,Base!$A$3:$F$994, 6, false) -> 0 | M58: . | P58: =VLOOKUP(M58,Base!$A$3:$F$994, 2, false) -> . | T58: =VLOOKUP(M58,Base!$A$3:$F$994, 5, false) -> 0 | U58: =T58*O58 -> 0 | W58: =VLOOKUP(X58,Base!$A$3:$F$994, 6, false) -> 0 | X58: . | AA58: =VLOOKUP(X58,Base!$A$3:$F$994, 2, false) -> . | AE58: =VLOOKUP(X58,Base!$A$3:$F$994, 5, false) -> 0 | AF58: =AE58*Z58 -> 0 | AH58: =VLOOKUP(AI58,Base!$A$3:$F$994, 6, false) -> 0 | AI58: . | AL58: =VLOOKUP(AI58,Base!$A$3:$F$994, 2, false) -> . | AP58: =VLOOKUP(AI58,Base!$A$3:$F$994, 5, false) -> 0 | AQ58: =AP58*AK58 -> 0 | AS58: =VLOOKUP(AT58,Base!$A$3:$F$994, 6, false) -> 0 | AT58: . | AW58: =VLOOKUP(AT58,Base!$A$3:$F$994, 2, false) -> . | BA58: =VLOOKUP(AT58,Base!$A$3:$F$994, 5, false) -> 0 | BB58: =BA58*AV58 -> 0 | BD58: =VLOOKUP(BE58,Base!$A$3:$F$994, 6, false) -> 0 | BE58: . | BH58: =VLOOKUP(BE58,Base!$A$3:$F$994, 2, false) -> . | BL58: =VLOOKUP(BE58,Base!$A$3:$F$994, 5, false) -> 0 | BM58: =BL58*BG58 -> 0
A59: =VLOOKUP(B59,Base!$A$3:$F$994, 6, false) -> 0 | B59: . | E59: =VLOOKUP(B59,Base!$A$3:$F$994, 2, false) -> . | I59: =VLOOKUP(B59,Base!$A$3:$F$994, 5, false) -> 0 | J59: =I59*D59 -> 0 | L59: =VLOOKUP(M59,Base!$A$3:$F$994, 6, false) -> 0 | M59: . | P59: =VLOOKUP(M59,Base!$A$3:$F$994, 2, false) -> . | T59: =VLOOKUP(M59,Base!$A$3:$F$994, 5, false) -> 0 | U59: =T59*O59 -> 0 | W59: =VLOOKUP(X59,Base!$A$3:$F$994, 6, false) -> 0 | X59: . | AA59: =VLOOKUP(X59,Base!$A$3:$F$994, 2, false) -> . | AE59: =VLOOKUP(X59,Base!$A$3:$F$994, 5, false) -> 0 | AF59: =AE59*Z59 -> 0 | AH59: =VLOOKUP(AI59,Base!$A$3:$F$994, 6, false) -> 0 | AI59: . | AL59: =VLOOKUP(AI59,Base!$A$3:$F$994, 2, false) -> . | AP59: =VLOOKUP(AI59,Base!$A$3:$F$994, 5, false) -> 0 | AQ59: =AP59*AK60 -> 0 | AS59: =VLOOKUP(AT59,Base!$A$3:$F$994, 6, false) -> 0 | AT59: . | AW59: =VLOOKUP(AT59,Base!$A$3:$F$994, 2, false) -> . | BA59: =VLOOKUP(AT59,Base!$A$3:$F$994, 5, false) -> 0 | BB59: =BA59*AV59 -> 0 | BD59: =VLOOKUP(BE59,Base!$A$3:$F$994, 6, false) -> 0 | BE59: . | BH59: =VLOOKUP(BE59,Base!$A$3:$F$994, 2, false) -> . | BL59: =VLOOKUP(BE59,Base!$A$3:$F$994, 5, false) -> 0 | BM59: =BL59*BG59 -> 0
A60: =VLOOKUP(B60,Base!$A$3:$F$994, 6, false) -> 0 | B60: . | E60: =VLOOKUP(B60,Base!$A$3:$F$994, 2, false) -> . | F60: PREPARACIÒN | I60: =VLOOKUP(B60,Base!$A$3:$F$994, 5, false) -> 0 | J60: =I60*D60 -> 0 | L60: =VLOOKUP(M60,Base!$A$3:$F$994, 6, false) -> 0 | M60: . | P60: =VLOOKUP(M60,Base!$A$3:$F$994, 2, false) -> . | Q60: PREPARACIÒN | T60: =VLOOKUP(M60,Base!$A$3:$F$994, 5, false) -> 0 | U60: =T60*O60 -> 0 | W60: =VLOOKUP(X60,Base!$A$3:$F$994, 6, false) -> 0 | X60: . | AA60: =VLOOKUP(X60,Base!$A$3:$F$994, 2, false) -> . | AB60: PREPARACIÒN | AE60: =VLOOKUP(X60,Base!$A$3:$F$994, 5, false) -> 0 | AF60: =AE60*Z60 -> 0 | AH60: =VLOOKUP(AI60,Base!$A$3:$F$994, 6, false) -> 0 | AI60: . | AL60: =VLOOKUP(AI60,Base!$A$3:$F$994, 2, false) -> . | AM60: PREPARACIÒN | AP60: =VLOOKUP(AI60,Base!$A$3:$F$994, 5, false) -> 0 | AQ60: =AP60*AK60 -> 0 | AS60: =VLOOKUP(AT60,Base!$A$3:$F$994, 6, false) -> 0 | AT60: . | AW60: =VLOOKUP(AT60,Base!$A$3:$F$994, 2, false) -> . | AX60: PREPARACIÒN | BA60: =VLOOKUP(AT60,Base!$A$3:$F$994, 5, false) -> 0 | BB60: =BA60*AV60 -> 0 | BD60: =VLOOKUP(BE60,Base!$A$3:$F$994, 6, false) -> 0 | BE60: . | BH60: =VLOOKUP(BE60,Base!$A$3:$F$994, 2, false) -> . | BI60: PREPARACIÒN | BL60: =VLOOKUP(BE60,Base!$A$3:$F$994, 5, false) -> 0 | BM60: =BL60*BG60 -> 0
A61: =VLOOKUP(B61,Base!$A$3:$F$994, 6, false) -> 0 | B61: . | E61: =VLOOKUP(B61,Base!$A$3:$F$994, 2, false) -> . | I61: =VLOOKUP(B61,Base!$A$3:$F$994, 5, false) -> 0 | J61: =I61*D61 -> 0 | L61: =VLOOKUP(M61,Base!$A$3:$F$994, 6, false) -> 0 | M61: . | P61: =VLOOKUP(M61,Base!$A$3:$F$994, 2, false) -> . | T61: =VLOOKUP(M61,Base!$A$3:$F$994, 5, false) -> 0 | U61: =T61*O61 -> 0 | W61: =VLOOKUP(X61,Base!$A$3:$F$994, 6, false) -> 0 | X61: . | AA61: =VLOOKUP(X61,Base!$A$3:$F$994, 2, false) -> . | AE61: =VLOOKUP(X61,Base!$A$3:$F$994, 5, false) -> 0 | AF61: =AE61*Z61 -> 0 | AH61: =VLOOKUP(AI61,Base!$A$3:$F$994, 6, false) -> 0 | AI61: . | AL61: =VLOOKUP(AI61,Base!$A$3:$F$994, 2, false) -> . | AP61: =VLOOKUP(AI61,Base!$A$3:$F$994, 5, false) -> 0 | AQ61: =AP61*AK61 -> 0 | AS61: =VLOOKUP(AT61,Base!$A$3:$F$994, 6, false) -> 0 | AT61: . | AW61: =VLOOKUP(AT61,Base!$A$3:$F$994, 2, false) -> . | BA61: =VLOOKUP(AT61,Base!$A$3:$F$994, 5, false) -> 0 | BB61: =BA61*AV61 -> 0 | BD61: =VLOOKUP(BE61,Base!$A$3:$F$994, 6, false) -> 0 | BE61: . | BH61: =VLOOKUP(BE61,Base!$A$3:$F$994, 2, false) -> . | BL61: =VLOOKUP(BE61,Base!$A$3:$F$994, 5, false) -> 0 | BM61: =BL61*BG61 -> 0
A62: =VLOOKUP(B62,Base!$A$3:$F$994, 6, false) -> 0 | B62: . | E62: =VLOOKUP(B62,Base!$A$3:$F$994, 2, false) -> . | I62: =VLOOKUP(B62,Base!$A$3:$F$994, 5, false) -> 0 | J62: =I62*D62 -> 0 | L62: =VLOOKUP(M62,Base!$A$3:$F$994, 6, false) -> 0 | M62: . | P62: =VLOOKUP(M62,Base!$A$3:$F$994, 2, false) -> . | T62: =VLOOKUP(M62,Base!$A$3:$F$994, 5, false) -> 0 | U62: =T62*O62 -> 0 | W62: =VLOOKUP(X62,Base!$A$3:$F$994, 6, false) -> 0 | X62: . | AA62: =VLOOKUP(X62,Base!$A$3:$F$994, 2, false) -> . | AE62: =VLOOKUP(X62,Base!$A$3:$F$994, 5, false) -> 0 | AF62: =AE62*Z62 -> 0 | AH62: =VLOOKUP(AI62,Base!$A$3:$F$994, 6, false) -> 0 | AI62: . | AL62: =VLOOKUP(AI62,Base!$A$3:$F$994, 2, false) -> . | AP62: =VLOOKUP(AI62,Base!$A$3:$F$994, 5, false) -> 0 | AQ62: =AP62*AK62 -> 0 | AS62: =VLOOKUP(AT62,Base!$A$3:$F$994, 6, false) -> 0 | AT62: . | AW62: =VLOOKUP(AT62,Base!$A$3:$F$994, 2, false) -> . | BA62: =VLOOKUP(AT62,Base!$A$3:$F$994, 5, false) -> 0 | BB62: =BA62*AV62 -> 0 | BD62: =VLOOKUP(BE62,Base!$A$3:$F$994, 6, false) -> 0 | BE62: . | BH62: =VLOOKUP(BE62,Base!$A$3:$F$994, 2, false) -> . | BL62: =VLOOKUP(BE62,Base!$A$3:$F$994, 5, false) -> 0 | BM62: =BL62*BG62 -> 0
A63: =VLOOKUP(B63,Base!$A$3:$F$994, 6, false) -> 0 | B63: . | E63: =VLOOKUP(B63,Base!$A$3:$F$994, 2, false) -> . | I63: =VLOOKUP(B63,Base!$A$3:$F$994, 5, false) -> 0 | J63: =I63*D63 -> 0 | L63: =VLOOKUP(M63,Base!$A$3:$F$994, 6, false) -> 0 | M63: . | P63: =VLOOKUP(M63,Base!$A$3:$F$994, 2, false) -> . | T63: =VLOOKUP(M63,Base!$A$3:$F$994, 5, false) -> 0 | U63: =T63*O63 -> 0 | W63: =VLOOKUP(X63,Base!$A$3:$F$994, 6, false) -> 0 | X63: . | AA63: =VLOOKUP(X63,Base!$A$3:$F$994, 2, false) -> . | AE63: =VLOOKUP(X63,Base!$A$3:$F$994, 5, false) -> 0 | AF63: =AE63*Z63 -> 0 | AH63: =VLOOKUP(AI63,Base!$A$3:$F$994, 6, false) -> 0 | AI63: . | AL63: =VLOOKUP(AI63,Base!$A$3:$F$994, 2, false) -> . | AP63: =VLOOKUP(AI63,Base!$A$3:$F$994, 5, false) -> 0 | AQ63: =AP63*AK63 -> 0 | AS63: =VLOOKUP(AT63,Base!$A$3:$F$994, 6, false) -> 0 | AT63: . | AW63: =VLOOKUP(AT63,Base!$A$3:$F$994, 2, false) -> . | BA63: =VLOOKUP(AT63,Base!$A$3:$F$994, 5, false) -> 0 | BB63: =BA63*AV63 -> 0 | BD63: =VLOOKUP(BE63,Base!$A$3:$F$994, 6, false) -> 0 | BE63: . | BH63: =VLOOKUP(BE63,Base!$A$3:$F$994, 2, false) -> . | BL63: =VLOOKUP(BE63,Base!$A$3:$F$994, 5, false) -> 0 | BM63: =BL63*BG63 -> 0
A64: =VLOOKUP(B64,Base!$A$3:$F$994, 6, false) -> 0 | B64: . | E64: =VLOOKUP(B64,Base!$A$3:$F$994, 2, false) -> . | I64: =VLOOKUP(B64,Base!$A$3:$F$994, 5, false) -> 0 | J64: =I64*D64 -> 0 | L64: =VLOOKUP(M64,Base!$A$3:$F$994, 6, false) -> 0 | M64: . | P64: =VLOOKUP(M64,Base!$A$3:$F$994, 2, false) -> . | T64: =VLOOKUP(M64,Base!$A$3:$F$994, 5, false) -> 0 | U64: =T64*O64 -> 0 | W64: =VLOOKUP(X64,Base!$A$3:$F$994, 6, false) -> 0 | X64: . | AA64: =VLOOKUP(X64,Base!$A$3:$F$994, 2, false) -> . | AE64: =VLOOKUP(X64,Base!$A$3:$F$994, 5, false) -> 0 | AF64: =AE64*Z64 -> 0 | AH64: =VLOOKUP(AI64,Base!$A$3:$F$994, 6, false) -> 0 | AI64: . | AL64: =VLOOKUP(AI64,Base!$A$3:$F$994, 2, false) -> . | AP64: =VLOOKUP(AI64,Base!$A$3:$F$994, 5, false) -> 0 | AQ64: =AP64*AK64 -> 0 | AS64: =VLOOKUP(AT64,Base!$A$3:$F$994, 6, false) -> 0 | AT64: . | AW64: =VLOOKUP(AT64,Base!$A$3:$F$994, 2, false) -> . | BA64: =VLOOKUP(AT64,Base!$A$3:$F$994, 5, false) -> 0 | BB64: =BA64*AV64 -> 0 | BD64: =VLOOKUP(BE64,Base!$A$3:$F$994, 6, false) -> 0 | BE64: . | BH64: =VLOOKUP(BE64,Base!$A$3:$F$994, 2, false) -> . | BL64: =VLOOKUP(BE64,Base!$A$3:$F$994, 5, false) -> 0 | BM64: =BL64*BG64 -> 0
A65: =VLOOKUP(B65,Base!$A$3:$F$994, 6, false) -> 0 | B65: . | E65: =VLOOKUP(B65,Base!$A$3:$F$994, 2, false) -> . | I65: =VLOOKUP(B65,Base!$A$3:$F$994, 5, false) -> 0 | J65: =I65*D65 -> 0 | L65: =VLOOKUP(M65,Base!$A$3:$F$994, 6, false) -> 0 | M65: . | P65: =VLOOKUP(M65,Base!$A$3:$F$994, 2, false) -> . | T65: =VLOOKUP(M65,Base!$A$3:$F$994, 5, false) -> 0 | U65: =T65*O65 -> 0 | W65: =VLOOKUP(X65,Base!$A$3:$F$994, 6, false) -> 0 | X65: . | AA65: =VLOOKUP(X65,Base!$A$3:$F$994, 2, false) -> . | AE65: =VLOOKUP(X65,Base!$A$3:$F$994, 5, false) -> 0 | AF65: =AE65*Z65 -> 0 | AH65: =VLOOKUP(AI65,Base!$A$3:$F$994, 6, false) -> 0 | AI65: . | AL65: =VLOOKUP(AI65,Base!$A$3:$F$994, 2, false) -> . | AP65: =VLOOKUP(AI65,Base!$A$3:$F$994, 5, false) -> 0 | AQ65: =AP65*AK65 -> 0 | AS65: =VLOOKUP(AT65,Base!$A$3:$F$994, 6, false) -> 0 | AT65: . | AW65: =VLOOKUP(AT65,Base!$A$3:$F$994, 2, false) -> . | BA65: =VLOOKUP(AT65,Base!$A$3:$F$994, 5, false) -> 0 | BB65: =BA65*AV65 -> 0 | BD65: =VLOOKUP(BE65,Base!$A$3:$F$994, 6, false) -> 0 | BE65: . | BH65: =VLOOKUP(BE65,Base!$A$3:$F$994, 2, false) -> . | BL65: =VLOOKUP(BE65,Base!$A$3:$F$994, 5, false) -> 0 | BM65: =BL65*BG65 -> 0
A66: =VLOOKUP(B66,Base!$A$3:$F$994, 6, false) -> 0 | B66: . | E66: =VLOOKUP(B66,Base!$A$3:$F$994, 2, false) -> . | I66: =VLOOKUP(B66,Base!$A$3:$F$994, 5, false) -> 0 | J66: =I66*D66 -> 0 | L66: =VLOOKUP(M66,Base!$A$3:$F$994, 6, false) -> 0 | M66: . | P66: =VLOOKUP(M66,Base!$A$3:$F$994, 2, false) -> . | T66: =VLOOKUP(M66,Base!$A$3:$F$994, 5, false) -> 0 | U66: =T66*O66 -> 0 | W66: =VLOOKUP(X66,Base!$A$3:$F$994, 6, false) -> 0 | X66: . | AA66: =VLOOKUP(X66,Base!$A$3:$F$994, 2, false) -> . | AE66: =VLOOKUP(X66,Base!$A$3:$F$994, 5, false) -> 0 | AF66: =AE66*Z66 -> 0 | AH66: =VLOOKUP(AI66,Base!$A$3:$F$994, 6, false) -> 0 | AI66: . | AL66: =VLOOKUP(AI66,Base!$A$3:$F$994, 2, false) -> . | AP66: =VLOOKUP(AI66,Base!$A$3:$F$994, 5, false) -> 0 | AQ66: =AP66*AK66 -> 0 | AS66: =VLOOKUP(AT66,Base!$A$3:$F$994, 6, false) -> 0 | AT66: . | AW66: =VLOOKUP(AT66,Base!$A$3:$F$994, 2, false) -> . | BA66: =VLOOKUP(AT66,Base!$A$3:$F$994, 5, false) -> 0 | BB66: =BA66*AV66 -> 0 | BD66: =VLOOKUP(BE66,Base!$A$3:$F$994, 6, false) -> 0 | BE66: . | BH66: =VLOOKUP(BE66,Base!$A$3:$F$994, 2, false) -> . | BL66: =VLOOKUP(BE66,Base!$A$3:$F$994, 5, false) -> 0 | BM66: =BL66*BG66 -> 0
A67: =VLOOKUP(B67,Base!$A$3:$F$994, 6, false) -> 0 | B67: . | E67: =VLOOKUP(B67,Base!$A$3:$F$994, 2, false) -> . | I67: =VLOOKUP(B67,Base!$A$3:$F$994, 5, false) -> 0 | J67: =I67*D67 -> 0 | L67: =VLOOKUP(M67,Base!$A$3:$F$994, 6, false) -> 0 | M67: . | P67: =VLOOKUP(M67,Base!$A$3:$F$994, 2, false) -> . | T67: =VLOOKUP(M67,Base!$A$3:$F$994, 5, false) -> 0 | U67: =T67*O67 -> 0 | W67: =VLOOKUP(X67,Base!$A$3:$F$994, 6, false) -> 0 | X67: . | AA67: =VLOOKUP(X67,Base!$A$3:$F$994, 2, false) -> . | AE67: =VLOOKUP(X67,Base!$A$3:$F$994, 5, false) -> 0 | AF67: =AE67*Z67 -> 0 | AH67: =VLOOKUP(AI67,Base!$A$3:$F$994, 6, false) -> 0 | AI67: . | AL67: =VLOOKUP(AI67,Base!$A$3:$F$994, 2, false) -> . | AP67: =VLOOKUP(AI67,Base!$A$3:$F$994, 5, false) -> 0 | AQ67: =AP67*AK67 -> 0 | AS67: =VLOOKUP(AT67,Base!$A$3:$F$994, 6, false) -> 0 | AT67: . | AW67: =VLOOKUP(AT67,Base!$A$3:$F$994, 2, false) -> . | BA67: =VLOOKUP(AT67,Base!$A$3:$F$994, 5, false) -> 0 | BB67: =BA67*AV67 -> 0 | BD67: =VLOOKUP(BE67,Base!$A$3:$F$994, 6, false) -> 0 | BE67: . | BH67: =VLOOKUP(BE67,Base!$A$3:$F$994, 2, false) -> . | BL67: =VLOOKUP(BE67,Base!$A$3:$F$994, 5, false) -> 0 | BM67: =BL67*BG67 -> 0
A68: ELABORACIÒN | I68: TOTAL DE MP: | J68: =SUM(J50:J67) -> 0 | L68: ELABORACIÒN | T68: TOTAL DE MP: | U68: =SUM(U50:U67) -> 0 | W68: ELABORACIÒN | AE68: TOTAL DE MP: | AF68: =SUM(AF50:AF67) -> 0 | AH68: ELABORACIÒN | AP68: TOTAL DE MP: | AQ68: =SUM(AQ50:AQ67) -> 0 | AS68: ELABORACIÒN | BA68: TOTAL DE MP: | BB68: =SUM(BB50:BB67) -> 0 | BD68: ELABORACIÒN | BL68: TOTAL DE MP: | BM68: =SUM(BM50:BM67) -> 0
I69: TOTAL P/P: | J69: =J68/E48 -> 0 | T69: TOTAL P/P: | U69: =U68/P48 -> 0 | AE69: TOTAL P/P: | AF69: =AF68/AA48 -> 0 | AP69: TOTAL P/P: | AQ69: =AQ68/AL48 -> 0 | BA69: TOTAL P/P: | BB69: =BB68/AW48 -> 0 | BL69: TOTAL P/P: | BM69: =BM68/BH48 -> 0
I70: IMPREVISTO: | J70: 0.05 | T70: IMPREVISTO: | U70: 0.05 | AE70: IMPREVISTO: | AF70: 0.05 | AP70: IMPREVISTO: | AQ70: 0.05 | BA70: IMPREVISTO: | BB70: 0.05 | BL70: IMPREVISTO: | BM70: 0.05
I71: TOTAL DE COSTO: | J71: =J69+(J69*J70) -> 0 | T71: TOTAL DE COSTO: | U71: =U69+(U69*U70) -> 0 | AE71: TOTAL DE COSTO: | AF71: =AF69+(AF69*AF70) -> 0 | AP71: TOTAL DE COSTO: | AQ71: =AQ69+(AQ69*AQ70) -> 0 | BA71: TOTAL DE COSTO: | BB71: =BB69+(BB69*BB70) -> 0 | BL71: TOTAL DE COSTO: | BM71: =BM69+(BM69*BM70) -> 0
I72: PRECIO SUGERIDO: | J72: =J71*I48 -> 0 | T72: PRECIO SUGERIDO: | U72: =U71*T48 -> 0 | AE72: PRECIO SUGERIDO: | AF72: =AF71*AE48 -> 0 | AP72: PRECIO SUGERIDO: | AQ72: =AQ71*AP48 -> 0 | BA72: PRECIO SUGERIDO: | BB72: =BB71*BA48 -> 0 | BL72: PRECIO SUGERIDO: | BM72: =BM71*BL48 -> 0
I73: IVA: | J73: =J74-J72 -> 0 | T73: IVA: | U73: =U74-U72 -> 0 | AE73: IVA: | AF73: =AF74-AF72 -> 0 | AP73: IVA: | AQ73: =AQ74-AQ72 -> 0 | BA73: IVA: | BB73: =BB74-BB72 -> 0 | BL73: IVA: | BM73: =BM74-BM72 -> 0
I74: PRECIO SUGERIDO CON IVA: | J74: =J72*(J46*1+1) -> 0 | T74: PRECIO SUGERIDO CON IVA: | U74: =U72*(U46*1+1) -> 0 | AE74: PRECIO SUGERIDO CON IVA: | AF74: =AF72*(AF46*1+1) -> 0 | AP74: PRECIO SUGERIDO CON IVA: | AQ74: =AQ72*(AQ46*1+1) -> 0 | BA74: PRECIO SUGERIDO CON IVA: | BB74: =BB72*(BB46*1+1) -> 0 | BL74: PRECIO SUGERIDO CON IVA: | BM74: =BM72*(BM46*1+1) -> 0
I75: AJUSTE A LA CARTA | T75: AJUSTE A LA CARTA | AE75: AJUSTE A LA CARTA | AP75: AJUSTE A LA CARTA | BA75: AJUSTE A LA CARTA | BL75: AJUSTE A LA CARTA
I76: PRECIO AJUSTADO: | T76: PRECIO AJUSTADO: | AE76: PRECIO AJUSTADO: | AP76: PRECIO AJUSTADO: | BA76: PRECIO AJUSTADO: | BL76: PRECIO AJUSTADO:
A77: MONTAJE | I77: IVA: | J77: =J76-J78 -> 0 | L77: MONTAJE | T77: IVA: | U77: =U76-U78 -> 0 | W77: MONTAJE | AE77: IVA: | AF77: =AF76-AF78 -> 0 | AH77: MONTAJE | AP77: IVA: | AQ77: =AQ76-AQ78 -> 0 | AS77: MONTAJE | BA77: IVA: | BB77: =BB76-BB78 -> 0 | BD77: MONTAJE | BL77: IVA: | BM77: =BM76-BM78 -> 0
I78: PRECIO AJUSTADO SIN IVA: | J78: =J76/(J46*1+1) -> 0 | T78: PRECIO AJUSTADO SIN IVA: | U78: =U76/(U46*1+1) -> 0 | AE78: PRECIO AJUSTADO SIN IVA: | AF78: =AF76/(AF46*1+1) -> 0 | AP78: PRECIO AJUSTADO SIN IVA: | AQ78: =AQ76/(AQ46*1+1) -> 0 | BA78: PRECIO AJUSTADO SIN IVA: | BB78: =BB76/(BB46*1+1) -> 0 | BL78: PRECIO AJUSTADO SIN IVA: | BM78: =BM76/(BM46*1+1) -> 0
I79: NUEVO % DE COSTO: | J79: =J71/J78 -> #DIV/0! | T79: NUEVO % DE COSTO: | U79: =U71/U78 -> #DIV/0! | AE79: NUEVO % DE COSTO: | AF79: =AF71/AF78 -> #DIV/0! | AP79: NUEVO % DE COSTO: | AQ79: =AQ71/AQ78 -> #DIV/0! | BA79: NUEVO % DE COSTO: | BB79: =BB71/BB78 -> #DIV/0! | BL79: NUEVO % DE COSTO: | BM79: =BM71/BM78 -> #DIV/0!
I80: NUEVO FACTOR DE VENTA: | J80: =J78/J71 -> #DIV/0! | T80: NUEVO FACTOR DE VENTA: | U80: =U78/U71 -> #DIV/0! | AE80: NUEVO FACTOR DE VENTA: | AF80: =AF78/AF71 -> #DIV/0! | AP80: NUEVO FACTOR DE VENTA: | AQ80: =AQ78/AQ71 -> #DIV/0! | BA80: NUEVO FACTOR DE VENTA: | BB80: =BB78/BB71 -> #DIV/0! | BL80: NUEVO FACTOR DE VENTA: | BM80: =BM78/BM71 -> #DIV/0!
A81: OBSERVACIONES | L81: OBSERVACIONES | W81: OBSERVACIONES | AH81: OBSERVACIONES | AS81: OBSERVACIONES | BD81: OBSERVACIONES
I89: IMPUESTO | J89: =$J$3 -> 0.16 | T89: IMPUESTO: | U89: =$J$3 -> 0.16 | AE89: IMPUESTO: | AF89: =$J$3 -> 0.16 | AP89: IMPUESTO: | AQ89: =$J$3 -> 0.16 | BA89: IMPUESTO: | BB89: =$J$3 -> 0.16 | BL89: IMPUESTO: | BM89: =$J$3 -> 0.16
A90: NOMBRE: | F90: FECHA: | G90: =$G$4 -> 42399 | I90: FACTOR DE VENTA | J90: % DE COSTO | L90: NOMBRE: | Q90: FECHA: | R90: =$G$4 -> 42399 | T90: FACTOR DE VENTA | U90: % DE COSTO | W90: NOMBRE: | AB90: FECHA: | AC90: =$G$4 -> 42399 | AE90: FACTOR DE VENTA | AF90: % DE COSTO | AH90: NOMBRE: | AM90: FECHA: | AN90: =$G$4 -> 42399 | AP90: FACTOR DE VENTA | AQ90: % DE COSTO | AS90: NOMBRE: | AX90: FECHA: | AY90: =$G$4 -> 42399 | BA90: FACTOR DE VENTA | BB90: % DE COSTO | BD90: NOMBRE: | BI90: FECHA: | BJ90: =$G$4 -> 42399 | BL90: FACTOR DE VENTA | BM90: % DE COSTO
A91: CÓDIGO DE RECETA: | B91: 3 | D91: PORCIONES: | E91: 10 | I91: =1/J91 -> 3.3333333 | J91: =$J$5 -> 0.3 | L91: CÓDIGO DE RECETA: | O91: PORCIONES: | P91: 10 | T91: =1/U91 -> 3.3333333 | U91: =$J$5 -> 0.3 | W91: CÓDIGO DE RECETA: | Z91: PORCIONES: | AA91: 10 | AE91: =1/AF91 -> 3.3333333 | AF91: =$J$5 -> 0.3 | AH91: CÓDIGO DE RECETA: | AK91: PORCIONES: | AL91: 10 | AP91: =1/AQ91 -> 3.3333333 | AQ91: =$J$5 -> 0.3 | AS91: CÓDIGO DE RECETA: | AV91: PORCIONES: | AW91: 10 | BA91: =1/BB91 -> 3.3333333 | BB91: =$J$5 -> 0.3 | BD91: CÓDIGO DE RECETA: | BG91: PORCIONES: | BH91: 10 | BL91: =1/BM91 -> 3.3333333 | BM91: =$J$5 -> 0.3
A92: CÓDIGO | B92: INGREDIENTES | D92: CANTIDAD | E92: UNIDAD | F92: EQUIPO Y UTENSILIOS | I92: COSTO NETO | J92: IMPORTE | L92: CÓDIGO | M92: INGREDIENTES | O92: CANTIDAD | P92: UNIDAD | Q92: EQUIPO Y UTENSILIOS | T92: COSTO NETO | U92: IMPORTE | W92: CÓDIGO | X92: INGREDIENTES | Z92: CANTIDAD | AA92: UNIDAD | AB92: EQUIPO Y UTENSILIOS | AE92: COSTO NETO | AF92: IMPORTE | AH92: CÓDIGO | AI92: INGREDIENTES | AK92: CANTIDAD | AL92: UNIDAD | AM92: EQUIPO Y UTENSILIOS | AP92: COSTO NETO | AQ92: IMPORTE | AS92: CÓDIGO | AT92: INGREDIENTES | AV92: CANTIDAD | AW92: UNIDAD | AX92: EQUIPO Y UTENSILIOS | BA92: COSTO NETO | BB92: IMPORTE | BD92: CÓDIGO | BE92: INGREDIENTES | BG92: CANTIDAD | BH92: UNIDAD | BI92: EQUIPO Y UTENSILIOS | BL92: COSTO NETO | BM92: IMPORTE
A93: =VLOOKUP(B93,Base!$A$3:$F$994, 6, false) -> 0 | B93: . | E93: =VLOOKUP(B93,Base!$A$3:$F$994, 2, false) -> . | I93: =VLOOKUP(B93,Base!$A$3:$F$994, 5, false) -> 0 | J93: =I93*D93 -> 0 | L93: =VLOOKUP(M93,Base!$A$3:$F$994, 6, false) -> 0 | M93: . | P93: =VLOOKUP(M93,Base!$A$3:$F$994, 2, false) -> . | T93: =VLOOKUP(M93,Base!$A$3:$F$994, 5, false) -> 0 | U93: =T93*O93 -> 0 | W93: =VLOOKUP(X93,Base!$A$3:$F$994, 6, false) -> 0 | X93: . | AA93: =VLOOKUP(X93,Base!$A$3:$F$994, 2, false) -> . | AE93: =VLOOKUP(X93,Base!$A$3:$F$994, 5, false) -> 0 | AF93: =AE93*Z93 -> 0 | AH93: =VLOOKUP(AI93,Base!$A$3:$F$994, 6, false) -> 0 | AI93: . | AL93: =VLOOKUP(AI93,Base!$A$3:$F$994, 2, false) -> . | AP93: =VLOOKUP(AI93,Base!$A$3:$F$994, 5, false) -> 0 | AQ93: =AP93*AK93 -> 0 | AS93: =VLOOKUP(AT93,Base!$A$3:$F$994, 6, false) -> 0 | AT93: . | AW93: =VLOOKUP(AT93,Base!$A$3:$F$994, 2, false) -> . | BA93: =VLOOKUP(AT93,Base!$A$3:$F$994, 5, false) -> 0 | BB93: =BA93*AV93 -> 0 | BD93: =VLOOKUP(BE93,Base!$A$3:$F$994, 6, false) -> 0 | BE93: . | BH93: =VLOOKUP(BE93,Base!$A$3:$F$994, 2, false) -> . | BL93: =VLOOKUP(BE93,Base!$A$3:$F$994, 5, false) -> 0 | BM93: =BL93*BG93 -> 0
A94: =VLOOKUP(B94,Base!$A$3:$F$994, 6, false) -> 0 | B94: . | E94: =VLOOKUP(B94,Base!$A$3:$F$994, 2, false) -> . | I94: =VLOOKUP(B94,Base!$A$3:$F$994, 5, false) -> 0 | J94: =I94*D94 -> 0 | L94: =VLOOKUP(M94,Base!$A$3:$F$994, 6, false) -> 0 | M94: . | P94: =VLOOKUP(M94,Base!$A$3:$F$994, 2, false) -> . | T94: =VLOOKUP(M94,Base!$A$3:$F$994, 5, false) -> 0 | U94: =T94*O94 -> 0 | W94: =VLOOKUP(X94,Base!$A$3:$F$994, 6, false) -> 0 | X94: . | AA94: =VLOOKUP(X94,Base!$A$3:$F$994, 2, false) -> . | AE94: =VLOOKUP(X94,Base!$A$3:$F$994, 5, false) -> 0 | AF94: =AE94*Z94 -> 0 | AH94: =VLOOKUP(AI94,Base!$A$3:$F$994, 6, false) -> 0 | AI94: . | AL94: =VLOOKUP(AI94,Base!$A$3:$F$994, 2, false) -> . | AP94: =VLOOKUP(AI94,Base!$A$3:$F$994, 5, false) -> 0 | AQ94: =AP94*AK94 -> 0 | AS94: =VLOOKUP(AT94,Base!$A$3:$F$994, 6, false) -> 0 | AT94: . | AW94: =VLOOKUP(AT94,Base!$A$3:$F$994, 2, false) -> . | BA94: =VLOOKUP(AT94,Base!$A$3:$F$994, 5, false) -> 0 | BB94: =BA94*AV94 -> 0 | BD94: =VLOOKUP(BE94,Base!$A$3:$F$994, 6, false) -> 0 | BE94: . | BH94: =VLOOKUP(BE94,Base!$A$3:$F$994, 2, false) -> . | BL94: =VLOOKUP(BE94,Base!$A$3:$F$994, 5, false) -> 0 | BM94: =BL94*BG94 -> 0
A95: =VLOOKUP(B95,Base!$A$3:$F$994, 6, false) -> 0 | B95: . | E95: =VLOOKUP(B95,Base!$A$3:$F$994, 2, false) -> . | I95: =VLOOKUP(B95,Base!$A$3:$F$994, 5, false) -> 0 | J95: =I95*D95 -> 0 | L95: =VLOOKUP(M95,Base!$A$3:$F$994, 6, false) -> 0 | M95: . | P95: =VLOOKUP(M95,Base!$A$3:$F$994, 2, false) -> . | T95: =VLOOKUP(M95,Base!$A$3:$F$994, 5, false) -> 0 | U95: =T95*O95 -> 0 | W95: =VLOOKUP(X95,Base!$A$3:$F$994, 6, false) -> 0 | X95: . | AA95: =VLOOKUP(X95,Base!$A$3:$F$994, 2, false) -> . | AE95: =VLOOKUP(X95,Base!$A$3:$F$994, 5, false) -> 0 | AF95: =AE95*Z95 -> 0 | AH95: =VLOOKUP(AI95,Base!$A$3:$F$994, 6, false) -> 0 | AI95: . | AL95: =VLOOKUP(AI95,Base!$A$3:$F$994, 2, false) -> . | AP95: =VLOOKUP(AI95,Base!$A$3:$F$994, 5, false) -> 0 | AQ95: =AP95*AK95 -> 0 | AS95: =VLOOKUP(AT95,Base!$A$3:$F$994, 6, false) -> 0 | AT95: . | AW95: =VLOOKUP(AT95,Base!$A$3:$F$994, 2, false) -> . | BA95: =VLOOKUP(AT95,Base!$A$3:$F$994, 5, false) -> 0 | BB95: =BA95*AV95 -> 0 | BD95: =VLOOKUP(BE95,Base!$A$3:$F$994, 6, false) -> 0 | BE95: . | BH95: =VLOOKUP(BE95,Base!$A$3:$F$994, 2, false) -> . | BL95: =VLOOKUP(BE95,Base!$A$3:$F$994, 5, false) -> 0 | BM95: =BL95*BG95 -> 0
A96: =VLOOKUP(B96,Base!$A$3:$F$994, 6, false) -> 0 | B96: . | E96: =VLOOKUP(B96,Base!$A$3:$F$994, 2, false) -> . | I96: =VLOOKUP(B96,Base!$A$3:$F$994, 5, false) -> 0 | J96: =I96*D96 -> 0 | L96: =VLOOKUP(M96,Base!$A$3:$F$994, 6, false) -> 0 | M96: . | P96: =VLOOKUP(M96,Base!$A$3:$F$994, 2, false) -> . | T96: =VLOOKUP(M96,Base!$A$3:$F$994, 5, false) -> 0 | U96: =T96*O96 -> 0 | W96: =VLOOKUP(X96,Base!$A$3:$F$994, 6, false) -> 0 | X96: . | AA96: =VLOOKUP(X96,Base!$A$3:$F$994, 2, false) -> . | AE96: =VLOOKUP(X96,Base!$A$3:$F$994, 5, false) -> 0 | AF96: =AE96*Z96 -> 0 | AH96: =VLOOKUP(AI96,Base!$A$3:$F$994, 6, false) -> 0 | AI96: . | AL96: =VLOOKUP(AI96,Base!$A$3:$F$994, 2, false) -> . | AP96: =VLOOKUP(AI96,Base!$A$3:$F$994, 5, false) -> 0 | AQ96: =AP96*AK96 -> 0 | AS96: =VLOOKUP(AT96,Base!$A$3:$F$994, 6, false) -> 0 | AT96: . | AW96: =VLOOKUP(AT96,Base!$A$3:$F$994, 2, false) -> . | BA96: =VLOOKUP(AT96,Base!$A$3:$F$994, 5, false) -> 0 | BB96: =BA96*AV96 -> 0 | BD96: =VLOOKUP(BE96,Base!$A$3:$F$994, 6, false) -> 0 | BE96: . | BH96: =VLOOKUP(BE96,Base!$A$3:$F$994, 2, false) -> . | BL96: =VLOOKUP(BE96,Base!$A$3:$F$994, 5, false) -> 0 | BM96: =BL96*BG96 -> 0
A97: =VLOOKUP(B97,Base!$A$3:$F$994, 6, false) -> 0 | B97: . | E97: =VLOOKUP(B97,Base!$A$3:$F$994, 2, false) -> . | I97: =VLOOKUP(B97,Base!$A$3:$F$994, 5, false) -> 0 | J97: =I97*D97 -> 0 | L97: =VLOOKUP(M97,Base!$A$3:$F$994, 6, false) -> 0 | M97: . | P97: =VLOOKUP(M97,Base!$A$3:$F$994, 2, false) -> . | T97: =VLOOKUP(M97,Base!$A$3:$F$994, 5, false) -> 0 | U97: =T97*O97 -> 0 | W97: =VLOOKUP(X97,Base!$A$3:$F$994, 6, false) -> 0 | X97: . | AA97: =VLOOKUP(X97,Base!$A$3:$F$994, 2, false) -> . | AE97: =VLOOKUP(X97,Base!$A$3:$F$994, 5, false) -> 0 | AF97: =AE97*Z97 -> 0 | AH97: =VLOOKUP(AI97,Base!$A$3:$F$994, 6, false) -> 0 | AI97: . | AL97: =VLOOKUP(AI97,Base!$A$3:$F$994, 2, false) -> . | AP97: =VLOOKUP(AI97,Base!$A$3:$F$994, 5, false) -> 0 | AQ97: =AP97*AK97 -> 0 | AS97: =VLOOKUP(AT97,Base!$A$3:$F$994, 6, false) -> 0 | AT97: . | AW97: =VLOOKUP(AT97,Base!$A$3:$F$994, 2, false) -> . | BA97: =VLOOKUP(AT97,Base!$A$3:$F$994, 5, false) -> 0 | BB97: =BA97*AV97 -> 0 | BD97: =VLOOKUP(BE97,Base!$A$3:$F$994, 6, false) -> 0 | BE97: . | BH97: =VLOOKUP(BE97,Base!$A$3:$F$994, 2, false) -> . | BL97: =VLOOKUP(BE97,Base!$A$3:$F$994, 5, false) -> 0 | BM97: =BL97*BG97 -> 0
A98: =VLOOKUP(B98,Base!$A$3:$F$994, 6, false) -> 0 | B98: . | E98: =VLOOKUP(B98,Base!$A$3:$F$994, 2, false) -> . | I98: =VLOOKUP(B98,Base!$A$3:$F$994, 5, false) -> 0 | J98: =I98*D98 -> 0 | L98: =VLOOKUP(M98,Base!$A$3:$F$994, 6, false) -> 0 | M98: . | P98: =VLOOKUP(M98,Base!$A$3:$F$994, 2, false) -> . | T98: =VLOOKUP(M98,Base!$A$3:$F$994, 5, false) -> 0 | U98: =T98*O98 -> 0 | W98: =VLOOKUP(X98,Base!$A$3:$F$994, 6, false) -> 0 | X98: . | AA98: =VLOOKUP(X98,Base!$A$3:$F$994, 2, false) -> . | AE98: =VLOOKUP(X98,Base!$A$3:$F$994, 5, false) -> 0 | AF98: =AE98*Z98 -> 0 | AH98: =VLOOKUP(AI98,Base!$A$3:$F$994, 6, false) -> 0 | AI98: . | AL98: =VLOOKUP(AI98,Base!$A$3:$F$994, 2, false) -> . | AP98: =VLOOKUP(AI98,Base!$A$3:$F$994, 5, false) -> 0 | AQ98: =AP98*AK98 -> 0 | AS98: =VLOOKUP(AT98,Base!$A$3:$F$994, 6, false) -> 0 | AT98: . | AW98: =VLOOKUP(AT98,Base!$A$3:$F$994, 2, false) -> . | BA98: =VLOOKUP(AT98,Base!$A$3:$F$994, 5, false) -> 0 | BB98: =BA98*AV98 -> 0 | BD98: =VLOOKUP(BE98,Base!$A$3:$F$994, 6, false) -> 0 | BE98: . | BH98: =VLOOKUP(BE98,Base!$A$3:$F$994, 2, false) -> . | BL98: =VLOOKUP(BE98,Base!$A$3:$F$994, 5, false) -> 0 | BM98: =BL98*BG98 -> 0
A99: =VLOOKUP(B99,Base!$A$3:$F$994, 6, false) -> 0 | B99: . | E99: =VLOOKUP(B99,Base!$A$3:$F$994, 2, false) -> . | I99: =VLOOKUP(B99,Base!$A$3:$F$994, 5, false) -> 0 | J99: =I99*D99 -> 0 | L99: =VLOOKUP(M99,Base!$A$3:$F$994, 6, false) -> 0 | M99: . | P99: =VLOOKUP(M99,Base!$A$3:$F$994, 2, false) -> . | T99: =VLOOKUP(M99,Base!$A$3:$F$994, 5, false) -> 0 | U99: =T99*O99 -> 0 | W99: =VLOOKUP(X99,Base!$A$3:$F$994, 6, false) -> 0 | X99: . | AA99: =VLOOKUP(X99,Base!$A$3:$F$994, 2, false) -> . | AE99: =VLOOKUP(X99,Base!$A$3:$F$994, 5, false) -> 0 | AF99: =AE99*Z99 -> 0 | AH99: =VLOOKUP(AI99,Base!$A$3:$F$994, 6, false) -> 0 | AI99: . | AL99: =VLOOKUP(AI99,Base!$A$3:$F$994, 2, false) -> . | AP99: =VLOOKUP(AI99,Base!$A$3:$F$994, 5, false) -> 0 | AQ99: =AP99*AK99 -> 0 | AS99: =VLOOKUP(AT99,Base!$A$3:$F$994, 6, false) -> 0 | AT99: . | AW99: =VLOOKUP(AT99,Base!$A$3:$F$994, 2, false) -> . | BA99: =VLOOKUP(AT99,Base!$A$3:$F$994, 5, false) -> 0 | BB99: =BA99*AV99 -> 0 | BD99: =VLOOKUP(BE99,Base!$A$3:$F$994, 6, false) -> 0 | BE99: . | BH99: =VLOOKUP(BE99,Base!$A$3:$F$994, 2, false) -> . | BL99: =VLOOKUP(BE99,Base!$A$3:$F$994, 5, false) -> 0 | BM99: =BL99*BG99 -> 0
A100: =VLOOKUP(B100,Base!$A$3:$F$994, 6, false) -> 0 | B100: . | E100: =VLOOKUP(B100,Base!$A$3:$F$994, 2, false) -> . | I100: =VLOOKUP(B100,Base!$A$3:$F$994, 5, false) -> 0 | J100: =I100*D100 -> 0 | L100: =VLOOKUP(M100,Base!$A$3:$F$994, 6, false) -> 0 | M100: . | P100: =VLOOKUP(M100,Base!$A$3:$F$994, 2, false) -> . | T100: =VLOOKUP(M100,Base!$A$3:$F$994, 5, false) -> 0 | U100: =T100*O100 -> 0 | W100: =VLOOKUP(X100,Base!$A$3:$F$994, 6, false) -> 0 | X100: . | AA100: =VLOOKUP(X100,Base!$A$3:$F$994, 2, false) -> . | AE100: =VLOOKUP(X100,Base!$A$3:$F$994, 5, false) -> 0 | AF100: =AE100*Z100 -> 0 | AH100: =VLOOKUP(AI100,Base!$A$3:$F$994, 6, false) -> 0 | AI100: . | AL100: =VLOOKUP(AI100,Base!$A$3:$F$994, 2, false) -> . | AP100: =VLOOKUP(AI100,Base!$A$3:$F$994, 5, false) -> 0 | AQ100: =AP100*AK100 -> 0 | AS100: =VLOOKUP(AT100,Base!$A$3:$F$994, 6, false) -> 0 | AT100: . | AW100: =VLOOKUP(AT100,Base!$A$3:$F$994, 2, false) -> . | BA100: =VLOOKUP(AT100,Base!$A$3:$F$994, 5, false) -> 0 | BB100: =BA100*AV100 -> 0 | BD100: =VLOOKUP(BE100,Base!$A$3:$F$994, 6, false) -> 0 | BE100: . | BH100: =VLOOKUP(BE100,Base!$A$3:$F$994, 2, false) -> . | BL100: =VLOOKUP(BE100,Base!$A$3:$F$994, 5, false) -> 0 | BM100: =BL100*BG100 -> 0
A101: =VLOOKUP(B101,Base!$A$3:$F$994, 6, false) -> 0 | B101: . | E101: =VLOOKUP(B101,Base!$A$3:$F$994, 2, false) -> . | I101: =VLOOKUP(B101,Base!$A$3:$F$994, 5, false) -> 0 | J101: =I101*D101 -> 0 | L101: =VLOOKUP(M101,Base!$A$3:$F$994, 6, false) -> 0 | M101: . | P101: =VLOOKUP(M101,Base!$A$3:$F$994, 2, false) -> . | T101: =VLOOKUP(M101,Base!$A$3:$F$994, 5, false) -> 0 | U101: =T101*O101 -> 0 | W101: =VLOOKUP(X101,Base!$A$3:$F$994, 6, false) -> 0 | X101: . | AA101: =VLOOKUP(X101,Base!$A$3:$F$994, 2, false) -> . | AE101: =VLOOKUP(X101,Base!$A$3:$F$994, 5, false) -> 0 | AF101: =AE101*Z101 -> 0 | AH101: =VLOOKUP(AI101,Base!$A$3:$F$994, 6, false) -> 0 | AI101: . | AL101: =VLOOKUP(AI101,Base!$A$3:$F$994, 2, false) -> . | AP101: =VLOOKUP(AI101,Base!$A$3:$F$994, 5, false) -> 0 | AQ101: =AP101*AK101 -> 0 | AS101: =VLOOKUP(AT101,Base!$A$3:$F$994, 6, false) -> 0 | AT101: . | AW101: =VLOOKUP(AT101,Base!$A$3:$F$994, 2, false) -> . | BA101: =VLOOKUP(AT101,Base!$A$3:$F$994, 5, false) -> 0 | BB101: =BA101*AV101 -> 0 | BD101: =VLOOKUP(BE101,Base!$A$3:$F$994, 6, false) -> 0 | BE101: . | BH101: =VLOOKUP(BE101,Base!$A$3:$F$994, 2, false) -> . | BL101: =VLOOKUP(BE101,Base!$A$3:$F$994, 5, false) -> 0 | BM101: =BL101*BG101 -> 0
A102: =VLOOKUP(B102,Base!$A$3:$F$994, 6, false) -> 0 | B102: . | E102: =VLOOKUP(B102,Base!$A$3:$F$994, 2, false) -> . | I102: =VLOOKUP(B102,Base!$A$3:$F$994, 5, false) -> 0 | J102: =I102*D102 -> 0 | L102: =VLOOKUP(M102,Base!$A$3:$F$994, 6, false) -> 0 | M102: . | P102: =VLOOKUP(M102,Base!$A$3:$F$994, 2, false) -> . | T102: =VLOOKUP(M102,Base!$A$3:$F$994, 5, false) -> 0 | U102: =T102*O102 -> 0 | W102: =VLOOKUP(X102,Base!$A$3:$F$994, 6, false) -> 0 | X102: . | AA102: =VLOOKUP(X102,Base!$A$3:$F$994, 2, false) -> . | AE102: =VLOOKUP(X102,Base!$A$3:$F$994, 5, false) -> 0 | AF102: =AE102*Z102 -> 0 | AH102: =VLOOKUP(AI102,Base!$A$3:$F$994, 6, false) -> 0 | AI102: . | AL102: =VLOOKUP(AI102,Base!$A$3:$F$994, 2, false) -> . | AP102: =VLOOKUP(AI102,Base!$A$3:$F$994, 5, false) -> 0 | AQ102: =AP102*AK103 -> 0 | AS102: =VLOOKUP(AT102,Base!$A$3:$F$994, 6, false) -> 0 | AT102: . | AW102: =VLOOKUP(AT102,Base!$A$3:$F$994, 2, false) -> . | BA102: =VLOOKUP(AT102,Base!$A$3:$F$994, 5, false) -> 0 | BB102: =BA102*AV102 -> 0 | BD102: =VLOOKUP(BE102,Base!$A$3:$F$994, 6, false) -> 0 | BE102: . | BH102: =VLOOKUP(BE102,Base!$A$3:$F$994, 2, false) -> . | BL102: =VLOOKUP(BE102,Base!$A$3:$F$994, 5, false) -> 0 | BM102: =BL102*BG102 -> 0
A103: =VLOOKUP(B103,Base!$A$3:$F$994, 6, false) -> 0 | B103: . | E103: =VLOOKUP(B103,Base!$A$3:$F$994, 2, false) -> . | F103: PREPARACIÒN | I103: =VLOOKUP(B103,Base!$A$3:$F$994, 5, false) -> 0 | J103: =I103*D103 -> 0 | L103: =VLOOKUP(M103,Base!$A$3:$F$994, 6, false) -> 0 | M103: . | P103: =VLOOKUP(M103,Base!$A$3:$F$994, 2, false) -> . | Q103: PREPARACIÒN | T103: =VLOOKUP(M103,Base!$A$3:$F$994, 5, false) -> 0 | U103: =T103*O103 -> 0 | W103: =VLOOKUP(X103,Base!$A$3:$F$994, 6, false) -> 0 | X103: . | AA103: =VLOOKUP(X103,Base!$A$3:$F$994, 2, false) -> . | AB103: PREPARACIÒN | AE103: =VLOOKUP(X103,Base!$A$3:$F$994, 5, false) -> 0 | AF103: =AE103*Z103 -> 0 | AH103: =VLOOKUP(AI103,Base!$A$3:$F$994, 6, false) -> 0 | AI103: . | AL103: =VLOOKUP(AI103,Base!$A$3:$F$994, 2, false) -> . | AM103: PREPARACIÒN | AP103: =VLOOKUP(AI103,Base!$A$3:$F$994, 5, false) -> 0 | AQ103: =AP103*AK103 -> 0 | AS103: =VLOOKUP(AT103,Base!$A$3:$F$994, 6, false) -> 0 | AT103: . | AW103: =VLOOKUP(AT103,Base!$A$3:$F$994, 2, false) -> . | AX103: PREPARACIÒN | BA103: =VLOOKUP(AT103,Base!$A$3:$F$994, 5, false) -> 0 | BB103: =BA103*AV103 -> 0 | BD103: =VLOOKUP(BE103,Base!$A$3:$F$994, 6, false) -> 0 | BE103: . | BH103: =VLOOKUP(BE103,Base!$A$3:$F$994, 2, false) -> . | BI103: PREPARACIÒN | BL103: =VLOOKUP(BE103,Base!$A$3:$F$994, 5, false) -> 0 | BM103: =BL103*BG103 -> 0
A104: =VLOOKUP(B104,Base!$A$3:$F$994, 6, false) -> 0 | B104: . | E104: =VLOOKUP(B104,Base!$A$3:$F$994, 2, false) -> . | I104: =VLOOKUP(B104,Base!$A$3:$F$994, 5, false) -> 0 | J104: =I104*D104 -> 0 | L104: =VLOOKUP(M104,Base!$A$3:$F$994, 6, false) -> 0 | M104: . | P104: =VLOOKUP(M104,Base!$A$3:$F$994, 2, false) -> . | T104: =VLOOKUP(M104,Base!$A$3:$F$994, 5, false) -> 0 | U104: =T104*O104 -> 0 | W104: =VLOOKUP(X104,Base!$A$3:$F$994, 6, false) -> 0 | X104: . | AA104: =VLOOKUP(X104,Base!$A$3:$F$994, 2, false) -> . | AE104: =VLOOKUP(X104,Base!$A$3:$F$994, 5, false) -> 0 | AF104: =AE104*Z104 -> 0 | AH104: =VLOOKUP(AI104,Base!$A$3:$F$994, 6, false) -> 0 | AI104: . | AL104: =VLOOKUP(AI104,Base!$A$3:$F$994, 2, false) -> . | AP104: =VLOOKUP(AI104,Base!$A$3:$F$994, 5, false) -> 0 | AQ104: =AP104*AK104 -> 0 | AS104: =VLOOKUP(AT104,Base!$A$3:$F$994, 6, false) -> 0 | AT104: . | AW104: =VLOOKUP(AT104,Base!$A$3:$F$994, 2, false) -> . | BA104: =VLOOKUP(AT104,Base!$A$3:$F$994, 5, false) -> 0 | BB104: =BA104*AV104 -> 0 | BD104: =VLOOKUP(BE104,Base!$A$3:$F$994, 6, false) -> 0 | BE104: . | BH104: =VLOOKUP(BE104,Base!$A$3:$F$994, 2, false) -> . | BL104: =VLOOKUP(BE104,Base!$A$3:$F$994, 5, false) -> 0 | BM104: =BL104*BG104 -> 0
A105: =VLOOKUP(B105,Base!$A$3:$F$994, 6, false) -> 0 | B105: . | E105: =VLOOKUP(B105,Base!$A$3:$F$994, 2, false) -> . | I105: =VLOOKUP(B105,Base!$A$3:$F$994, 5, false) -> 0 | J105: =I105*D105 -> 0 | L105: =VLOOKUP(M105,Base!$A$3:$F$994, 6, false) -> 0 | M105: . | P105: =VLOOKUP(M105,Base!$A$3:$F$994, 2, false) -> . | T105: =VLOOKUP(M105,Base!$A$3:$F$994, 5, false) -> 0 | U105: =T105*O105 -> 0 | W105: =VLOOKUP(X105,Base!$A$3:$F$994, 6, false) -> 0 | X105: . | AA105: =VLOOKUP(X105,Base!$A$3:$F$994, 2, false) -> . | AE105: =VLOOKUP(X105,Base!$A$3:$F$994, 5, false) -> 0 | AF105: =AE105*Z105 -> 0 | AH105: =VLOOKUP(AI105,Base!$A$3:$F$994, 6, false) -> 0 | AI105: . | AL105: =VLOOKUP(AI105,Base!$A$3:$F$994, 2, false) -> . | AP105: =VLOOKUP(AI105,Base!$A$3:$F$994, 5, false) -> 0 | AQ105: =AP105*AK105 -> 0 | AS105: =VLOOKUP(AT105,Base!$A$3:$F$994, 6, false) -> 0 | AT105: . | AW105: =VLOOKUP(AT105,Base!$A$3:$F$994, 2, false) -> . | BA105: =VLOOKUP(AT105,Base!$A$3:$F$994, 5, false) -> 0 | BB105: =BA105*AV105 -> 0 | BD105: =VLOOKUP(BE105,Base!$A$3:$F$994, 6, false) -> 0 | BE105: . | BH105: =VLOOKUP(BE105,Base!$A$3:$F$994, 2, false) -> . | BL105: =VLOOKUP(BE105,Base!$A$3:$F$994, 5, false) -> 0 | BM105: =BL105*BG105 -> 0
A106: =VLOOKUP(B106,Base!$A$3:$F$994, 6, false) -> 0 | B106: . | E106: =VLOOKUP(B106,Base!$A$3:$F$994, 2, false) -> . | I106: =VLOOKUP(B106,Base!$A$3:$F$994, 5, false) -> 0 | J106: =I106*D106 -> 0 | L106: =VLOOKUP(M106,Base!$A$3:$F$994, 6, false) -> 0 | M106: . | P106: =VLOOKUP(M106,Base!$A$3:$F$994, 2, false) -> . | T106: =VLOOKUP(M106,Base!$A$3:$F$994, 5, false) -> 0 | U106: =T106*O106 -> 0 | W106: =VLOOKUP(X106,Base!$A$3:$F$994, 6, false) -> 0 | X106: . | AA106: =VLOOKUP(X106,Base!$A$3:$F$994, 2, false) -> . | AE106: =VLOOKUP(X106,Base!$A$3:$F$994, 5, false) -> 0 | AF106: =AE106*Z106 -> 0 | AH106: =VLOOKUP(AI106,Base!$A$3:$F$994, 6, false) -> 0 | AI106: . | AL106: =VLOOKUP(AI106,Base!$A$3:$F$994, 2, false) -> . | AP106: =VLOOKUP(AI106,Base!$A$3:$F$994, 5, false) -> 0 | AQ106: =AP106*AK106 -> 0 | AS106: =VLOOKUP(AT106,Base!$A$3:$F$994, 6, false) -> 0 | AT106: . | AW106: =VLOOKUP(AT106,Base!$A$3:$F$994, 2, false) -> . | BA106: =VLOOKUP(AT106,Base!$A$3:$F$994, 5, false) -> 0 | BB106: =BA106*AV106 -> 0 | BD106: =VLOOKUP(BE106,Base!$A$3:$F$994, 6, false) -> 0 | BE106: . | BH106: =VLOOKUP(BE106,Base!$A$3:$F$994, 2, false) -> . | BL106: =VLOOKUP(BE106,Base!$A$3:$F$994, 5, false) -> 0 | BM106: =BL106*BG106 -> 0
A107: =VLOOKUP(B107,Base!$A$3:$F$994, 6, false) -> 0 | B107: . | E107: =VLOOKUP(B107,Base!$A$3:$F$994, 2, false) -> . | I107: =VLOOKUP(B107,Base!$A$3:$F$994, 5, false) -> 0 | J107: =I107*D107 -> 0 | L107: =VLOOKUP(M107,Base!$A$3:$F$994, 6, false) -> 0 | M107: . | P107: =VLOOKUP(M107,Base!$A$3:$F$994, 2, false) -> . | T107: =VLOOKUP(M107,Base!$A$3:$F$994, 5, false) -> 0 | U107: =T107*O107 -> 0 | W107: =VLOOKUP(X107,Base!$A$3:$F$994, 6, false) -> 0 | X107: . | AA107: =VLOOKUP(X107,Base!$A$3:$F$994, 2, false) -> . | AE107: =VLOOKUP(X107,Base!$A$3:$F$994, 5, false) -> 0 | AF107: =AE107*Z107 -> 0 | AH107: =VLOOKUP(AI107,Base!$A$3:$F$994, 6, false) -> 0 | AI107: . | AL107: =VLOOKUP(AI107,Base!$A$3:$F$994, 2, false) -> . | AP107: =VLOOKUP(AI107,Base!$A$3:$F$994, 5, false) -> 0 | AQ107: =AP107*AK107 -> 0 | AS107: =VLOOKUP(AT107,Base!$A$3:$F$994, 6, false) -> 0 | AT107: . | AW107: =VLOOKUP(AT107,Base!$A$3:$F$994, 2, false) -> . | BA107: =VLOOKUP(AT107,Base!$A$3:$F$994, 5, false) -> 0 | BB107: =BA107*AV107 -> 0 | BD107: =VLOOKUP(BE107,Base!$A$3:$F$994, 6, false) -> 0 | BE107: . | BH107: =VLOOKUP(BE107,Base!$A$3:$F$994, 2, false) -> . | BL107: =VLOOKUP(BE107,Base!$A$3:$F$994, 5, false) -> 0 | BM107: =BL107*BG107 -> 0
A108: =VLOOKUP(B108,Base!$A$3:$F$994, 6, false) -> 0 | B108: . | E108: =VLOOKUP(B108,Base!$A$3:$F$994, 2, false) -> . | I108: =VLOOKUP(B108,Base!$A$3:$F$994, 5, false) -> 0 | J108: =I108*D108 -> 0 | L108: =VLOOKUP(M108,Base!$A$3:$F$994, 6, false) -> 0 | M108: . | P108: =VLOOKUP(M108,Base!$A$3:$F$994, 2, false) -> . | T108: =VLOOKUP(M108,Base!$A$3:$F$994, 5, false) -> 0 | U108: =T108*O108 -> 0 | W108: =VLOOKUP(X108,Base!$A$3:$F$994, 6, false) -> 0 | X108: . | AA108: =VLOOKUP(X108,Base!$A$3:$F$994, 2, false) -> . | AE108: =VLOOKUP(X108,Base!$A$3:$F$994, 5, false) -> 0 | AF108: =AE108*Z108 -> 0 | AH108: =VLOOKUP(AI108,Base!$A$3:$F$994, 6, false) -> 0 | AI108: . | AL108: =VLOOKUP(AI108,Base!$A$3:$F$994, 2, false) -> . | AP108: =VLOOKUP(AI108,Base!$A$3:$F$994, 5, false) -> 0 | AQ108: =AP108*AK108 -> 0 | AS108: =VLOOKUP(AT108,Base!$A$3:$F$994, 6, false) -> 0 | AT108: . | AW108: =VLOOKUP(AT108,Base!$A$3:$F$994, 2, false) -> . | BA108: =VLOOKUP(AT108,Base!$A$3:$F$994, 5, false) -> 0 | BB108: =BA108*AV108 -> 0 | BD108: =VLOOKUP(BE108,Base!$A$3:$F$994, 6, false) -> 0 | BE108: . | BH108: =VLOOKUP(BE108,Base!$A$3:$F$994, 2, false) -> . | BL108: =VLOOKUP(BE108,Base!$A$3:$F$994, 5, false) -> 0 | BM108: =BL108*BG108 -> 0
A109: =VLOOKUP(B109,Base!$A$3:$F$994, 6, false) -> 0 | B109: . | E109: =VLOOKUP(B109,Base!$A$3:$F$994, 2, false) -> . | I109: =VLOOKUP(B109,Base!$A$3:$F$994, 5, false) -> 0 | J109: =I109*D109 -> 0 | L109: =VLOOKUP(M109,Base!$A$3:$F$994, 6, false) -> 0 | M109: . | P109: =VLOOKUP(M109,Base!$A$3:$F$994, 2, false) -> . | T109: =VLOOKUP(M109,Base!$A$3:$F$994, 5, false) -> 0 | U109: =T109*O109 -> 0 | W109: =VLOOKUP(X109,Base!$A$3:$F$994, 6, false) -> 0 | X109: . | AA109: =VLOOKUP(X109,Base!$A$3:$F$994, 2, false) -> . | AE109: =VLOOKUP(X109,Base!$A$3:$F$994, 5, false) -> 0 | AF109: =AE109*Z109 -> 0 | AH109: =VLOOKUP(AI109,Base!$A$3:$F$994, 6, false) -> 0 | AI109: . | AL109: =VLOOKUP(AI109,Base!$A$3:$F$994, 2, false) -> . | AP109: =VLOOKUP(AI109,Base!$A$3:$F$994, 5, false) -> 0 | AQ109: =AP109*AK109 -> 0 | AS109: =VLOOKUP(AT109,Base!$A$3:$F$994, 6, false) -> 0 | AT109: . | AW109: =VLOOKUP(AT109,Base!$A$3:$F$994, 2, false) -> . | BA109: =VLOOKUP(AT109,Base!$A$3:$F$994, 5, false) -> 0 | BB109: =BA109*AV109 -> 0 | BD109: =VLOOKUP(BE109,Base!$A$3:$F$994, 6, false) -> 0 | BE109: . | BH109: =VLOOKUP(BE109,Base!$A$3:$F$994, 2, false) -> . | BL109: =VLOOKUP(BE109,Base!$A$3:$F$994, 5, false) -> 0 | BM109: =BL109*BG109 -> 0
A110: =VLOOKUP(B110,Base!$A$3:$F$994, 6, false) -> 0 | B110: . | E110: =VLOOKUP(B110,Base!$A$3:$F$994, 2, false) -> . | I110: =VLOOKUP(B110,Base!$A$3:$F$994, 5, false) -> 0 | J110: =I110*D110 -> 0 | L110: =VLOOKUP(M110,Base!$A$3:$F$994, 6, false) -> 0 | M110: . | P110: =VLOOKUP(M110,Base!$A$3:$F$994, 2, false) -> . | T110: =VLOOKUP(M110,Base!$A$3:$F$994, 5, false) -> 0 | U110: =T110*O110 -> 0 | W110: =VLOOKUP(X110,Base!$A$3:$F$994, 6, false) -> 0 | X110: . | AA110: =VLOOKUP(X110,Base!$A$3:$F$994, 2, false) -> . | AE110: =VLOOKUP(X110,Base!$A$3:$F$994, 5, false) -> 0 | AF110: =AE110*Z110 -> 0 | AH110: =VLOOKUP(AI110,Base!$A$3:$F$994, 6, false) -> 0 | AI110: . | AL110: =VLOOKUP(AI110,Base!$A$3:$F$994, 2, false) -> . | AP110: =VLOOKUP(AI110,Base!$A$3:$F$994, 5, false) -> 0 | AQ110: =AP110*AK110 -> 0 | AS110: =VLOOKUP(AT110,Base!$A$3:$F$994, 6, false) -> 0 | AT110: . | AW110: =VLOOKUP(AT110,Base!$A$3:$F$994, 2, false) -> . | BA110: =VLOOKUP(AT110,Base!$A$3:$F$994, 5, false) -> 0 | BB110: =BA110*AV110 -> 0 | BD110: =VLOOKUP(BE110,Base!$A$3:$F$994, 6, false) -> 0 | BE110: . | BH110: =VLOOKUP(BE110,Base!$A$3:$F$994, 2, false) -> . | BL110: =VLOOKUP(BE110,Base!$A$3:$F$994, 5, false) -> 0 | BM110: =BL110*BG110 -> 0
A111: ELABORACIÒN | I111: TOTAL DE MP: | J111: =SUM(J93:J110) -> 0 | L111: ELABORACIÒN | T111: TOTAL DE MP: | U111: =SUM(U93:U110) -> 0 | W111: ELABORACIÒN | AE111: TOTAL DE MP: | AF111: =SUM(AF93:AF110) -> 0 | AH111: ELABORACIÒN | AP111: TOTAL DE MP: | AQ111: =SUM(AQ93:AQ110) -> 0 | AS111: ELABORACIÒN | BA111: TOTAL DE MP: | BB111: =SUM(BB93:BB110) -> 0 | BD111: ELABORACIÒN | BL111: TOTAL DE MP: | BM111: =SUM(BM93:BM110) -> 0
I112: TOTAL P/P: | J112: =J111/E91 -> 0 | T112: TOTAL P/P: | U112: =U111/P91 -> 0 | AE112: TOTAL P/P: | AF112: =AF111/AA91 -> 0 | AP112: TOTAL P/P: | AQ112: =AQ111/AL91 -> 0 | BA112: TOTAL P/P: | BB112: =BB111/AW91 -> 0 | BL112: TOTAL P/P: | BM112: =BM111/BH91 -> 0
I113: IMPREVISTO: | J113: 0.05 | T113: IMPREVISTO: | U113: 0.05 | AE113: IMPREVISTO: | AF113: 0.05 | AP113: IMPREVISTO: | AQ113: 0.05 | BA113: IMPREVISTO: | BB113: 0.05 | BL113: IMPREVISTO: | BM113: 0.05
I114: TOTAL DE COSTO: | J114: =J112+(J112*J113) -> 0 | T114: TOTAL DE COSTO: | U114: =U112+(U112*U113) -> 0 | AE114: TOTAL DE COSTO: | AF114: =AF112+(AF112*AF113) -> 0 | AP114: TOTAL DE COSTO: | AQ114: =AQ112+(AQ112*AQ113) -> 0 | BA114: TOTAL DE COSTO: | BB114: =BB112+(BB112*BB113) -> 0 | BL114: TOTAL DE COSTO: | BM114: =BM112+(BM112*BM113) -> 0
...

Sheet COSTEO COPEO Y BOTELLA
A1: NOMBRE DEL ESTABLECIMIENTO
A3: COSTEO DE BEBIDAS POR BOTELLA
A4: Código | B4: ArtÍculo | C4: Capacidad (L) | D4: Costo unitario | E4: Factor | F4: Precio de venta | G4: IVA | H4: Precio sugerido a la carta | I4: Ajuste a la carta | J4: Ajuste s/IVA | K4: IVA | L4: Nuevo % de costo | M4: Nuevo Factor
A5: =vlookup(B5,Base!$A$3:$F$994, 6, false) -> 0 | B5: . | C5: =VLOOKUP(B5,Base!$A$3:$F$994, 3, FALSE) -> . | D5: =VLOOKUP(B5,Base!$A$3:$F$994, 4, FALSE) -> . | F5: =E5*D5 -> #VALUE! | G5: =H5-F5 -> #VALUE! | H5: =F5*1.16 -> #VALUE! | J5: =I5/1.16 -> 0 | K5: =I5-J5 -> 0 | L5: =D5/J5 -> #VALUE! | M5: =J5/D5 -> #VALUE!
A6: =vlookup(B6,Base!$A$3:$F$994, 6, false) -> 0 | B6: . | C6: =VLOOKUP(B6,Base!$A$3:$F$994, 3, FALSE) -> . | D6: =VLOOKUP(B6,Base!$A$3:$F$994, 4, FALSE) -> . | F6: =E6*D6 -> #VALUE! | G6: =H6-F6 -> #VALUE! | H6: =F6*1.16 -> #VALUE! | J6: =I6/1.16 -> 0 | K6: =I6-J6 -> 0 | L6: =D6/J6 -> #VALUE! | M6: =J6/D6 -> #VALUE!
A7: =vlookup(B7,Base!$A$3:$F$994, 6, false) -> 0 | B7: . | C7: =VLOOKUP(B7,Base!$A$3:$F$994, 3, FALSE) -> . | D7: =VLOOKUP(B7,Base!$A$3:$F$994, 4, FALSE) -> . | F7: =E7*D7 -> #VALUE! | G7: =H7-F7 -> #VALUE! | H7: =F7*1.16 -> #VALUE! | J7: =I7/1.16 -> 0 | K7: =I7-J7 -> 0 | L7: =D7/J7 -> #VALUE! | M7: =J7/D7 -> #VALUE!
A8: =vlookup(B8,Base!$A$3:$F$994, 6, false) -> 0 | B8: . | C8: =VLOOKUP(B8,Base!$A$3:$F$994, 3, FALSE) -> . | D8: =VLOOKUP(B8,Base!$A$3:$F$994, 4, FALSE) -> . | F8: =E8*D8 -> #VALUE! | G8: =H8-F8 -> #VALUE! | H8: =F8*1.16 -> #VALUE! | J8: =I8/1.16 -> 0 | K8: =I8-J8 -> 0 | L8: =D8/J8 -> #VALUE! | M8: =J8/D8 -> #VALUE!
A9: =vlookup(B9,Base!$A$3:$F$994, 6, false) -> 0 | B9: . | C9: =VLOOKUP(B9,Base!$A$3:$F$994, 3, FALSE) -> . | D9: =VLOOKUP(B9,Base!$A$3:$F$994, 4, FALSE) -> . | F9: =E9*D9 -> #VALUE! | G9: =H9-F9 -> #VALUE! | H9: =F9*1.16 -> #VALUE! | J9: =I9/1.16 -> 0 | K9: =I9-J9 -> 0 | L9: =D9/J9 -> #VALUE! | M9: =J9/D9 -> #VALUE!
A10: =vlookup(B10,Base!$A$3:$F$994, 6, false) -> 0 | B10: . | C10: =VLOOKUP(B10,Base!$A$3:$F$994, 3, FALSE) -> . | D10: =VLOOKUP(B10,Base!$A$3:$F$994, 4, FALSE) -> . | F10: =E10*D10 -> #VALUE! | G10: =H10-F10 -> #VALUE! | H10: =F10*1.16 -> #VALUE! | J10: =I10/1.16 -> 0 | K10: =I10-J10 -> 0 | L10: =D10/J10 -> #VALUE! | M10: =J10/D10 -> #VALUE!
A11: =vlookup(B11,Base!$A$3:$F$994, 6, false) -> 0 | B11: . | C11: =VLOOKUP(B11,Base!$A$3:$F$994, 3, FALSE) -> . | D11: =VLOOKUP(B11,Base!$A$3:$F$994, 4, FALSE) -> . | F11: =E11*D11 -> #VALUE! | G11: =H11-F11 -> #VALUE! | H11: =F11*1.16 -> #VALUE! | J11: =I11/1.16 -> 0 | K11: =I11-J11 -> 0 | L11: =D11/J11 -> #VALUE! | M11: =J11/D11 -> #VALUE!
A12: =vlookup(B12,Base!$A$3:$F$994, 6, false) -> 0 | B12: . | C12: =VLOOKUP(B12,Base!$A$3:$F$994, 3, FALSE) -> . | D12: =VLOOKUP(B12,Base!$A$3:$F$994, 4, FALSE) -> . | F12: =E12*D12 -> #VALUE! | G12: =H12-F12 -> #VALUE! | H12: =F12*1.16 -> #VALUE! | J12: =I12/1.16 -> 0 | K12: =I12-J12 -> 0 | L12: =D12/J12 -> #VALUE! | M12: =J12/D12 -> #VALUE!
A13: =vlookup(B13,Base!$A$3:$F$994, 6, false) -> 0 | B13: . | C13: =VLOOKUP(B13,Base!$A$3:$F$994, 3, FALSE) -> . | D13: =VLOOKUP(B13,Base!$A$3:$F$994, 4, FALSE) -> . | F13: =E13*D13 -> #VALUE! | G13: =H13-F13 -> #VALUE! | H13: =F13*1.16 -> #VALUE! | J13: =I13/1.16 -> 0 | K13: =I13-J13 -> 0 | L13: =D13/J13 -> #VALUE! | M13: =J13/D13 -> #VALUE!
A14: =vlookup(B14,Base!$A$3:$F$994, 6, false) -> 0 | B14: . | C14: =VLOOKUP(B14,Base!$A$3:$F$994, 3, FALSE) -> . | D14: =VLOOKUP(B14,Base!$A$3:$F$994, 4, FALSE) -> . | F14: =E14*D14 -> #VALUE! | G14: =H14-F14 -> #VALUE! | H14: =F14*1.16 -> #VALUE! | J14: =I14/1.16 -> 0 | K14: =I14-J14 -> 0 | L14: =D14/J14 -> #VALUE! | M14: =J14/D14 -> #VALUE!
A15: =vlookup(B15,Base!$A$3:$F$994, 6, false) -> 0 | B15: . | C15: =VLOOKUP(B15,Base!$A$3:$F$994, 3, FALSE) -> . | D15: =VLOOKUP(B15,Base!$A$3:$F$994, 4, FALSE) -> . | F15: =E15*D15 -> #VALUE! | G15: =H15-F15 -> #VALUE! | H15: =F15*1.16 -> #VALUE! | J15: =I15/1.16 -> 0 | K15: =I15-J15 -> 0 | L15: =D15/J15 -> #VALUE! | M15: =J15/D15 -> #VALUE!
A16: =vlookup(B16,Base!$A$3:$F$994, 6, false) -> 0 | B16: . | C16: =VLOOKUP(B16,Base!$A$3:$F$994, 3, FALSE) -> . | D16: =VLOOKUP(B16,Base!$A$3:$F$994, 4, FALSE) -> . | F16: =E16*D16 -> #VALUE! | G16: =H16-F16 -> #VALUE! | H16: =F16*1.16 -> #VALUE! | J16: =I16/1.16 -> 0 | K16: =I16-J16 -> 0 | L16: =D16/J16 -> #VALUE! | M16: =J16/D16 -> #VALUE!
... A44: =vlookup(B44,Base!$A$3:$F$994, 6, false) -> 0 | B44: . | C44: =VLOOKUP(B44,Base!$A$3:$F$994, 3, FALSE) -> . | D44: =VLOOKUP(B44,Base!$A$3:$F$994, 4, FALSE) -> . | F44: =E44*D44 -> #VALUE! | G44: =H44-F44 -> #VALUE! | H44: =F44*1.16 -> #VALUE! | J44: =I44/1.16 -> 0 | K44: =I44-J44 -> 0 | L44: =D44/J44 -> #VALUE! | M44: =J44/D44 -> #VALUE!
A47: COSTEO DE BEBIDAS POR COPEO
A48: Código | B48: ArtÍculo | C48: Capacidad (L) | D48: Costo unitario | E48: Número de copas | F48: Costo por copa | G48: Mezclador | H48: Total de costo | I48: Factor | J48: Precio de venta | K48: IVA | L48: Precio sugerido a la carta | M48: Ajuste a la carta | N48: Ajuste s/IVA | O48: IVA | P48: Nuevo % de costo | Q48: Nuevo Factor
A49: =vlookup(B49,Base!$A$3:$F$994, 6, false) -> 0 | B49: . | C49: =VLOOKUP(B49,Base!$A$3:$F$994, 3, FALSE) -> . | D49: =VLOOKUP(B49,Base!$A$3:$F$994, 4, FALSE) -> . | F49: =D49/E49 -> #VALUE! | H49: =G49+F49 -> #VALUE! | J49: =I49*H49 -> #VALUE! | K49: =L49-J49 -> #VALUE! | L49: =J49*1.16 -> #VALUE! | N49: =M49/1.16 -> 0 | O49: =M49-N49 -> 0 | P49: =H49/N49 -> #VALUE! | Q49: =N49/H49 -> #VALUE!
A50: =vlookup(B50,Base!$A$3:$F$994, 6, false) -> 0 | B50: . | C50: =VLOOKUP(B50,Base!$A$3:$F$994, 3, FALSE) -> . | D50: =VLOOKUP(B50,Base!$A$3:$F$994, 4, FALSE) -> . | F50: =D50/E50 -> #VALUE! | H50: =G50+F50 -> #VALUE! | J50: =I50*H50 -> #VALUE! | K50: =L50-J50 -> #VALUE! | L50: =J50*1.16 -> #VALUE! | N50: =M50/1.16 -> 0 | O50: =M50-N50 -> 0 | P50: =H50/N50 -> #VALUE! | Q50: =N50/H50 -> #VALUE!
A51: =vlookup(B51,Base!$A$3:$F$994, 6, false) -> 0 | B51: . | C51: =VLOOKUP(B51,Base!$A$3:$F$994, 3, FALSE) -> . | D51: =VLOOKUP(B51,Base!$A$3:$F$994, 4, FALSE) -> . | F51: =D51/E51 -> #VALUE! | H51: =G51+F51 -> #VALUE! | J51: =I51*H51 -> #VALUE! | K51: =L51-J51 -> #VALUE! | L51: =J51*1.16 -> #VALUE! | N51: =M51/1.16 -> 0 | O51: =M51-N51 -> 0 | P51: =H51/N51 -> #VALUE! | Q51: =N51/H51 -> #VALUE!
A52: =vlookup(B52,Base!$A$3:$F$994, 6, false) -> 0 | B52: . | C52: =VLOOKUP(B52,Base!$A$3:$F$994, 3, FALSE) -> . | D52: =VLOOKUP(B52,Base!$A$3:$F$994, 4, FALSE) -> . | F52: =D52/E52 -> #VALUE! | H52: =G52+F52 -> #VALUE! | J52: =I52*H52 -> #VALUE! | K52: =L52-J52 -> #VALUE! | L52: =J52*1.16 -> #VALUE! | N52: =M52/1.16 -> 0 | O52: =M52-N52 -> 0 | P52: =H52/N52 -> #VALUE! | Q52: =N52/H52 -> #VALUE!
A53: =vlookup(B53,Base!$A$3:$F$994, 6, false) -> 0 | B53: . | C53: =VLOOKUP(B53,Base!$A$3:$F$994, 3, FALSE) -> . | D53: =VLOOKUP(B53,Base!$A$3:$F$994, 4, FALSE) -> . | F53: =D53/E53 -> #VALUE! | H53: =G53+F53 -> #VALUE! | J53: =I53*H53 -> #VALUE! | K53: =L53-J53 -> #VALUE! | L53: =J53*1.16 -> #VALUE! | N53: =M53/1.16 -> 0 | O53: =M53-N53 -> 0 | P53: =H53/N53 -> #VALUE! | Q53: =N53/H53 -> #VALUE!
A54: =vlookup(B54,Base!$A$3:$F$994, 6, false) -> 0 | B54: . | C54: =VLOOKUP(B54,Base!$A$3:$F$994, 3, FALSE) -> . | D54: =VLOOKUP(B54,Base!$A$3:$F$994, 4, FALSE) -> . | F54: =D54/E54 -> #VALUE! | H54: =G54+F54 -> #VALUE! | J54: =I54*H54 -> #VALUE! | K54: =L54-J54 -> #VALUE! | L54: =J54*1.16 -> #VALUE! | N54: =M54/1.16 -> 0 | O54: =M54-N54 -> 0 | P54: =H54/N54 -> #VALUE! | Q54: =N54/H54 -> #VALUE!
A55: =vlookup(B55,Base!$A$3:$F$994, 6, false) -> 0 | B55: . | C55: =VLOOKUP(B55,Base!$A$3:$F$994, 3, FALSE) -> . | D55: =VLOOKUP(B55,Base!$A$3:$F$994, 4, FALSE) -> . | F55: =D55/E55 -> #VALUE! | H55: =G55+F55 -> #VALUE! | J55: =I55*H55 -> #VALUE! | K55: =L55-J55 -> #VALUE! | L55: =J55*1.16 -> #VALUE! | N55: =M55/1.16 -> 0 | O55: =M55-N55 -> 0 | P55: =H55/N55 -> #VALUE! | Q55: =N55/H55 -> #VALUE!
A56: =vlookup(B56,Base!$A$3:$F$994, 6, false) -> 0 | B56: . | C56: =VLOOKUP(B56,Base!$A$3:$F$994, 3, FALSE) -> . | D56: =VLOOKUP(B56,Base!$A$3:$F$994, 4, FALSE) -> . | F56: =D56/E56 -> #VALUE! | H56: =G56+F56 -> #VALUE! | J56: =I56*H56 -> #VALUE! | K56: =L56-J56 -> #VALUE! | L56: =J56*1.16 -> #VALUE! | N56: =M56/1.16 -> 0 | O56: =M56-N56 -> 0 | P56: =H56/N56 -> #VALUE! | Q56: =N56/H56 -> #VALUE!
A57: =vlookup(B57,Base!$A$3:$F$994, 6, false) -> 0 | B57: . | C57: =VLOOKUP(B57,Base!$A$3:$F$994, 3, FALSE) -> . | D57: =VLOOKUP(B57,Base!$A$3:$F$994, 4, FALSE) -> . | F57: =D57/E57 -> #VALUE! | H57: =G57+F57 -> #VALUE! | J57: =I57*H57 -> #VALUE! | K57: =L57-J57 -> #VALUE! | L57: =J57*1.16 -> #VALUE! | N57: =M57/1.16 -> 0 | O57: =M57-N57 -> 0 | P57: =H57/N57 -> #VALUE! | Q57: =N57/H57 -> #VALUE!
A58: =vlookup(B58,Base!$A$3:$F$994, 6, false) -> 0 | B58: . | C58: =VLOOKUP(B58,Base!$A$3:$F$994, 3, FALSE) -> . | D58: =VLOOKUP(B58,Base!$A$3:$F$994, 4, FALSE) -> . | F58: =D58/E58 -> #VALUE! | H58: =G58+F58 -> #VALUE! | J58: =I58*H58 -> #VALUE! | K58: =L58-J58 -> #VALUE! | L58: =J58*1.16 -> #VALUE! | N58: =M58/1.16 -> 0 | O58: =M58-N58 -> 0 | P58: =H58/N58 -> #VALUE! | Q58: =N58/H58 -> #VALUE!
A59: =vlookup(B59,Base!$A$3:$F$994, 6, false) -> 0 | B59: . | C59: =VLOOKUP(B59,Base!$A$3:$F$994, 3, FALSE) -> . | D59: =VLOOKUP(B59,Base!$A$3:$F$994, 4, FALSE) -> . | F59: =D59/E59 -> #VALUE! | H59: =G59+F59 -> #VALUE! | J59: =I59*H59 -> #VALUE! | K59: =L59-J59 -> #VALUE! | L59: =J59*1.16 -> #VALUE! | N59: =M59/1.16 -> 0 | O59: =M59-N59 -> 0 | P59: =H59/N59 -> #VALUE! | Q59: =N59/H59 -> #VALUE!
A60: =vlookup(B60,Base!$A$3:$F$994, 6, false) -> 0 | B60: . | C60: =VLOOKUP(B60,Base!$A$3:$F$994, 3, FALSE) -> . | D60: =VLOOKUP(B60,Base!$A$3:$F$994, 4, FALSE) -> . | F60: =D60/E60 -> #VALUE! | H60: =G60+F60 -> #VALUE! | J60: =I60*H60 -> #VALUE! | K60: =L60-J60 -> #VALUE! | L60: =J60*1.16 -> #VALUE! | N60: =M60/1.16 -> 0 | O60: =M60-N60 -> 0 | P60: =H60/N60 -> #VALUE! | Q60: =N60/H60 -> #VALUE!
... A88: =vlookup(B88,Base!$A$3:$F$994, 6, false) -> 0 | B88: . | C88: =VLOOKUP(B88,Base!$A$3:$F$994, 3, FALSE) -> . | D88: =VLOOKUP(B88,Base!$A$3:$F$994, 4, FALSE) -> . | F88: =D88/E88 -> #VALUE! | H88: =G88+F88 -> #VALUE! | J88: =I88*H88 -> #VALUE! | K88: =L88-J88 -> #VALUE! | L88: =J88*1.16 -> #VALUE! | N88: =M88/1.16 -> 0 | O88: =M88-N88 -> 0 | P88: =H88/N88 -> #VALUE! | Q88: =N88/H88 -> #VALUE!

Sheet Copia de COSTEO COPEO Y BOTELLA
A1: NOMBRE DEL ESTABLECIMIENTO
A3: COSTEO DE BEBIDAS POR BOTELLA
A4: Código | B4: ArtÍculo | C4: Capacidad (L) | D4: Costo unitario | E4: Factor | F4: Precio de venta | G4: IVA | H4: Precio sugerido a la carta | I4: Ajuste a la carta | J4: Ajuste s/IVA | K4: IVA | L4: Nuevo % de costo | M4: Nuevo Factor
A5: =vlookup(B5,Base!$A$3:$F$994, 6, false) -> 0 | B5: . | C5: =VLOOKUP(B5,Base!$A$3:$F$994, 3, FALSE) -> . | D5: =VLOOKUP(B5,Base!$A$3:$F$994, 4, FALSE) -> . | F5: =E5*D5 -> #VALUE! | G5: =H5-F5 -> #VALUE! | H5: =F5*1.16 -> #VALUE! | J5: =I5/1.16 -> 0 | K5: =I5-J5 -> 0 | L5: =D5/J5 -> #VALUE! | M5: =J5/D5 -> #VALUE!
A6: =vlookup(B6,Base!$A$3:$F$994, 6, false) -> 0 | B6: . | C6: =VLOOKUP(B6,Base!$A$3:$F$994, 3, FALSE) -> . | D6: =VLOOKUP(B6,Base!$A$3:$F$994, 4, FALSE) -> . | F6: =E6*D6 -> #VALUE! | G6: =H6-F6 -> #VALUE! | H6: =F6*1.16 -> #VALUE! | J6: =I6/1.16 -> 0 | K6: =I6-J6 -> 0 | L6: =D6/J6 -> #VALUE! | M6: =J6/D6 -> #VALUE!
A7: =vlookup(B7,Base!$A$3:$F$994, 6, false) -> 0 | B7: . | C7: =VLOOKUP(B7,Base!$A$3:$F$994, 3, FALSE) -> . | D7: =VLOOKUP(B7,Base!$A$3:$F$994, 4, FALSE) -> . | F7: =E7*D7 -> #VALUE! | G7: =H7-F7 -> #VALUE! | H7: =F7*1.16 -> #VALUE! | J7: =I7/1.16 -> 0 | K7: =I7-J7 -> 0 | L7: =D7/J7 -> #VALUE! | M7: =J7/D7 -> #VALUE!
A8: =vlookup(B8,Base!$A$3:$F$994, 6, false) -> 0 | B8: . | C8: =VLOOKUP(B8,Base!$A$3:$F$994, 3, FALSE) -> . | D8: =VLOOKUP(B8,Base!$A$3:$F$994, 4, FALSE) -> . | F8: =E8*D8 -> #VALUE! | G8: =H8-F8 -> #VALUE! | H8: =F8*1.16 -> #VALUE! | J8: =I8/1.16 -> 0 | K8: =I8-J8 -> 0 | L8: =D8/J8 -> #VALUE! | M8: =J8/D8 -> #VALUE!
A9: =vlookup(B9,Base!$A$3:$F$994, 6, false) -> 0 | B9: . | C9: =VLOOKUP(B9,Base!$A$3:$F$994, 3, FALSE) -> . | D9: =VLOOKUP(B9,Base!$A$3:$F$994, 4, FALSE) -> . | F9: =E9*D9 -> #VALUE! | G9: =H9-F9 -> #VALUE! | H9: =F9*1.16 -> #VALUE! | J9: =I9/1.16 -> 0 | K9: =I9-J9 -> 0 | L9: =D9/J9 -> #VALUE! | M9: =J9/D9 -> #VALUE!
A10: =vlookup(B10,Base!$A$3:$F$994, 6, false) -> 0 | B10: . | C10: =VLOOKUP(B10,Base!$A$3:$F$994, 3, FALSE) -> . | D10: =VLOOKUP(B10,Base!$A$3:$F$994, 4, FALSE) -> . | F10: =E10*D10 -> #VALUE! | G10: =H10-F10 -> #VALUE! | H10: =F10*1.16 -> #VALUE! | J10: =I10/1.16 -> 0 | K10: =I10-J10 -> 0 | L10: =D10/J10 -> #VALUE! | M10: =J10/D10 -> #VALUE!
A11: =vlookup(B11,Base!$A$3:$F$994, 6, false) -> 0 | B11: . | C11: =VLOOKUP(B11,Base!$A$3:$F$994, 3, FALSE) -> . | D11: =VLOOKUP(B11,Base!$A$3:$F$994, 4, FALSE) -> . | F11: =E11*D11 -> #VALUE! | G11: =H11-F11 -> #VALUE! | H11: =F11*1.16 -> #VALUE! | J11: =I11/1.16 -> 0 | K11: =I11-J11 -> 0 | L11: =D11/J11 -> #VALUE! | M11: =J11/D11 -> #VALUE!
A12: =vlookup(B12,Base!$A$3:$F$994, 6, false) -> 0 | B12: . | C12: =VLOOKUP(B12,Base!$A$3:$F$994, 3, FALSE) -> . | D12: =VLOOKUP(B12,Base!$A$3:$F$994, 4, FALSE) -> . | F12: =E12*D12 -> #VALUE! | G12: =H12-F12 -> #VALUE! | H12: =F12*1.16 -> #VALUE! | J12: =I12/1.16 -> 0 | K12: =I12-J12 -> 0 | L12: =D12/J12 -> #VALUE! | M12: =J12/D12 -> #VALUE!
A13: =vlookup(B13,Base!$A$3:$F$994, 6, false) -> 0 | B13: . | C13: =VLOOKUP(B13,Base!$A$3:$F$994, 3, FALSE) -> . | D13: =VLOOKUP(B13,Base!$A$3:$F$994, 4, FALSE) -> . | F13: =E13*D13 -> #VALUE! | G13: =H13-F13 -> #VALUE! | H13: =F13*1.16 -> #VALUE! | J13: =I13/1.16 -> 0 | K13: =I13-J13 -> 0 | L13: =D13/J13 -> #VALUE! | M13: =J13/D13 -> #VALUE!
A14: =vlookup(B14,Base!$A$3:$F$994, 6, false) -> 0 | B14: . | C14: =VLOOKUP(B14,Base!$A$3:$F$994, 3, FALSE) -> . | D14: =VLOOKUP(B14,Base!$A$3:$F$994, 4, FALSE) -> . | F14: =E14*D14 -> #VALUE! | G14: =H14-F14 -> #VALUE! | H14: =F14*1.16 -> #VALUE! | J14: =I14/1.16 -> 0 | K14: =I14-J14 -> 0 | L14: =D14/J14 -> #VALUE! | M14: =J14/D14 -> #VALUE!
A15: =vlookup(B15,Base!$A$3:$F$994, 6, false) -> 0 | B15: . | C15: =VLOOKUP(B15,Base!$A$3:$F$994, 3, FALSE) -> . | D15: =VLOOKUP(B15,Base!$A$3:$F$994, 4, FALSE) -> . | F15: =E15*D15 -> #VALUE! | G15: =H15-F15 -> #VALUE! | H15: =F15*1.16 -> #VALUE! | J15: =I15/1.16 -> 0 | K15: =I15-J15 -> 0 | L15: =D15/J15 -> #VALUE! | M15: =J15/D15 -> #VALUE!
A16: =vlookup(B16,Base!$A$3:$F$994, 6, false) -> 0 | B16: . | C16: =VLOOKUP(B16,Base!$A$3:$F$994, 3, FALSE) -> . | D16: =VLOOKUP(B16,Base!$A$3:$F$994, 4, FALSE) -> . | F16: =E16*D16 -> #VALUE! | G16: =H16-F16 -> #VALUE! | H16: =F16*1.16 -> #VALUE! | J16: =I16/1.16 -> 0 | K16: =I16-J16 -> 0 | L16: =D16/J16 -> #VALUE! | M16: =J16/D16 -> #VALUE!
... A44: =vlookup(B44,Base!$A$3:$F$994, 6, false) -> 0 | B44: . | C44: =VLOOKUP(B44,Base!$A$3:$F$994, 3, FALSE) -> . | D44: =VLOOKUP(B44,Base!$A$3:$F$994, 4, FALSE) -> . | F44: =E44*D44 -> #VALUE! | G44: =H44-F44 -> #VALUE! | H44: =F44*1.16 -> #VALUE! | J44: =I44/1.16 -> 0 | K44: =I44-J44 -> 0 | L44: =D44/J44 -> #VALUE! | M44: =J44/D44 -> #VALUE!
A47: COSTEO DE BEBIDAS POR COPEO
A48: Código | B48: ArtÍculo | C48: Capacidad (L) | D48: Costo unitario | E48: Número de copas | F48: Costo por copa | G48: Mezclador | H48: Total de costo | I48: Factor | J48: Precio de venta | K48: IVA | L48: Precio sugerido a la carta | M48: Ajuste a la carta | N48: Ajuste s/IVA | O48: IVA | P48: Nuevo % de costo | Q48: Nuevo Factor
A49: =vlookup(B49,Base!$A$3:$F$994, 6, false) -> 0 | B49: . | C49: =VLOOKUP(B49,Base!$A$3:$F$994, 3, FALSE) -> . | D49: =VLOOKUP(B49,Base!$A$3:$F$994, 4, FALSE) -> . | F49: =D49/E49 -> #VALUE! | H49: =G49+F49 -> #VALUE! | J49: =I49*H49 -> #VALUE! | K49: =L49-J49 -> #VALUE! | L49: =J49*1.16 -> #VALUE! | N49: =M49/1.16 -> 0 | O49: =M49-N49 -> 0 | P49: =H49/N49 -> #VALUE! | Q49: =N49/H49 -> #VALUE!
A50: =vlookup(B50,Base!$A$3:$F$994, 6, false) -> 0 | B50: . | C50: =VLOOKUP(B50,Base!$A$3:$F$994, 3, FALSE) -> . | D50: =VLOOKUP(B50,Base!$A$3:$F$994, 4, FALSE) -> . | F50: =D50/E50 -> #VALUE! | H50: =G50+F50 -> #VALUE! | J50: =I50*H50 -> #VALUE! | K50: =L50-J50 -> #VALUE! | L50: =J50*1.16 -> #VALUE! | N50: =M50/1.16 -> 0 | O50: =M50-N50 -> 0 | P50: =H50/N50 -> #VALUE! | Q50: =N50/H50 -> #VALUE!
A51: =vlookup(B51,Base!$A$3:$F$994, 6, false) -> 0 | B51: . | C51: =VLOOKUP(B51,Base!$A$3:$F$994, 3, FALSE) -> . | D51: =VLOOKUP(B51,Base!$A$3:$F$994, 4, FALSE) -> . | F51: =D51/E51 -> #VALUE! | H51: =G51+F51 -> #VALUE! | J51: =I51*H51 -> #VALUE! | K51: =L51-J51 -> #VALUE! | L51: =J51*1.16 -> #VALUE! | N51: =M51/1.16 -> 0 | O51: =M51-N51 -> 0 | P51: =H51/N51 -> #VALUE! | Q51: =N51/H51 -> #VALUE!
A52: =vlookup(B52,Base!$A$3:$F$994, 6, false) -> 0 | B52: . | C52: =VLOOKUP(B52,Base!$A$3:$F$994, 3, FALSE) -> . | D52: =VLOOKUP(B52,Base!$A$3:$F$994, 4, FALSE) -> . | F52: =D52/E52 -> #VALUE! | H52: =G52+F52 -> #VALUE! | J52: =I52*H52 -> #VALUE! | K52: =L52-J52 -> #VALUE! | L52: =J52*1.16 -> #VALUE! | N52: =M52/1.16 -> 0 | O52: =M52-N52 -> 0 | P52: =H52/N52 -> #VALUE! | Q52: =N52/H52 -> #VALUE!
A53: =vlookup(B53,Base!$A$3:$F$994, 6, false) -> 0 | B53: . | C53: =VLOOKUP(B53,Base!$A$3:$F$994, 3, FALSE) -> . | D53: =VLOOKUP(B53,Base!$A$3:$F$994, 4, FALSE) -> . | F53: =D53/E53 -> #VALUE! | H53: =G53+F53 -> #VALUE! | J53: =I53*H53 -> #VALUE! | K53: =L53-J53 -> #VALUE! | L53: =J53*1.16 -> #VALUE! | N53: =M53/1.16 -> 0 | O53: =M53-N53 -> 0 | P53: =H53/N53 -> #VALUE! | Q53: =N53/H53 -> #VALUE!
A54: =vlookup(B54,Base!$A$3:$F$994, 6, false) -> 0 | B54: . | C54: =VLOOKUP(B54,Base!$A$3:$F$994, 3, FALSE) -> . | D54: =VLOOKUP(B54,Base!$A$3:$F$994, 4, FALSE) -> . | F54: =D54/E54 -> #VALUE! | H54: =G54+F54 -> #VALUE! | J54: =I54*H54 -> #VALUE! | K54: =L54-J54 -> #VALUE! | L54: =J54*1.16 -> #VALUE! | N54: =M54/1.16 -> 0 | O54: =M54-N54 -> 0 | P54: =H54/N54 -> #VALUE! | Q54: =N54/H54 -> #VALUE!
A55: =vlookup(B55,Base!$A$3:$F$994, 6, false) -> 0 | B55: . | C55: =VLOOKUP(B55,Base!$A$3:$F$994, 3, FALSE) -> . | D55: =VLOOKUP(B55,Base!$A$3:$F$994, 4, FALSE) -> . | F55: =D55/E55 -> #VALUE! | H55: =G55+F55 -> #VALUE! | J55: =I55*H55 -> #VALUE! | K55: =L55-J55 -> #VALUE! | L55: =J55*1.16 -> #VALUE! | N55: =M55/1.16 -> 0 | O55: =M55-N55 -> 0 | P55: =H55/N55 -> #VALUE! | Q55: =N55/H55 -> #VALUE!
A56: =vlookup(B56,Base!$A$3:$F$994, 6, false) -> 0 | B56: . | C56: =VLOOKUP(B56,Base!$A$3:$F$994, 3, FALSE) -> . | D56: =VLOOKUP(B56,Base!$A$3:$F$994, 4, FALSE) -> . | F56: =D56/E56 -> #VALUE! | H56: =G56+F56 -> #VALUE! | J56: =I56*H56 -> #VALUE! | K56: =L56-J56 -> #VALUE! | L56: =J56*1.16 -> #VALUE! | N56: =M56/1.16 -> 0 | O56: =M56-N56 -> 0 | P56: =H56/N56 -> #VALUE! | Q56: =N56/H56 -> #VALUE!
A57: =vlookup(B57,Base!$A$3:$F$994, 6, false) -> 0 | B57: . | C57: =VLOOKUP(B57,Base!$A$3:$F$994, 3, FALSE) -> . | D57: =VLOOKUP(B57,Base!$A$3:$F$994, 4, FALSE) -> . | F57: =D57/E57 -> #VALUE! | H57: =G57+F57 -> #VALUE! | J57: =I57*H57 -> #VALUE! | K57: =L57-J57 -> #VALUE! | L57: =J57*1.16 -> #VALUE! | N57: =M57/1.16 -> 0 | O57: =M57-N57 -> 0 | P57: =H57/N57 -> #VALUE! | Q57: =N57/H57 -> #VALUE!
A58: =vlookup(B58,Base!$A$3:$F$994, 6, false) -> 0 | B58: . | C58: =VLOOKUP(B58,Base!$A$3:$F$994, 3, FALSE) -> . | D58: =VLOOKUP(B58,Base!$A$3:$F$994, 4, FALSE) -> . | F58: =D58/E58 -> #VALUE! | H58: =G58+F58 -> #VALUE! | J58: =I58*H58 -> #VALUE! | K58: =L58-J58 -> #VALUE! | L58: =J58*1.16 -> #VALUE! | N58: =M58/1.16 -> 0 | O58: =M58-N58 -> 0 | P58: =H58/N58 -> #VALUE! | Q58: =N58/H58 -> #VALUE!
A59: =vlookup(B59,Base!$A$3:$F$994, 6, false) -> 0 | B59: . | C59: =VLOOKUP(B59,Base!$A$3:$F$994, 3, FALSE) -> . | D59: =VLOOKUP(B59,Base!$A$3:$F$994, 4, FALSE) -> . | F59: =D59/E59 -> #VALUE! | H59: =G59+F59 -> #VALUE! | J59: =I59*H59 -> #VALUE! | K59: =L59-J59 -> #VALUE! | L59: =J59*1.16 -> #VALUE! | N59: =M59/1.16 -> 0 | O59: =M59-N59 -> 0 | P59: =H59/N59 -> #VALUE! | Q59: =N59/H59 -> #VALUE!
A60: =vlookup(B60,Base!$A$3:$F$994, 6, false) -> 0 | B60: . | C60: =VLOOKUP(B60,Base!$A$3:$F$994, 3, FALSE) -> . | D60: =VLOOKUP(B60,Base!$A$3:$F$994, 4, FALSE) -> . | F60: =D60/E60 -> #VALUE! | H60: =G60+F60 -> #VALUE! | J60: =I60*H60 -> #VALUE! | K60: =L60-J60 -> #VALUE! | L60: =J60*1.16 -> #VALUE! | N60: =M60/1.16 -> 0 | O60: =M60-N60 -> 0 | P60: =H60/N60 -> #VALUE! | Q60: =N60/H60 -> #VALUE!
... A88: =vlookup(B88,Base!$A$3:$F$994, 6, false) -> 0 | B88: . | C88: =VLOOKUP(B88,Base!$A$3:$F$994, 3, FALSE) -> . | D88: =VLOOKUP(B88,Base!$A$3:$F$994, 4, FALSE) -> . | F88: =D88/E88 -> #VALUE! | H88: =G88+F88 -> #VALUE! | J88: =I88*H88 -> #VALUE! | K88: =L88-J88 -> #VALUE! | L88: =J88*1.16 -> #VALUE! | N88: =M88/1.16 -> 0 | O88: =M88-N88 -> 0 | P88: =H88/N88 -> #VALUE! | Q88: =N88/H88 -> #VALUE!

Sheet REC COCTELES
A1: NOMBRE DEL ESTABLECIMIENTO
A2: COCTELES
I3: IMPUESTO | J3: 0.16
A4: NOMBRE: | B4: DSAD | F4: FECHA: | G4: ='REC ALIMENTOS'!G4 -> 42399 | I4: FACTOR DE VENTA | J4: % DE COSTO
A5: CÓDIGO DE RECETA: | B5: 4535 | D5: PORCIONES: | E5: 1 | I5: =1/J5 -> 4 | J5: 0.25
A6: CÓDIGO | B6: INGREDIENTES | D6: CANTIDAD | E6: UNIDAD | F6: EQUIPO Y UTENSILIOS | I6: COSTO NETO | J6: IMPORTE
A7: =VLOOKUP(B7,Base!$A$3:$F$994, 6, false) -> ABA-002 | B7: Azucár | D7: 0.200 | E7: =VLOOKUP(B7,Base!$A$3:$F$994, 2, false) -> Kg | I7: =VLOOKUP(B7,Base!$A$3:$F$994, 5, false) -> 30 | J7: =I7*D7 -> 6
A8: =VLOOKUP(B8,Base!$A$3:$F$994, 6, false) -> ABA-003 | B8: Canela en polvo | D8: 1 | E8: =VLOOKUP(B8,Base!$A$3:$F$994, 2, false) -> Kg | I8: =VLOOKUP(B8,Base!$A$3:$F$994, 5, false) -> 50 | J8: =I8*D8 -> 50
A9: =VLOOKUP(B9,Base!$A$3:$F$994, 6, false) -> ABA-003 | B9: Canela en polvo | D9: .3 | E9: =VLOOKUP(B9,Base!$A$3:$F$994, 2, false) -> Kg | I9: =VLOOKUP(B9,Base!$A$3:$F$994, 5, false) -> 50 | J9: =I9*D9 -> 15
A10: =VLOOKUP(B10,Base!$A$3:$F$994, 6, false) -> ABA-003 | B10: Canela en polvo | D10: .4 | E10: =VLOOKUP(B10,Base!$A$3:$F$994, 2, false) -> Kg | I10: =VLOOKUP(B10,Base!$A$3:$F$994, 5, false) -> 50 | J10: =I10*D10 -> 20
A11: =VLOOKUP(B11,Base!$A$3:$F$994, 6, false) -> 0 | B11: . | E11: =VLOOKUP(B11,Base!$A$3:$F$994, 2, false) -> . | I11: =VLOOKUP(B11,Base!$A$3:$F$994, 5, false) -> 0 | J11: =I11*D11 -> 0
A12: =VLOOKUP(B12,Base!$A$3:$F$994, 6, false) -> 0 | B12: . | E12: =VLOOKUP(B12,Base!$A$3:$F$994, 2, false) -> . | I12: =VLOOKUP(B12,Base!$A$3:$F$994, 5, false) -> 0 | J12: =I12*D12 -> 0
A13: =VLOOKUP(B13,Base!$A$3:$F$994, 6, false) -> 0 | B13: . | E13: =VLOOKUP(B13,Base!$A$3:$F$994, 2, false) -> . | I13: =VLOOKUP(B13,Base!$A$3:$F$994, 5, false) -> 0 | J13: =I13*D13 -> 0
A14: =VLOOKUP(B14,Base!$A$3:$F$994, 6, false) -> 0 | B14: . | E14: =VLOOKUP(B14,Base!$A$3:$F$994, 2, false) -> . | I14: =VLOOKUP(B14,Base!$A$3:$F$994, 5, false) -> 0 | J14: =I14*D14 -> 0
A15: =VLOOKUP(B15,Base!$A$3:$F$994, 6, false) -> 0 | B15: . | E15: =VLOOKUP(B15,Base!$A$3:$F$994, 2, false) -> . | I15: =VLOOKUP(B15,Base!$A$3:$F$994, 5, false) -> 0 | J15: =I15*D15 -> 0
A16: =VLOOKUP(B16,Base!$A$3:$F$994, 6, false) -> 0 | B16: . | E16: =VLOOKUP(B16,Base!$A$3:$F$994, 2, false) -> . | I16: =VLOOKUP(B16,Base!$A$3:$F$994, 5, false) -> 0 | J16: =I16*D16 -> 0
A17: =VLOOKUP(B17,Base!$A$3:$F$994, 6, false) -> 0 | B17: . | E17: =VLOOKUP(B17,Base!$A$3:$F$994, 2, false) -> . | F17: PREPARACIÒN | I17: =VLOOKUP(B17,Base!$A$3:$F$994, 5, false) -> 0 | J17: =I17*D17 -> 0
A18: =VLOOKUP(B18,Base!$A$3:$F$994, 6, false) -> 0 | B18: . | E18: =VLOOKUP(B18,Base!$A$3:$F$994, 2, false) -> . | I18: =VLOOKUP(B18,Base!$A$3:$F$994, 5, false) -> 0 | J18: =I18*D18 -> 0
A19: =VLOOKUP(B19,Base!$A$3:$F$994, 6, false) -> 0 | B19: . | E19: =VLOOKUP(B19,Base!$A$3:$F$994, 2, false) -> . | I19: =VLOOKUP(B19,Base!$A$3:$F$994, 5, false) -> 0 | J19: =I19*D19 -> 0
A20: =VLOOKUP(B20,Base!$A$3:$F$994, 6, false) -> 0 | B20: . | E20: =VLOOKUP(B20,Base!$A$3:$F$994, 2, false) -> . | I20: =VLOOKUP(B20,Base!$A$3:$F$994, 5, false) -> 0 | J20: =I20*D20 -> 0
A21: =VLOOKUP(B21,Base!$A$3:$F$994, 6, false) -> 0 | B21: . | E21: =VLOOKUP(B21,Base!$A$3:$F$994, 2, false) -> . | I21: =VLOOKUP(B21,Base!$A$3:$F$994, 5, false) -> 0 | J21: =I21*D21 -> 0
A22: =VLOOKUP(B22,Base!$A$3:$F$994, 6, false) -> 0 | B22: . | E22: =VLOOKUP(B22,Base!$A$3:$F$994, 2, false) -> . | I22: =VLOOKUP(B22,Base!$A$3:$F$994, 5, false) -> 0 | J22: =I22*D22 -> 0
A23: =VLOOKUP(B23,Base!$A$3:$F$994, 6, false) -> 0 | B23: . | E23: =VLOOKUP(B23,Base!$A$3:$F$994, 2, false) -> . | I23: =VLOOKUP(B23,Base!$A$3:$F$994, 5, false) -> 0 | J23: =I23*D23 -> 0
A24: =VLOOKUP(B24,Base!$A$3:$F$994, 6, false) -> 0 | B24: . | E24: =VLOOKUP(B24,Base!$A$3:$F$994, 2, false) -> . | I24: =VLOOKUP(B24,Base!$A$3:$F$994, 5, false) -> 0 | J24: =I24*D24 -> 0
A25: ELABORACIÒN | I25: TOTAL DE MP: | J25: =SUM(J7:J24) -> 91
I26: TOTAL P/P: | J26: =J25/E5 -> 91
I27: IMPREVISTO: | J27: 0.05
I28: TOTAL DE COSTO: | J28: =J26+(J26*J27) -> 95.55
I29: PRECIO SUGERIDO: | J29: =J28*I5 -> 382.2
I30: IVA: | J30: =J31-J29 -> 61.152
I31: PRECIO SUGERIDO CON IVA: | J31: =J29*(J3*1+1) -> 443.352
I32: AJUSTE A LA CARTA
I33: PRECIO AJUSTADO:
A34: MONTAJE | I34: IVA: | J34: =J33-J35 -> 0
I35: PRECIO AJUSTADO SIN IVA: | J35: =J33/(J3*1+1) -> 0
I36: NUEVO % DE COSTO: | J36: =J28/J35 -> #DIV/0!
I37: NUEVO FACTOR DE VENTA: | J37: =J35/J28 -> 0
A38: OBSERVACIONES
I46: IMPUESTO | J46: =$J$3 -> 0.16
A47: NOMBRE: | F47: FECHA: | G47: =$G$4 -> 42399 | I47: FACTOR DE VENTA | J47: % DE COSTO
A48: CÓDIGO DE RECETA: | B48: 2 | D48: PORCIONES: | E48: 1 | I48: =1/J48 -> 4 | J48: =$J$5 -> 0.25
A49: CÓDIGO | B49: INGREDIENTES | D49: CANTIDAD | E49: UNIDAD | F49: EQUIPO Y UTENSILIOS | I49: COSTO NETO | J49: IMPORTE
A50: =VLOOKUP(B50,Base!$A$3:$F$994, 6, false) -> 0 | B50: . | E50: =VLOOKUP(B50,Base!$A$3:$F$994, 2, false) -> . | I50: =VLOOKUP(B50,Base!$A$3:$F$994, 5, false) -> 0 | J50: =I50*D50 -> 0
A51: =VLOOKUP(B51,Base!$A$3:$F$994, 6, false) -> 0 | B51: . | E51: =VLOOKUP(B51,Base!$A$3:$F$994, 2, false) -> . | I51: =VLOOKUP(B51,Base!$A$3:$F$994, 5, false) -> 0 | J51: =I51*D51 -> 0
A52: =VLOOKUP(B52,Base!$A$3:$F$994, 6, false) -> 0 | B52: . | E52: =VLOOKUP(B52,Base!$A$3:$F$994, 2, false) -> . | I52: =VLOOKUP(B52,Base!$A$3:$F$994, 5, false) -> 0 | J52: =I52*D52 -> 0
A53: =VLOOKUP(B53,Base!$A$3:$F$994, 6, false) -> 0 | B53: . | E53: =VLOOKUP(B53,Base!$A$3:$F$994, 2, false) -> . | I53: =VLOOKUP(B53,Base!$A$3:$F$994, 5, false) -> 0 | J53: =I53*D53 -> 0
A54: =VLOOKUP(B54,Base!$A$3:$F$994, 6, false) -> 0 | B54: . | E54: =VLOOKUP(B54,Base!$A$3:$F$994, 2, false) -> . | I54: =VLOOKUP(B54,Base!$A$3:$F$994, 5, false) -> 0 | J54: =I54*D54 -> 0
A55: =VLOOKUP(B55,Base!$A$3:$F$994, 6, false) -> 0 | B55: . | E55: =VLOOKUP(B55,Base!$A$3:$F$994, 2, false) -> . | I55: =VLOOKUP(B55,Base!$A$3:$F$994, 5, false) -> 0 | J55: =I55*D55 -> 0
A56: =VLOOKUP(B56,Base!$A$3:$F$994, 6, false) -> 0 | B56: . | E56: =VLOOKUP(B56,Base!$A$3:$F$994, 2, false) -> . | I56: =VLOOKUP(B56,Base!$A$3:$F$994, 5, false) -> 0 | J56: =I56*D56 -> 0
A57: =VLOOKUP(B57,Base!$A$3:$F$994, 6, false) -> 0 | B57: . | E57: =VLOOKUP(B57,Base!$A$3:$F$994, 2, false) -> . | I57: =VLOOKUP(B57,Base!$A$3:$F$994, 5, false) -> 0 | J57: =I57*D57 -> 0
A58: =VLOOKUP(B58,Base!$A$3:$F$994, 6, false) -> 0 | B58: . | E58: =VLOOKUP(B58,Base!$A$3:$F$994, 2, false) -> . | I58: =VLOOKUP(B58,Base!$A$3:$F$994, 5, false) -> 0 | J58: =I58*D58 -> 0
A59: =VLOOKUP(B59,Base!$A$3:$F$994, 6, false) -> 0 | B59: . | E59: =VLOOKUP(B59,Base!$A$3:$F$994, 2, false) -> . | I59: =VLOOKUP(B59,Base!$A$3:$F$994, 5, false) -> 0 | J59: =I59*D59 -> 0
A60: =VLOOKUP(B60,Base!$A$3:$F$994, 6, false) -> 0 | B60: . | E60: =VLOOKUP(B60,Base!$A$3:$F$994, 2, false) -> . | F60: PREPARACIÒN | I60: =VLOOKUP(B60,Base!$A$3:$F$994, 5, false) -> 0 | J60: =I60*D60 -> 0
A61: =VLOOKUP(B61,Base!$A$3:$F$994, 6, false) -> 0 | B61: . | E61: =VLOOKUP(B61,Base!$A$3:$F$994, 2, false) -> . | I61: =VLOOKUP(B61,Base!$A$3:$F$994, 5, false) -> 0 | J61: =I61*D61 -> 0
A62: =VLOOKUP(B62,Base!$A$3:$F$994, 6, false) -> 0 | B62: . | E62: =VLOOKUP(B62,Base!$A$3:$F$994, 2, false) -> . | I62: =VLOOKUP(B62,Base!$A$3:$F$994, 5, false) -> 0 | J62: =I62*D62 -> 0
A63: =VLOOKUP(B63,Base!$A$3:$F$994, 6, false) -> 0 | B63: . | E63: =VLOOKUP(B63,Base!$A$3:$F$994, 2, false) -> . | I63: =VLOOKUP(B63,Base!$A$3:$F$994, 5, false) -> 0 | J63: =I63*D63 -> 0
A64: =VLOOKUP(B64,Base!$A$3:$F$994, 6, false) -> 0 | B64: . | E64: =VLOOKUP(B64,Base!$A$3:$F$994, 2, false) -> . | I64: =VLOOKUP(B64,Base!$A$3:$F$994, 5, false) -> 0 | J64: =I64*D64 -> 0
A65: =VLOOKUP(B65,Base!$A$3:$F$994, 6, false) -> 0 | B65: . | E65: =VLOOKUP(B65,Base!$A$3:$F$994, 2, false) -> . | I65: =VLOOKUP(B65,Base!$A$3:$F$994, 5, false) -> 0 | J65: =I65*D65 -> 0
A66: =VLOOKUP(B66,Base!$A$3:$F$994, 6, false) -> 0 | B66: . | E66: =VLOOKUP(B66,Base!$A$3:$F$994, 2, false) -> . | I66: =VLOOKUP(B66,Base!$A$3:$F$994, 5, false) -> 0 | J66: =I66*D66 -> 0
A67: =VLOOKUP(B67,Base!$A$3:$F$994, 6, false) -> 0 | B67: . | E67: =VLOOKUP(B67,Base!$A$3:$F$994, 2, false) -> . | I67: =VLOOKUP(B67,Base!$A$3:$F$994, 5, false) -> 0 | J67: =I67*D67 -> 0
A68: ELABORACIÒN | I68: TOTAL DE MP: | J68: =SUM(J50:J67) -> 0
I69: TOTAL P/P: | J69: =J68/E48 -> 0
I70: IMPREVISTO: | J70: 0.05
I71: TOTAL DE COSTO: | J71: =J69+(J69*J70) -> 0
I72: PRECIO SUGERIDO: | J72: =J71*I48 -> 0
I73: IVA: | J73: =J74-J72 -> 0
I74: PRECIO SUGERIDO CON IVA: | J74: =J72*(J46*1+1) -> 0
I75: AJUSTE A LA CARTA
I76: PRECIO AJUSTADO:
A77: MONTAJE | I77: IVA: | J77: =J76-J78 -> 0
I78: PRECIO AJUSTADO SIN IVA: | J78: =J76/(J46*1+1) -> 0
I79: NUEVO % DE COSTO: | J79: =J71/J78 -> #DIV/0!
I80: NUEVO FACTOR DE VENTA: | J80: =J78/J71 -> #DIV/0!
A81: OBSERVACIONES
I89: IMPUESTO | J89: =$J$3 -> 0.16
A90: NOMBRE: | F90: FECHA: | G90: =$G$4 -> 42399 | I90: FACTOR DE VENTA | J90: % DE COSTO
A91: CÓDIGO DE RECETA: | B91: 3 | D91: PORCIONES: | E91: 1 | I91: =1/J91 -> 4 | J91: =$J$5 -> 0.25
A92: CÓDIGO | B92: INGREDIENTES | D92: CANTIDAD | E92: UNIDAD | F92: EQUIPO Y UTENSILIOS | I92: COSTO NETO | J92: IMPORTE
A93: =VLOOKUP(B93,Base!$A$3:$F$994, 6, false) -> 0 | B93: . | E93: =VLOOKUP(B93,Base!$A$3:$F$994, 2, false) -> . | I93: =VLOOKUP(B93,Base!$A$3:$F$994, 5, false) -> 0 | J93: =I93*D93 -> 0
A94: =VLOOKUP(B94,Base!$A$3:$F$994, 6, false) -> 0 | B94: . | E94: =VLOOKUP(B94,Base!$A$3:$F$994, 2, false) -> . | I94: =VLOOKUP(B94,Base!$A$3:$F$994, 5, false) -> 0 | J94: =I94*D94 -> 0
A95: =VLOOKUP(B95,Base!$A$3:$F$994, 6, false) -> 0 | B95: . | E95: =VLOOKUP(B95,Base!$A$3:$F$994, 2, false) -> . | I95: =VLOOKUP(B95,Base!$A$3:$F$994, 5, false) -> 0 | J95: =I95*D95 -> 0
A96: =VLOOKUP(B96,Base!$A$3:$F$994, 6, false) -> 0 | B96: . | E96: =VLOOKUP(B96,Base!$A$3:$F$994, 2, false) -> . | I96: =VLOOKUP(B96,Base!$A$3:$F$994, 5, false) -> 0 | J96: =I96*D96 -> 0
A97: =VLOOKUP(B97,Base!$A$3:$F$994, 6, false) -> 0 | B97: . | E97: =VLOOKUP(B97,Base!$A$3:$F$994, 2, false) -> . | I97: =VLOOKUP(B97,Base!$A$3:$F$994, 5, false) -> 0 | J97: =I97*D97 -> 0
A98: =VLOOKUP(B98,Base!$A$3:$F$994, 6, false) -> 0 | B98: . | E98: =VLOOKUP(B98,Base!$A$3:$F$994, 2, false) -> . | I98: =VLOOKUP(B98,Base!$A$3:$F$994, 5, false) -> 0 | J98: =I98*D98 -> 0
A99: =VLOOKUP(B99,Base!$A$3:$F$994, 6, false) -> 0 | B99: . | E99: =VLOOKUP(B99,Base!$A$3:$F$994, 2, false) -> . | I99: =VLOOKUP(B99,Base!$A$3:$F$994, 5, false) -> 0 | J99: =I99*D99 -> 0
A100: =VLOOKUP(B100,Base!$A$3:$F$994, 6, false) -> 0 | B100: . | E100: =VLOOKUP(B100,Base!$A$3:$F$994, 2, false) -> . | I100: =VLOOKUP(B100,Base!$A$3:$F$994, 5, false) -> 0 | J100: =I100*D100 -> 0
A101: =VLOOKUP(B101,Base!$A$3:$F$994, 6, false) -> 0 | B101: . | E101: =VLOOKUP(B101,Base!$A$3:$F$994, 2, false) -> . | I101: =VLOOKUP(B101,Base!$A$3:$F$994, 5, false) -> 0 | J101: =I101*D101 -> 0
A102: =VLOOKUP(B102,Base!$A$3:$F$994, 6, false) -> 0 | B102: . | E102: =VLOOKUP(B102,Base!$A$3:$F$994, 2, false) -> . | I102: =VLOOKUP(B102,Base!$A$3:$F$994, 5, false) -> 0 | J102: =I102*D102 -> 0
A103: =VLOOKUP(B103,Base!$A$3:$F$994, 6, false) -> 0 | B103: . | E103: =VLOOKUP(B103,Base!$A$3:$F$994, 2, false) -> . | F103: PREPARACIÒN | I103: =VLOOKUP(B103,Base!$A$3:$F$994, 5, false) -> 0 | J103: =I103*D103 -> 0
A104: =VLOOKUP(B104,Base!$A$3:$F$994, 6, false) -> 0 | B104: . | E104: =VLOOKUP(B104,Base!$A$3:$F$994, 2, false) -> . | I104: =VLOOKUP(B104,Base!$A$3:$F$994, 5, false) -> 0 | J104: =I104*D104 -> 0
A105: =VLOOKUP(B105,Base!$A$3:$F$994, 6, false) -> 0 | B105: . | E105: =VLOOKUP(B105,Base!$A$3:$F$994, 2, false) -> . | I105: =VLOOKUP(B105,Base!$A$3:$F$994, 5, false) -> 0 | J105: =I105*D105 -> 0
A106: =VLOOKUP(B106,Base!$A$3:$F$994, 6, false) -> 0 | B106: . | E106: =VLOOKUP(B106,Base!$A$3:$F$994, 2, false) -> . | I106: =VLOOKUP(B106,Base!$A$3:$F$994, 5, false) -> 0 | J106: =I106*D106 -> 0
A107: =VLOOKUP(B107,Base!$A$3:$F$994, 6, false) -> 0 | B107: . | E107: =VLOOKUP(B107,Base!$A$3:$F$994, 2, false) -> . | I107: =VLOOKUP(B107,Base!$A$3:$F$994, 5, false) -> 0 | J107: =I107*D107 -> 0
A108: =VLOOKUP(B108,Base!$A$3:$F$994, 6, false) -> 0 | B108: . | E108: =VLOOKUP(B108,Base!$A$3:$F$994, 2, false) -> . | I108: =VLOOKUP(B108,Base!$A$3:$F$994, 5, false) -> 0 | J108: =I108*D108 -> 0
A109: =VLOOKUP(B109,Base!$A$3:$F$994, 6, false) -> 0 | B109: . | E109: =VLOOKUP(B109,Base!$A$3:$F$994, 2, false) -> . | I109: =VLOOKUP(B109,Base!$A$3:$F$994, 5, false) -> 0 | J109: =I109*D109 -> 0
A110: =VLOOKUP(B110,Base!$A$3:$F$994, 6, false) -> 0 | B110: . | E110: =VLOOKUP(B110,Base!$A$3:$F$994, 2, false) -> . | I110: =VLOOKUP(B110,Base!$A$3:$F$994, 5, false) -> 0 | J110: =I110*D110 -> 0
A111: ELABORACIÒN | I111: TOTAL DE MP: | J111: =SUM(J93:J110) -> 0
I112: TOTAL P/P: | J112: =J111/E91 -> 0
I113: IMPREVISTO: | J113: 0.05
I114: TOTAL DE COSTO: | J114: =J112+(J112*J113) -> 0
...

Sheet Rotación
A1: NOMBRE DEL ESTABLECIMIENTO
B3: Mes | E3: Enero | F3: Febrero | G3: Marzo | H3: Abril | I3: Mayo | J3: Junio | K3: Julio | L3: Agosto | M3: Septiembre | N3: Octubre | O3: Noviembre | P3: Diciembre
B4: Días hábiles | E4: 31 | F4: 28 | G4: 31 | H4: 30 | I4: 31 | J4: 30 | K4: 31 | L4: 30 | M4: 31 | N4: 30 | O4: 31 | P4: 30
B5: Aforo máximo al día | E5: =C19 -> 44 | F5: =C37 -> 44 | G5: =C55 -> 44 | H5: =C73 -> 44 | I5: =C91 -> 44 | J5: =C109 -> 44 | K5: =C127 -> 44 | L5: =C145 -> 44 | M5: =C163 -> 44 | N5: =C181 -> 44 | O5: =C199 -> 44 | P5: =C217 -> 44
B6: Rotación anual por mes
B7: Mes | E7: =E3 -> Enero | F7: =F3 -> Febrero | G7: =G3 -> Marzo | H7: =H3 -> Abril | I7: =I3 -> Mayo | J7: =J3 -> Junio | K7: =K3 -> Julio | L7: =L3 -> Agosto | ... P7: =P3 -> Diciembre | Q7: TOTAL ANUAL | R7: PROMEDIO DE ROTACIÓN
B8: Rotación | E8: =J29 -> 0.60357143 | F8: =J47 -> 0.62857143 | G8: =J65 -> 0.65714286 | H8: =J83 -> 0.72142857 | I8: =J101 -> 0.76428571 | J8: =J119 -> 0.82142857 | K8: =J137 -> 0.83571429 | L8: =J155 -> 0.88571429 | M8: =J173 -> 0.90714286 | N8: =J191 -> 0.90714286 | O8: =J209 -> 0.92142857 | P8: =J227 -> 0.93571429 | R8: =AVERAGEIF(E8:P8,">0") -> 0.79910714
B9: Comensales diarios | E9: =E8*E5 -> 26.557143 | F9: =F8*F5 -> 27.657143 | G9: =G8*G5 -> 28.914286 | H9: =H8*H5 -> 31.742857 | I9: =I8*I5 -> 33.628571 | J9: =J8*J5 -> 36.142857 | K9: =K8*K5 -> 36.771429 | L9: =L8*L5 -> 38.971429 | ... P9: =P8*P5 -> 41.171429 | Q9: =SUM(E9:P9) -> 421.92857
B10: Total de comensales mensuales | E10: =E9*E4 -> 823.27143 | F10: =F9*F4 -> 774.4 | G10: =G9*G4 -> 896.34286 | H10: =H9*H4 -> 952.28571 | I10: =I9*I4 -> 1042.4857 | J10: =J9*J4 -> 1084.2857 | K10: =K9*K4 -> 1139.9143 | L10: =L9*L4 -> 1169.1429 | ... P10: =P9*P4 -> 1235.1429 | Q10: =SUM(E10:P10) -> 12808.871
B12: Porcentaje de operación | E12: =E9/E5 -> 0.60357143 | F12: =F9/F5 -> 0.62857143 | G12: =G9/G5 -> 0.65714286 | H12: =H9/H5 -> 0.72142857 | I12: =I9/I5 -> 0.76428571 | J12: =J9/J5 -> 0.82142857 | K12: =K9/K5 -> 0.83571429 | L12: =L9/L5 -> 0.88571429 | ... P12: =P9/P5 -> 0.93571429 | R12: =R8 -> 0.79910714
F14: =F10-E10 -> -48.871429 | G14: =G10-F10 -> 121.94286 | H14: =H10-G10 -> 55.942857 | I14: =I10-H10 -> 90.2 | J14: =J10-I10 -> 41.8 | K14: =K10-J10 -> 55.628571 | L14: =L10-K10 -> 29.228571 | M14: =M10-L10 -> 68.2 | ... P14: =P10-O10 -> -21.685714 | R14: =P10-E10 -> 411.87143 | S14: =R14/44 -> 9.3607143
B15: CÁLCULO DE ROTACIÓN
B17: Mes | C17: =E3 -> Enero | G17: =700*149 -> 104300
B18: Capacidad máxima por servicio | C18: 22
B19: Aforo máximo al día | C19: 44
C20: Lunes | D20: Martes | E20: Miércoles | F20: Jueves | G20: Viernes | H20: Sábado | I20: Domingo | J20: Total semanal
B21: Desayuno % estimado | I21: 0.6
B22: Comensales desayuno | C22: =C21*$C$18 -> 0 | D22: =D21*$C$18 -> 0 | E22: =E21*$C$18 -> 0 | F22: =F21*$C$18 -> 0 | G22: =G21*$C$18 -> 0 | H22: =H21*$C$18 -> 0 | I22: =I21*$C$18 -> 13.2 | J22: =SUM(C22:I22) -> 13.2
B23: Comidas % estimado | C23: 0.5 | D23: 0.6 | E23: 0.5 | F23: 0.7 | G23: 0.65 | H23: 0.6 | I23: 0.7
B24: Comensales comidas | C24: =C23*$C$18 -> 11 | D24: =D23*$C$18 -> 13.2 | E24: =E23*$C$18 -> 11 | F24: =F23*$C$18 -> 15.4 | G24: =G23*$C$18 -> 14.3 | H24: =H23*$C$18 -> 13.2 | I24: =I23*$C$18 -> 15.4 | J24: =SUM(C24:I24) -> 93.5
B25: Cenas % estimado | C25: 0.5 | D25: 0.6 | E25: 0.5 | F25: 0.7 | G25: 0.6 | H25: 0.7 | I25: 0
B26: comensales cenas | C26: =C25*$C$18 -> 11 | D26: =D25*$C$18 -> 13.2 | E26: =E25*$C$18 -> 11 | F26: =F25*$C$18 -> 15.4 | G26: =G25*$C$18 -> 13.2 | H26: =H25*$C$18 -> 15.4 | J26: =SUM(C26:I26) -> 79.2
B28: Total comensales diarios | C28: =C26+C24+C22 -> 22 | D28: =D26+D24+D22 -> 26.4 | E28: =E26+E24+E22 -> 22 | F28: =F26+F24+F22 -> 30.8 | G28: =G26+G24+G22 -> 27.5 | H28: =H26+H24+H22 -> 28.6 | I28: =I26+I24+I22 -> 28.6 | J28: =SUM(C28:I28) -> 185.9
B29: Rotación diaria | C29: =C28/$C$19 -> 0.5 | D29: =D28/$C$19 -> 0.6 | E29: =E28/$C$19 -> 0.5 | F29: =F28/$C$19 -> 0.7 | G29: =G28/$C$19 -> 0.625 | H29: =H28/$C$19 -> 0.65 | I29: =I28/$C$19 -> 0.65 | J29: =AVERAGEIF(C29:I29,">0") -> 0.60357143
B30: Porcentaje de operación | C30: =C28/$C$19 -> 0.5 | D30: =D28/$C$19 -> 0.6 | E30: =E28/$C$19 -> 0.5 | F30: =F28/$C$19 -> 0.7 | G30: =G28/$C$19 -> 0.625 | H30: =H28/$C$19 -> 0.65 | I30: =I28/$C$19 -> 0.65 | J30: =AVERAGEIF(C30:I30,">0") -> 0.60357143
B35: Mes | C35: =F3 -> Febrero
B36: Capacidad máxima por servicio | C36: 22
B37: Aforo máximo al día | C37: 44
C38: Lunes | D38: Martes | E38: Miércoles | F38: Jueves | G38: Viernes | H38: Sábado | I38: Domingo | J38: Total semanal
B39: Desayuno % estimado | I39: 0.6
B40: Comensales desayuno | C40: =C39*$C$36 -> 0 | D40: =D39*$C$36 -> 0 | E40: =E39*$C$36 -> 0 | F40: =F39*$C$36 -> 0 | G40: =G39*$C$36 -> 0 | H40: =H39*$C$36 -> 0 | I40: =I39*$C$36 -> 13.2 | J40: =SUM(C40:I40) -> 13.2
B41: Comidas % estimado | C41: 0.6 | D41: 0.7 | E41: 0.5 | F41: 0.7 | G41: 0.5 | H41: 0.7 | I41: 0.6
B42: Comensales comidas | C42: =C41*$C$36 -> 13.2 | D42: =D41*$C$36 -> 15.4 | E42: =E41*$C$36 -> 11 | F42: =F41*$C$36 -> 15.4 | G42: =G41*$C$36 -> 11 | H42: =H41*$C$36 -> 15.4 | I42: =I41*$C$36 -> 13.2 | J42: =SUM(C42:I42) -> 94.6
B43: Cenas % estimado | C43: 0.5 | D43: 0.7 | E43: 0.5 | F43: 0.7 | G43: 0.7 | H43: 0.8
B44: comensales cenas | C44: =C43*$C$36 -> 11 | D44: =D43*$C$36 -> 15.4 | E44: =E43*$C$36 -> 11 | F44: =F43*$C$36 -> 15.4 | G44: =G43*$C$36 -> 15.4 | H44: =H43*$C$36 -> 17.6 | I44: =I43*$C$36 -> 0 | J44: =SUM(C44:I44) -> 85.8
B46: Total comensales diarios | C46: =C44+C42+C40 -> 24.2 | D46: =D44+D42+D40 -> 30.8 | E46: =E44+E42+E40 -> 22 | F46: =F44+F42+F40 -> 30.8 | G46: =G44+G42+G40 -> 26.4 | H46: =H44+H42+H40 -> 33 | I46: =I44+I42+I40 -> 26.4 | J46: =SUM(C46:I46) -> 193.6
B47: Rotación diaria | C47: =C46/$C$19 -> 0.55 | D47: =D46/$C$19 -> 0.7 | E47: =E46/$C$19 -> 0.5 | F47: =F46/$C$19 -> 0.7 | G47: =G46/$C$19 -> 0.6 | H47: =H46/$C$19 -> 0.75 | I47: =I46/$C$19 -> 0.6 | J47: =AVERAGEIF(C47:I47,">0") -> 0.62857143
B48: Porcentaje de operación | C48: =C46/$C$19 -> 0.55 | D48: =D46/$C$19 -> 0.7 | E48: =E46/$C$19 -> 0.5 | F48: =F46/$C$19 -> 0.7 | G48: =G46/$C$19 -> 0.6 | H48: =H46/$C$19 -> 0.75 | I48: =I46/$C$19 -> 0.6 | J48: =AVERAGEIF(C48:I48,">0") -> 0.62857143
B53: Mes | C53: =G3 -> Marzo
B54: Capacidad máxima por servicio | C54: 22
B55: Aforo máximo al día | C55: 44
C56: Lunes | D56: Martes | E56: Miércoles | F56: Jueves | G56: Viernes | H56: Sábado | I56: Domingo | J56: Total semanal
B57: Desayuno % estimado | I57: 0.7
B58: Comensales desayuno | C58: =C57*$C$54 -> 0 | D58: =D57*$C$54 -> 0 | E58: =E57*$C$54 -> 0 | F58: =F57*$C$54 -> 0 | G58: =G57*$C$54 -> 0 | H58: =H57*$C$54 -> 0 | I58: =I57*$C$54 -> 15.4 | J58: =SUM(C58:I58) -> 15.4
B59: Comidas % estimado | C59: 0.5 | D59: 0.6 | E59: 0.6 | F59: 0.7 | G59: 0.6 | H59: 0.7 | I59: 0.6
B60: Comensales comidas | C60: =C59*$C$54 -> 11 | D60: =D59*$C$54 -> 13.2 | E60: =E59*$C$54 -> 13.2 | F60: =F59*$C$54 -> 15.4 | G60: =G59*$C$54 -> 13.2 | H60: =H59*$C$54 -> 15.4 | I60: =I59*$C$54 -> 13.2 | J60: =SUM(C60:I60) -> 94.6
B61: Cenas % estimado | C61: 0.6 | D61: 0.7 | E61: 0.7 | F61: 0.8 | G61: 0.7 | H61: 0.7
B62: comensales cenas | C62: =C61*$C$54 -> 13.2 | D62: =D61*$C$54 -> 15.4 | E62: =E61*$C$54 -> 15.4 | F62: =F61*$C$54 -> 17.6 | G62: =G61*$C$54 -> 15.4 | H62: =H61*$C$54 -> 15.4 | I62: =I61*$C$54 -> 0 | J62: =SUM(C62:I62) -> 92.4
B64: Total comensales diarios | C64: =C62+C60+C58 -> 24.2 | D64: =D62+D60+D58 -> 28.6 | E64: =E62+E60+E58 -> 28.6 | F64: =F62+F60+F58 -> 33 | G64: =G62+G60+G58 -> 28.6 | H64: =H62+H60+H58 -> 30.8 | I64: =I62+I60+I58 -> 28.6 | J64: =SUM(C64:I64) -> 202.4
B65: Rotación diaria | C65: =C64/$C$19 -> 0.55 | D65: =D64/$C$19 -> 0.65 | E65: =E64/$C$19 -> 0.65 | F65: =F64/$C$19 -> 0.75 | G65: =G64/$C$19 -> 0.65 | H65: =H64/$C$19 -> 0.7 | I65: =I64/$C$19 -> 0.65 | J65: =AVERAGEIF(C65:I65,">0") -> 0.65714286
B66: Porcentaje de operación | C66: =C64/$C$19 -> 0.55 | D66: =D64/$C$19 -> 0.65 | E66: =E64/$C$19 -> 0.65 | F66: =F64/$C$19 -> 0.75 | G66: =G64/$C$19 -> 0.65 | H66: =H64/$C$19 -> 0.7 | I66: =I64/$C$19 -> 0.65 | J66: =AVERAGEIF(C66:I66,">0") -> 0.65714286
B71: Mes | C71: =H3 -> Abril
B72: Capacidad máxima por servicio | C72: 22
B73: Aforo máximo al día | C73: 44
C74: Lunes | D74: Martes | E74: Miércoles | F74: Jueves | G74: Viernes | H74: Sábado | I74: Domingo | J74: Total semanal
B75: Desayuno % estimado | I75: 0.7
B76: Comensales desayuno | I76: =I75*$C$72 -> 15.4 | J76: =SUM(C76:I76) -> 15.4
B77: Comidas % estimado | C77: 0.5 | D77: 0.6 | E77: 0.6 | F77: 0.7 | G77: 0.7 | H77: 0.8 | I77: 0.7
B78: Comensales comidas | C78: =C77*$C$72 -> 11 | D78: =D77*$C$72 -> 13.2 | E78: =E77*$C$72 -> 13.2 | F78: =F77*$C$72 -> 15.4 | G78: =G77*$C$72 -> 15.4 | H78: =H77*$C$72 -> 17.6 | I78: =I77*$C$72 -> 15.4 | J78: =SUM(C78:I78) -> 101.2
B79: Cenas % estimado | C79: 0.6 | D79: 0.7 | E79: 0.7 | F79: 0.8 | G79: 1 | H79: 1
B80: comensales cenas | C80: =C79*$C$72 -> 13.2 | D80: =D79*$C$72 -> 15.4 | E80: =E79*$C$72 -> 15.4 | F80: =F79*$C$72 -> 17.6 | G80: =G79*$C$72 -> 22 | H80: =H79*$C$72 -> 22 | J80: =SUM(C80:I80) -> 105.6
B82: Total comensales diarios | C82: =C80+C78+C76 -> 24.2 | D82: =D80+D78+D76 -> 28.6 | E82: =E80+E78+E76 -> 28.6 | F82: =F80+F78+F76 -> 33 | G82: =G80+G78+G76 -> 37.4 | H82: =H80+H78+H76 -> 39.6 | I82: =I80+I78+I76 -> 30.8 | J82: =SUM(C82:I82) -> 222.2
B83: Rotación diaria | C83: =C82/$C$19 -> 0.55 | D83: =D82/$C$19 -> 0.65 | E83: =E82/$C$19 -> 0.65 | F83: =F82/$C$19 -> 0.75 | G83: =G82/$C$19 -> 0.85 | H83: =H82/$C$19 -> 0.9 | I83: =I82/$C$19 -> 0.7 | J83: =AVERAGEIF(C83:I83,">0") -> 0.72142857
B84: Porcentaje de operación | C84: =C82/$C$19 -> 0.55 | D84: =D82/$C$19 -> 0.65 | E84: =E82/$C$19 -> 0.65 | F84: =F82/$C$19 -> 0.75 | G84: =G82/$C$19 -> 0.85 | H84: =H82/$C$19 -> 0.9 | I84: =I82/$C$19 -> 0.7 | J84: =AVERAGEIF(C84:I84,">0") -> 0.72142857
B89: Mes | C89: =I3 -> Mayo
B90: Capacidad máxima por servicio | C90: 22
B91: Aforo máximo al día | C91: 44
C92: Lunes | D92: Martes | E92: Miércoles | F92: Jueves | G92: Viernes | H92: Sábado | I92: Domingo | J92: Total semanal
B93: Desayuno % estimado | I93: 0.7
B94: Comensales desayuno | I94: =I93*C90 -> 15.4 | J94: =SUM(C94:I94) -> 15.4
B95: Comidas % estimado | C95: 0.6 | D95: 0.6 | E95: 0.6 | F95: 0.7 | G95: 0.7 | H95: 0.8 | I95: 0.7
B96: Comensales comidas | C96: =C95*$C$90 -> 13.2 | D96: =D95*$C$90 -> 13.2 | E96: =E95*$C$90 -> 13.2 | F96: =F95*$C$90 -> 15.4 | G96: =G95*$C$90 -> 15.4 | H96: =H95*$C$90 -> 17.6 | I96: =I95*$C$90 -> 15.4 | J96: =SUM(C96:I96) -> 103.4
B97: Cenas % estimado | C97: 0.8 | D97: 0.7 | E97: 0.8 | F97: 0.7 | G97: 1.1 | H97: 1.2
B98: comensales cenas | C98: =C97*$C$90 -> 17.6 | D98: =D97*$C$90 -> 15.4 | E98: =E97*$C$90 -> 17.6 | F98: =F97*$C$90 -> 15.4 | G98: =G97*$C$90 -> 24.2 | H98: =H97*$C$90 -> 26.4 | I98: =I97*$C$90 -> 0 | J98: =SUM(C98:I98) -> 116.6
B100: Total comensales diarios | C100: =C98+C96+C94 -> 30.8 | D100: =D98+D96+D94 -> 28.6 | E100: =E98+E96+E94 -> 30.8 | F100: =F98+F96+F94 -> 30.8 | G100: =G98+G96+G94 -> 39.6 | H100: =H98+H96+H94 -> 44 | I100: =I98+I96+I94 -> 30.8 | J100: =SUM(C100:I100) -> 235.4
B101: Rotación diaria | C101: =C100/$C$19 -> 0.7 | D101: =D100/$C$19 -> 0.65 | E101: =E100/$C$19 -> 0.7 | F101: =F100/$C$19 -> 0.7 | G101: =G100/$C$19 -> 0.9 | H101: =H100/$C$19 -> 1 | I101: =I100/$C$19 -> 0.7 | J101: =AVERAGEIF(C101:I101,">0") -> 0.76428571
B102: Porcentaje de operación | C102: =C100/$C$19 -> 0.7 | D102: =D100/$C$19 -> 0.65 | E102: =E100/$C$19 -> 0.7 | F102: =F100/$C$19 -> 0.7 | G102: =G100/$C$19 -> 0.9 | H102: =H100/$C$19 -> 1 | I102: =I100/$C$19 -> 0.7 | J102: =AVERAGEIF(C102:I102,">0") -> 0.76428571
B107: Mes | C107: =J3 -> Junio
B108: Capacidad máxima por servicio | C108: 22
B109: Aforo máximo al día | C109: 44
C110: Lunes | D110: Martes | E110: Miércoles | F110: Jueves | G110: Viernes | H110: Sábado | I110: Domingo | J110: Total semanal
B111: Desayuno % estimado | I111: 0.8
B112: Comensales desayuno | I112: =I111*C108 -> 17.6 | J112: =SUM(C112:I112) -> 17.6
B113: Comidas % estimado | C113: 0.6 | D113: 0.7 | E113: 0.7 | F113: 0.8 | G113: 0.8 | H113: 1 | I113: 0.8
B114: Comensales comidas | C114: =C113*$C$108 -> 13.2 | D114: =D113*$C$108 -> 15.4 | E114: =E113*$C$108 -> 15.4 | F114: =F113*$C$108 -> 17.6 | G114: =G113*$C$108 -> 17.6 | H114: =H113*$C$108 -> 22 | I114: =I113*$C$108 -> 17.6 | J114: =SUM(C114:I114) -> 118.8
B115: Cenas % estimado | C115: 0.7 | D115: 0.7 | E115: 0.7 | F115: 1.1 | G115: 1 | H115: 1.1
B116: comensales cenas | C116: =C115*$C$108 -> 15.4 | D116: =D115*$C$108 -> 15.4 | E116: =E115*$C$108 -> 15.4 | F116: =F115*$C$108 -> 24.2 | G116: =G115*$C$108 -> 22 | H116: =H115*$C$108 -> 24.2 | J116: =SUM(C116:I116) -> 116.6
B118: Total comensales diarios | C118: =C116+C114+C112 -> 28.6 | D118: =D116+D114+D112 -> 30.8 | E118: =E116+E114+E112 -> 30.8 | F118: =F116+F114+F112 -> 41.8 | G118: =G116+G114+G112 -> 39.6 | H118: =H116+H114+H112 -> 46.2 | I118: =I116+I114+I112 -> 35.2 | J118: =SUM(C118:I118) -> 253
B119: Rotación diaria | C119: =C118/$C$19 -> 0.65 | D119: =D118/$C$19 -> 0.7 | E119: =E118/$C$19 -> 0.7 | F119: =F118/$C$19 -> 0.95 | G119: =G118/$C$19 -> 0.9 | H119: =H118/$C$19 -> 1.05 | I119: =I118/$C$19 -> 0.8 | J119: =AVERAGEIF(C119:I119,">0") -> 0.82142857
B120: Porcentaje de operación | C120: =C118/$C$19 -> 0.65 | D120: =D118/$C$19 -> 0.7 | E120: =E118/$C$19 -> 0.7 | F120: =F118/$C$19 -> 0.95 | G120: =G118/$C$19 -> 0.9 | H120: =H118/$C$19 -> 1.05 | I120: =I118/$C$19 -> 0.8 | J120: =AVERAGEIF(C120:I120,">0") -> 0.82142857
B125: Mes | C125: =K3 -> Julio
B126: Capacidad máxima por servicio | C126: 22
B127: Aforo máximo al día | C127: 44
C128: Lunes | D128: Martes | E128: Miércoles | F128: Jueves | G128: Viernes | H128: Sábado | I128: Domingo | J128: Total semanal
B129: Desayuno % estimado | I129: 0.9
B130: Comensales desayuno | I130: =I129*C126 -> 19.8 | J130: =SUM(C130:I130) -> 19.8
B131: Comidas % estimado | C131: 0.6 | D131: 0.5 | E131: 1 | F131: 1.2 | G131: 0.5 | H131: 0.6 | I131: 0.8
B132: Comensales comidas | C132: =C131*$C$126 -> 13.2 | D132: =D131*$C$126 -> 11 | E132: =E131*$C$126 -> 22 | F132: =F131*$C$126 -> 26.4 | G132: =G131*$C$126 -> 11 | H132: =H131*$C$126 -> 13.2 | I132: =I131*$C$126 -> 17.6 | J132: =SUM(C132:I132) -> 114.4
B133: Cenas % estimado | C133: 0.6 | D133: 1 | E133: 0.7 | F133: 1 | G133: 1.1 | H133: 1.2
B134: comensales cenas | C134: =C133*$C$126 -> 13.2 | D134: =D133*$C$126 -> 22 | E134: =E133*$C$126 -> 15.4 | F134: =F133*$C$126 -> 22 | G134: =G133*$C$126 -> 24.2 | H134: =H133*$C$126 -> 26.4 | I134: =I133*$C$126 -> 0 | J134: =SUM(C134:I134) -> 123.2
...

Sheet PRONOSTICO DE ALIMENTOS
A1: NOMBRE DEL ESTABLECIMIENTO
A2: PRONÓSTICO DE VENTAS DE ALIMENTOS
B4: INFORMACIÓN GENERAL | E4: AFORO DIARIO | F4: =C8 -> 26.557143 | G4: # PLATILLOS | H4: AJUSTE
B5: MES: | C5: ='Rotación'!C17 -> Enero | E5: Primer tiempo | F5: 2 | G5: =F5*F4 -> 53.114286 | H5: 65
B6: Aforo Máximo al Día | C6: ='Rotación'!E5 -> 44
B7: Rotación | C7: ='Rotación'!E8 -> 0.60357143
B8: No. de Comensales Promedio Diarios | C8: =C7*C6 -> 26.557143
B9: No. de Comensales Promedio al Mes | C9: =C8*C10 -> 823.27143
B10: Días Hábiles al Mes | C10: ='Rotación'!E4 -> 31
B11: Cheque Promedio de Alimentos S/IVA | C11: =J111/C9 -> 363.56217 | H11: =SUM(H5:H10) -> 65 | I11: =H11/F4 -> 2.4475524
B12: Porcentaje de Costo de Venta de Alimentos | C12: =K111 -> 0.31382143
A14: CÓDIGO DE RECETA | B14: PLATILLO | C14: ESTIMACIÓN POR DÍA | D14: VECES DE RECETA | E14: TOTAL DE COSTO | F14: TOTAL DE COSTO DIARIO | G14: TOTAL DE COSTO MENSUAL | H14: PRECIO AJUSTADO SIN IVA | I14: VENTA DIARA | J14: VENTA MENSUAL | K14: PORCENTAJE DE COSTO
B15: Sándwich pollo | C15: 4 | D15: =C15/10 -> 0.4 | E15: 60 | F15: =E15*C15 -> 240 | G15: =F15*$C$10 -> 7440 | H15: =M15/1.16 -> 181.03448 | I15: =H15*C15 -> 724.13793 | J15: =I15*$C$10 -> 22448.276 | K15: =G15/J15 -> 0.33142857 | M15: 210
B16: Sándwich cordero | C16: 3 | D16: =C16/10 -> 0.3 | E16: =1200/10 -> 120 | F16: =E16*C16 -> 360 | G16: =F16*$C$10 -> 11160 | H16: =M16/1.16 -> 327.58621 | I16: =H16*C16 -> 982.75862 | J16: =I16*$C$10 -> 30465.517 | K16: =G16/J16 -> 0.36631579 | M16: 380
B17: Sándwich picanha | C17: 3 | D17: =C17/10 -> 0.3 | E17: =1100/10 -> 110 | F17: =E17*C17 -> 330 | G17: =F17*$C$10 -> 10230 | H17: =M17/1.16 -> 258.62069 | I17: =H17*C17 -> 775.86207 | J17: =I17*$C$10 -> 24051.724 | K17: =G17/J17 -> 0.42533333 | M17: 300
B18: Sándwich pescado | C18: 4 | D18: =C18/10 -> 0.4 | E18: =800/10 -> 80 | F18: =E18*C18 -> 320 | G18: =F18*$C$10 -> 9920 | H18: =M18/1.16 -> 232.75862 | I18: =H18*C18 -> 931.03448 | J18: =I18*$C$10 -> 28862.069 | K18: =G18/J18 -> 0.3437037 | M18: 270
B19: Sándwich pork belly | C19: 4 | D19: =C19/10 -> 0.4 | E19: =700/10 -> 70 | F19: =E19*C19 -> 280 | G19: =F19*$C$10 -> 8680 | H19: =M19/1.16 -> 250 | I19: =H19*C19 -> 1000 | J19: =I19*$C$10 -> 31000 | K19: =G19/J19 -> 0.28 | M19: 290
B20: Tosta hongos | C20: 5 | D20: =C20/10 -> 0.5 | E20: =800/10 -> 80 | F20: =E20*C20 -> 400 | G20: =F20*$C$10 -> 12400 | H20: =M20/1.16 -> 232.75862 | I20: =H20*C20 -> 1163.7931 | J20: =I20*$C$10 -> 36077.586 | K20: =G20/J20 -> 0.3437037 | M20: 270
B21: Bollo veggie | C21: 5 | D21: =C21/10 -> 0.5 | E21: =450/10 -> 45 | F21: =E21*C21 -> 225 | G21: =F21*$C$10 -> 6975 | H21: =M21/1.16 -> 155.17241 | I21: =H21*C21 -> 775.86207 | J21: =I21*$C$10 -> 24051.724 | K21: =G21/J21 -> 0.29 | M21: 180
B22: Croquetas cordero | C22: 3 | D22: =C22/10 -> 0.3 | E22: =300/10 -> 30 | F22: =E22*C22 -> 90 | G22: =F22*$C$10 -> 2790 | H22: =M22/1.16 -> 146.55172 | I22: =H22*C22 -> 439.65517 | J22: =I22*$C$10 -> 13629.31 | K22: =G22/J22 -> 0.20470588 | M22: 170
B23: Croquetas camarón y cazón | C23: 5 | D23: =C23/10 -> 0.5 | E23: =350/10 -> 35 | F23: =E23*C23 -> 175 | G23: =F23*$C$10 -> 5425 | H23: =M23/1.16 -> 146.55172 | I23: =H23*C23 -> 732.75862 | J23: =I23*$C$10 -> 22715.517 | K23: =G23/J23 -> 0.23882353 | M23: 170
